Workbook
Name VK: 'Virgin Stock'!$A$2:$I$501
Name SK: 'Semi Stock'!$A$2:$I$501
Name VIRGIN: 'Virgin Stock'!$B$2:$J$501
Name SKP: Semi!$A$4:$I$520
Name semi: Semi!$B$3:$BZ$7
Name vksearch: Virgin!$A$4:$J$16
Name SK: Semi!$A$2:$I$520
Name ITEMLIST: 'FG Stock'!$B:$B
Name vksearch: 'Virgin Stock'!$A$6:$J$501
Name semi: 'Semi Stock'!$B$3:$K$10
Name FILTER: #REF!
Name SEMIKRAFT: Semi!$B$2:$J$520
Name __xludf.DUMMYFUNCTION: #REF!
Name sksearch: Semi!$A$4:$J$520
Name VIRGIN: Virgin!$B$2:$J$16
Name FG: WFG!$B$2:$G$418
Name FG: 'FG Stock'!$B$2:$G$540
Name SEMIKRAFT: 'Semi Stock'!$B$2:$J$501
Name ITEMLIST: WFG!$B:$B
Name VK: Virgin!$A$2:$I$16
Name sksearch: 'Semi Stock'!$A$5:$J$501
Name SKP: 'Semi Stock'!$A$5:$I$501

Sheet MR
A1: PROFIT & LOSS REPORT FOR THE M/O JULY, 2026
B2: OPENING | D2: PURCHASE | F2: CONSUMPTION | H2: CLOSING
A3: PAPER | B3: Opn Stock | C3: Opn Amt | D3: Purchase Qty | E3: Purchase Amt | F3: Consumption Qty | G3: Consumption Amt | H3: Closing Qty | I3: Closing Amt
A4: Semi Kraft | B4: =Semi!F1 -> 46016 | C4: =Semi!BV1 -> 1242115.4 | D4: =Semi!G1 -> 2215 | E4: =Semi!BW1 -> 64933.5 | F4: =Semi!H1 -> 9606 | G4: =Semi!BX1 -> 303896.68 | H4: =Semi!I1 -> 38625 | I4: =Semi!BY1 -> 1242115.4
A5: Virgin Kraft | B5: =Virgin!F1 -> 63229 | C5: =Virgin!BV1 -> 2365180.8 | D5: =Virgin!G1 -> 5037 | E5: =Virgin!BW1 -> 14872 | F5: =Virgin!H1 -> 18476 | G5: =Virgin!BX1 -> 542957.75 | H5: =Virgin!I1 -> 49790 | I5: =Virgin!BY1 -> 1837095
A6: Chennai | B6: =Dup!F1 -> 2251 | C6: =Dup!BU1 -> 135850.5 | D6: =Dup!G1 -> 0 | E6: =Dup!BV1 -> 0 | F6: =Dup!H1 -> 0 | G6: =Dup!BW1 -> 0 | H6: =Dup!I1 -> 2251 | I6: =Dup!BX1 -> 135850.5
B8: =B4+B5+B6+B7 -> 111496 | C8: =C4+C5+C6+C7 -> 3743146.6 | D8: =D4+D5+D6+D7 -> 7252 | E8: =E4+E5+E6+E7 -> 79805.5 | F8: =F4+F5+F6+F7 -> 28082 | G8: =G4+G5+G6+G7 -> 846854.43 | H8: =H4+H5+H6+H7 -> 90666 | I8: =I4+I5+I6+I7 -> 3215060.9
A10: TOTAL SALE | F10: Without GST | G10: With GST | H10: Difference
B11: Without GST | C11: With GST | E11: Paper Used | F11: =G8 -> 846854.43 | G11: =F11+(F11*18%) -> 999288.23 | H11: Without GST | I11: With GST
A12: =Summarry!B23 -> Diya Industries | B12: =Summarry!C23 | C12: =B12*(B12*18%) -> 0 | E12: =A12 -> Diya Industries | F12: =Summarry!D23 -> 39905 | G12: =F12+(F12*18%) -> 47087.9 | H12: =B12-F12 -> -39905 | I12: =C12-G12 -> -47087.9
A13: =Summarry!B24 -> PACKAGING INDIA | B13: =Summarry!C24 -> 0 | C13: =B13*(B13*18%) -> 0 | E13: =A13 -> PACKAGING INDIA | F13: =Summarry!D24 -> 113884 | G13: =F13+(F13*18%) -> 134383.12 | H13: =B13-F13 -> -113884 | I13: =C13-G13 -> -134383.12
A14: =Summarry!B25 -> RADHE RADHE | B14: =Summarry!C25 | C14: =B14+(B14*18%) -> 0 | E14: =A14 -> RADHE RADHE | F14: =Summarry!D25 | G14: =F14+(F14*18%) -> 0 | H14: =B14-F14 -> 0 | I14: =C14-G14 -> 0
A15: PI | B15: =Summarry!C26 -> 0 | C15: =B15*(B15*18%) -> 0 | E15: =A15 -> PI | F15: =Summarry!D26 | G15: =F15+(F15*5%) -> 0 | H15: =B15-F15 -> 0 | I15: =C15-G15 -> 0
A16: SCRAP(CASH) | B16: =Summarry!C27 -> 524594 | C16: =B16 -> 524594 | E16: SCRAP(CASH) | F16: =Summarry!D27 | G16: =F16+(F16*12%) -> 0 | H16: =B16-F16 -> 524594 | I16: =C16-G16 -> 524594
A17: TALLY DATA | B17: =Summarry!C28 -> 9764926 | C17: =Summarry!D28 -> 10264565 | E17: G. Total Purchase | F17: =F11+F12+F13+F14+F15+F16 -> 1000643.4 | G17: =G11+G12+G13+G14+G15+G16 -> 1180759.2 | H17: =B19-F17 -> 8506364.6 | I17: =C19-G17 -> 8812810.8
A18: CREDIT NOTE | B18: 257918 | C18: 270995 | E18: Bank Charges | H18: =Summarry!C3
A19: NETT SALE | B19: =B17-B18 -> 9507008 | C19: =C17-C18 -> 9993570 | E19: Interest on OD A/c | H19: =Summarry!C4 -> 120154
A20: TOTAL PURCHASE | E20: Freight Outward Charges | H20: =Summarry!C5 -> 237130
B21: Without GST | C21: With GST | E21: Salary with Director Remuneration | H21: =Summarry!C6 -> 282277
A22: Current Month Purchase | B22: =Summarry!C36 | C22: =Summarry!D36 | E22: Client Welfare / Commission | H22: =Summarry!C7
E23: Staff Welfare & Pantry Exp. | H23: =Summarry!C8 -> 0
E24: Freight Inward Charges | H24: =Summarry!C9 -> 15500
E25: Conveyance & Bike Petrol Expense | H25: =Summarry!C10 -> 1040
E26: AMC Charges and Factory Insurance Exp | H26: =Summarry!C11 -> 9500
A27: TOTAL SCRAP RATIO ON CONSUMPTION | E27: Machine Exp | H27: =Summarry!C12 -> 16394
E28: Factory Rent Exp | H28: =Summarry!C13 -> 199000
E29: Plant Exp | H29: =Summarry!C14
E30: Office & Stationery Exp | H30: =Summarry!C15 -> 4890
E31: Legal Expenses | H31: =Summarry!C16 -> 3000
E32: DG Diesel | H32: =Summarry!C17 -> 30000
A33: Finish Goods Stock | C33: =Summarry!C29 -> 1492974.7 | E33: DG Rent | H33: =Summarry!C18 -> 12000
A34: Non-Moving Stock | C34: =Summarry!C30 -> 1470807.7 | E34: Electricity Bill | H34: =Summarry!C19 -> 122280
A35: Work in Process Stock | C35: =Summarry!C31 -> 1341382.4 | E35: LPG Cylinder | H35: =Summarry!C20 -> 0
A36: Paper Stock | C36: =Summarry!C32+Summarry!C33+Summarry!C34 -> 3215060.9 | E36: Forklift Diesel | H36: =Summarry!C21 -> 0
A37: Raw material Stock | C37: =Summarry!C35 -> 375402.88 | E37: Consumable Goods (Excl. Gas) | H37: =Summarry!C22 -> 433075 | I37: =H18+H19+H20+H21+H22+H23+H24+H25+H26+H27+H28+H29+H30+H31+H32+H33+H34+H35+H36+H37 -> 1486240
A38: Grand Total Stock | C38: =C33+C34+C35+C36+C37 -> 7895628.5 | E38: NET PROFIT | H38: =H17-I37 -> 7020124.6

Sheet Summarry
A1: PACKWELL INDIA DETAILS FOR MONTHLY REPORT
A2: S. No. | B2: Particulars | C2: Expenses Amount | F2: AUG | G2: Employee | H2: DIARY & Refreshment | I2: Employee Dinner | J2: 70 | K2: DG | L2: Forklift
A3: 1 | B3: =MR!E18 -> Bank Charges | F3: 1
A4: 2 | B4: =MR!E19 -> Interest on OD A/c | C4: 120154 | F4: 2
A5: 3 | B5: =MR!E20 -> Freight Outward Charges | C5: =Freight!M125 -> 237130 | F5: 3
A6: 4 | B6: =MR!E21 -> Salary with Director Remuneration | C6: =Wages!J51 -> 282277 | F6: 4
A7: 5 | B7: =MR!E22 -> Client Welfare / Commission | F7: 5
A8: 6 | B8: =MR!E23 -> Staff Welfare & Pantry Exp. | C8: =J36+H36 -> 0 | F8: 6
A9: 7 | B9: =MR!E24 -> Freight Inward Charges | C9: =6000+9500 -> 15500 | F9: 7
A10: 8 | B10: =MR!E25 -> Conveyance & Bike Petrol Expense | C10: =840+200 -> 1040 | F10: 8
A11: 9 | B11: =MR!E26 -> AMC Charges and Factory Insurance Exp | C11: =4000+2500+3000 -> 9500 | F11: 9
A12: 10 | B12: =MR!E27 -> Machine Exp | C12: 16394 | F12: 10
A13: 11 | B13: =MR!E28 -> Factory Rent Exp | C13: 199000 | F13: 11
A14: 12 | B14: =MR!E29 -> Plant Exp | F14: 12
A15: 13 | B15: =MR!E30 -> Office & Stationery Exp | C15: 4890 | F15: 13
A16: 14 | B16: =MR!E31 -> Legal Expenses | C16: 3000 | F16: 14
A17: 15 | B17: =MR!E32 -> DG Diesel | C17: 30000 | F17: 15
A18: 16 | B18: =MR!E33 -> DG Rent | C18: 12000 | F18: 16
A19: 17 | B19: =MR!E34 -> Electricity Bill | C19: 122280 | F19: 17
A20: 18 | B20: =MR!E35 -> LPG Cylinder | C20: =RM!BT14 -> 0 | F20: 18
A21: 19 | B21: =MR!E36 -> Forklift Diesel | C21: =L36 -> 0 | F21: 19
A22: 20 | B22: =MR!E37 -> Consumable Goods (Excl. Gas) | C22: =RM!BV19 -> 433075 | F22: 20
A23: 21 | B23: Diya Industries | D23: 39905 | F23: 21
A24: 22 | B24: PACKAGING INDIA | C24: 0 | D24: 113884 | F24: 22
A25: 23 | B25: RADHE RADHE | F25: 23
A26: 24 | B26: PACKAGING INDIA | C26: 0 | F26: 24
A27: 25 | B27: SCRAP | C27: =Scrap!E21 -> 524594 | F27: 25
A28: 26 | B28: Sale | C28: 9764926 | D28: 10264565 | F28: 26
A29: 27 | B29: FINISH GOODS | C29: =WFG!BV1 -> 1492974.7 | D29: =C29+C30+C31 -> 4305164.8 | F29: 27
A30: 28 | B30: NON MOVING FINISH GOODS | C30: =DFG!BT1 -> 1470807.7 | F30: 28
A31: 29 | B31: WIP | C31: =WIP!K75 -> 1341382.4 | F31: 29
A32: 30 | B32: Semi Paper Stock | C32: =Semi!BY1 -> 1242115.4 | D32: =C32+C33+C34+C35 -> 3590463.8 | F32: 30
A33: 31 | B33: Virgin Paper Stock | C33: =Virgin!BY1 -> 1837095 | F33: 31 | J33: =I33*J2 -> 0
A34: 32 | B34: Chennai Paper Stock | C34: =Dup!BX1 -> 135850.5 | F34: 32
A35: 33 | B35: Raw Material Stock | C35: =RM!BU1 -> 375402.88 | G35: DIARY | J35: =I35*70 -> 0
A36: 34 | B36: Purchase | F36: Total | G36: =SUM(G3:G35) -> 0 | H36: =SUM(H3:H35) -> 0 | I36: =SUM(I3:I35) -> 0 | J36: =SUM(J3:J35) -> 0 | K36: =SUM(K3:K35) -> 0 | L36: =SUM(L3:L35) -> 0
A37: 35
A38: 36
A39: 37
A40: 38

Sheet Wages
A2: PACKWELL WAGES SHEET FOR THE MONTH OF JULY - 2026 | F2: 31 | H2: 248 | K2: 1 | N2: 2 | Q2: 3 | T2: 4 | W2: 5 | Z2: 6 | AC2: 7 | AF2: 8 | AI2: 9 | AL2: 10 | AO2: 11 | AR2: 12 | AU2: 13 | AX2: 14 | BA2: 15 | BD2: 16 | BG2: 17 | BJ2: 18 | BM2: 19 | BP2: 20 | BS2: 21 | BV2: 22 | BY2: 23 | CB2: 24 | CE2: 25 | CH2: 26 | CK2: 27 | CN2: 28 | CQ2: 29 | CT2: 30 | CW2: 31 | CZ2: 1
A3: S.No. | B3: Employee Name | C3: Designation | D3: Basic Salary | E3: 31 | F3: Days Amount | G3: 248 | H3: OT Amount | I3: Gross Salary | J3: Gross Income | K3: Day's | L3: OT | M3: Gross Salary | N3: Day's Amount | O3: OT Amount | P3: Salary | Q3: Day's | R3: OT | S3: Gross Salary | T3: Day's | U3: OT | V3: Gross Salary | W3: Day's | X3: OT | Y3: Gross Salary | Z3: Day's | AA3: OT | AB3: Gross Salary | AC3: Day's | AD3: OT | AE3: Gross Salary | AF3: Day's | AG3: OT | AH3: Gross Salary | AI3: Day's | AJ3: OT | AK3: Gross Salary | AL3: Day's | AM3: OT | AN3: Gross Salary | AO3: Day's | AP3: OT | AQ3: Gross Salary | AR3: Day's | AS3: OT | AT3: Gross Salary | AU3: Day's | AV3: OT | AW3: Gross Salary | AX3: Day's | AY3: OT | AZ3: Gross Salary | BA3: Day's | BB3: OT | BC3: Gross Salary | BD3: Day's | BE3: OT | BF3: Gross Salary | BG3: Day's | BH3: OT | BI3: Gross Salary | BJ3: Day's | BK3: OT | BL3: Gross Salary | BM3: Day's | BN3: OT | BO3: Gross Salary | BP3: Day's | BQ3: OT | BR3: Gross Salary | BS3: Day's | BT3: OT | BU3: Gross Salary | BV3: Day's | BW3: OT | BX3: Gross Salary | BY3: Day's | BZ3: OT | CA3: Gross Salary | CB3: Day's | CC3: OT | CD3: Gross Salary | CE3: Day's | CF3: OT | CG3: Gross Salary | CH3: Day's | CI3: OT | CJ3: Gross Salary | CK3: Day's | CL3: OT | CM3: Gross Salary | CN3: Day's | CO3: OT | CP3: Gross Salary | CQ3: Day's | CR3: OT | CS3: Gross Salary | CT3: Day's | CU3: OT | CV3: Gross Salary | CW3: Day's | CX3: OT | CY3: Gross Salary | CZ3: Day's | DA3: OT | DB3: Gross Salary
A4: 1 | B4: Mr Jitender Ji | C4: Director | D4: 75000 | E4: =K4+N4+Q4+T4+W4+Z4+AC4+AF4+AI4+AL4+AO4+AR4+AU4+AX4+BA4+BD4+BG4+BJ4+BM4+BP4+BS4+BV4+BY4+CB4+CE4+CH4+CK4+CN4+CQ4+CT4+CW4+CZ4 -> 7 | F4: =ROUND(D4/$F$2*E4,0) -> 16935 | G4: =L4+O4+R4+U4+X4+AA4+AD4+AG4+AJ4+AM4+AP4+AS4+AV4+AY4+BB4+BE4+BH4+BK4+BN4+BQ4+BT4+BW4+BZ4+CC4+CF4+CI4+CL4+CO4+CR4+CU4+CX4+DA4 -> 0 | H4: =ROUND(D4/$H$2*G4,0) -> 0 | I4: =F4+H4 -> 16935 | J4: =M4+P4+S4+V4+Y4+AB4+AE4+AH4+AK4+AN4+AQ4+AT4+AW4+AZ4+BC4+BF4+BI4+BL4+BO4+BR4+BU4+BX4+CA4+CD4+CG4+CJ4+CM4+CP4+CS4+CV4+CY4 -> 16933 | K4: 1 | M4: =ROUND((($D$4/$E$3*K4)+($D$4/$H$2*L4)),0) -> 2419 | N4: 1 | P4: =ROUND(($D$4/$E$3*N4)+($D$4/$H$2*O4),0) -> 2419 | Q4: 1 | S4: =ROUND(($D$4/$E$3*Q4)+($D$4/$H$2*R4),0) -> 2419 | T4: 1 | V4: =ROUND(($D$4/$E$3*T4)+($D$4/$H$2*U4),0) -> 2419 | W4: 1 | Y4: =ROUND(($D$4/$E$3*W4)+($D$4/$H$2*X4),0) -> 2419 | Z4: 1 | AB4: =ROUND(($D$4/$E$3*Z4)+($D$4/$H$2*AA4),0) -> 2419 | AC4: 1 | AE4: =ROUND(($D$4/$E$3*AC4)+($D$4/$H$2*AD4),0) -> 2419 | AH4: =ROUND(($D$4/$E$3*AF4)+($D$4/$H$2*AG4),0) -> 0 | AK4: =ROUND(($D$4/$E$3*AI4)+($D$4/$H$2*AJ4),0) -> 0 | AN4: =ROUND(($D$4/$E$3*AL4)+($D$4/$H$2*AM4),0) -> 0 | AQ4: =ROUND(($D$4/$E$3*AO4)+($D$4/$H$2*AP4),0) -> 0 | AT4: =ROUND(($D$4/$E$3*AR4)+($D$4/$H$2*AS4),0) -> 0 | AW4: =ROUND(($D$4/$E$3*AU4)+($D$4/$H$2*AV4),0) -> 0 | AZ4: =ROUND(($D$4/$E$3*AX4)+($D$4/$H$2*AY4),0) -> 0 | BC4: =ROUND(($D$4/$E$3*BA4)+($D$4/$H$2*BB4),0) -> 0 | BF4: =ROUND(($D$4/$E$3*BD4)+($D$4/$H$2*BE4),0) -> 0 | BI4: =ROUND(($D$4/$E$3*BG4)+($D$4/$H$2*BH4),0) -> 0 | BL4: =ROUND(($D$4/$E$3*BJ4)+($D$4/$H$2*BK4),0) -> 0 | BO4: =ROUND(($D$4/$E$3*BM4)+($D$4/$H$2*BN4),0) -> 0 | BR4: =ROUND(($D$4/$E$3*BP4)+($D$4/$H$2*BQ4),0) -> 0 | BU4: =ROUND(($D$4/$E$3*BS4)+($D$4/$H$2*BT4),0) -> 0 | BX4: =ROUND(($D$4/$E$3*BV4)+($D$4/$H$2*BW4),0) -> 0 | CA4: =ROUND(($D$4/$E$3*BY4)+($D$4/$H$2*BZ4),0) -> 0 | CD4: =ROUND(($D$4/$E$3*CB4)+($D$4/$H$2*CC4),0) -> 0 | CG4: =ROUND(($D$4/$E$3*CE4)+($D$4/$H$2*CF4),0) -> 0 | CJ4: =ROUND(($D$4/$E$3*CH4)+($D$4/$H$2*CI4),0) -> 0 | CM4: =ROUND(($D$4/$E$3*CK4)+($D$4/$H$2*CL4),0) -> 0 | CP4: =ROUND(($D$4/$E$3*CN4)+($D$4/$H$2*CO4),0) -> 0 | CS4: =ROUND(($D$4/$E$3*CQ4)+($D$4/$H$2*CR4),0) -> 0 | CV4: =ROUND(($D$4/$E$3*CT4)+($D$4/$H$2*CU4),0) -> 0 | CY4: =ROUND(($D$4/$E$3*CW4)+($D$4/$H$2*CX4),0) -> 0 | DB4: =ROUND(($D$4/$E$3*CZ4)+($D$4/$H$2*DA4),0) -> 0
A5: 2 | B5: Rajiv Pal | C5: Accounts/HR | D5: 37500 | E5: =K5+N5+Q5+T5+W5+Z5+AC5+AF5+AI5+AL5+AO5+AR5+AU5+AX5+BA5+BD5+BG5+BJ5+BM5+BP5+BS5+BV5+BY5+CB5+CE5+CH5+CK5+CN5+CQ5+CT5+CW5+CZ5 -> 7 | F5: =ROUND(D5/$F$2*E5,0) -> 8468 | G5: =L5+O5+R5+U5+X5+AA5+AD5+AG5+AJ5+AM5+AP5+AS5+AV5+AY5+BB5+BE5+BH5+BK5+BN5+BQ5+BT5+BW5+BZ5+CC5+CF5+CI5+CL5+CO5+CR5+CU5+CX5+DA4 -> 0 | H5: =ROUND(D5/$H$2*G5,0) -> 0 | I5: =F5+H5 -> 8468 | J5: =M5+P5+S5+V5+Y5+AB5+AE5+AH5+AK5+AN5+AQ5+AT5+AW5+AZ5+BC5+BF5+BI5+BL5+BO5+BR5+BU5+BX5+CA5+CD5+CG5+CJ5+CM5+CP5+CS5+CV5+CY5 -> 8470 | K5: 1 | M5: =ROUND(($D$5/$E$3*K5)+($D$5/$H$2*L5),0) -> 1210 | N5: 1 | P5: =ROUND(($D$5/$E$3*N5)+($D$5/$H$2*O5),0) -> 1210 | Q5: 1 | S5: =ROUND(($D$5/$E$3*Q5)+($D$5/$H$2*R5),0) -> 1210 | T5: 1 | V5: =ROUND(($D$5/$E$3*T5)+($D$5/$H$2*U5),0) -> 1210 | W5: 1 | Y5: =ROUND(($D$5/$E$3*W5)+($D$5/$H$2*X5),0) -> 1210 | Z5: 1 | AB5: =ROUND(($D$5/$E$3*Z5)+($D$5/$H$2*AA5),0) -> 1210 | AC5: 1 | AE5: =ROUND(($D$5/$E$3*AC5)+($D$5/$H$2*AD5),0) -> 1210 | AH5: =ROUND(($D$5/$E$3*AF5)+($D$5/$H$2*AG5),0) -> 0 | AK5: =ROUND(($D$5/$E$3*AI5)+($D$5/$H$2*AJ5),0) -> 0 | AN5: =ROUND(($D$5/$E$3*AL5)+($D$5/$H$2*AM5),0) -> 0 | AQ5: =ROUND(($D$5/$E$3*AO5)+($D$5/$H$2*AP5),0) -> 0 | AT5: =ROUND(($D$5/$E$3*AR5)+($D$5/$H$2*AS5),0) -> 0 | AW5: =ROUND(($D$5/$E$3*AU5)+($D$5/$H$2*AV5),0) -> 0 | AZ5: =ROUND(($D$5/$E$3*AX5)+($D$5/$H$2*AY5),0) -> 0 | BC5: =ROUND(($D$5/$E$3*BA5)+($D$5/$H$2*BB5),0) -> 0 | BF5: =ROUND(($D$5/$E$3*BD5)+($D$5/$H$2*BE5),0) -> 0 | BI5: =ROUND(($D$5/$E$3*BG5)+($D$5/$H$2*BH5),0) -> 0 | BL5: =ROUND(($D$5/$E$3*BJ5)+($D$5/$H$2*BK5),0) -> 0 | BO5: =ROUND(($D$5/$E$3*BM5)+($D$5/$H$2*BN5),0) -> 0 | BR5: =ROUND(($D$5/$E$3*BP5)+($D$5/$H$2*BQ5),0) -> 0 | BU5: =ROUND(($D$5/$E$3*BS5)+($D$5/$H$2*BT5),0) -> 0 | BX5: =ROUND(($D$5/$E$3*BV5)+($D$5/$H$2*BW5),0) -> 0 | CA5: =ROUND(($D$5/$E$3*BY5)+($D$5/$H$2*BZ5),0) -> 0 | CD5: =ROUND(($D$5/$E$3*CB5)+($D$5/$H$2*CC5),0) -> 0 | CG5: =ROUND(($D$5/$E$3*CE5)+($D$5/$H$2*CF5),0) -> 0 | CJ5: =ROUND(($D$5/$E$3*CH5)+($D$5/$H$2*CI5),0) -> 0 | CM5: =ROUND(($D$5/$E$3*CK5)+($D$5/$H$2*CL5),0) -> 0 | CP5: =ROUND(($D$5/$E$3*CN5)+($D$5/$H$2*CO5),0) -> 0 | CS5: =ROUND(($D$5/$E$3*CQ5)+($D$5/$H$2*CR5),0) -> 0 | CV5: =ROUND(($D$5/$E$3*CT5)+($D$5/$H$2*CU5),0) -> 0 | CY5: =ROUND(($D$5/$E$3*CW5)+($D$5/$H$2*CX5),0) -> 0 | DB5: =ROUND(($D$5/$E$3*CZ5)+($D$5/$H$2*DA5),0) -> 0
A6: 3 | B6: Shubham Singh | C6: Production Head | D6: 41500 | E6: =K6+N6+Q6+T6+W6+Z6+AC6+AF6+AI6+AL6+AO6+AR6+AU6+AX6+BA6+BD6+BG6+BJ6+BM6+BP6+BS6+BV6+BY6+CB6+CE6+CH6+CK6+CN6+CQ6+CT6+CW6+CZ6 -> 7 | F6: =ROUND(D6/$F$2*E6,0) -> 9371 | G6: =L6+O6+R6+U6+X6+AA6+AD6+AG6+AJ6+AM6+AP6+AS6+AV6+AY6+BB6+BE6+BH6+BK6+BN6+BQ6+BT6+BW6+BZ6+CC6+CF6+CI6+CL6+CO6+CR6+CU6+CX6+DA5 -> 0 | H6: =ROUND(D6/$H$2*G6,0) -> 0 | I6: =F6+H6 -> 9371 | J6: =M6+P6+S6+V6+Y6+AB6+AE6+AH6+AK6+AN6+AQ6+AT6+AW6+AZ6+BC6+BF6+BI6+BL6+BO6+BR6+BU6+BX6+CA6+CD6+CG6+CJ6+CM6+CP6+CS6+CV6+CY6 -> 9373 | K6: 1 | M6: =ROUND(($D$6/$E$3*K6)+($D$6/$H$2*L6),0) -> 1339 | N6: 1 | P6: =ROUND(($D$6/$E$3*N6)+($D$6/$H$2*O6),0) -> 1339 | Q6: 1 | S6: =ROUND(($D$6/$E$3*Q6)+($D$6/$H$2*R6),0) -> 1339 | T6: 1 | V6: =ROUND(($D$6/$E$3*T6)+($D$6/$H$2*U6),0) -> 1339 | W6: 1 | Y6: =ROUND(($D$6/$E$3*W6)+($D$6/$H$2*X6),0) -> 1339 | Z6: 1 | AB6: =ROUND(($D$6/$E$3*Z6)+($D$6/$H$2*AA6),0) -> 1339 | AC6: 1 | AE6: =ROUND(($D$6/$E$3*AC6)+($D$6/$H$2*AD6),0) -> 1339 | AH6: =ROUND(($D$6/$E$3*AF6)+($D$6/$H$2*AG6),0) -> 0 | AK6: =ROUND(($D$6/$E$3*AI6)+($D$6/$H$2*AJ6),0) -> 0 | AN6: =ROUND(($D$6/$E$3*AL6)+($D$6/$H$2*AM6),0) -> 0 | AQ6: =ROUND(($D$6/$E$3*AO6)+($D$6/$H$2*AP6),0) -> 0 | AT6: =ROUND(($D$6/$E$3*AR6)+($D$6/$H$2*AS6),0) -> 0 | AW6: =ROUND(($D$6/$E$3*AU6)+($D$6/$H$2*AV6),0) -> 0 | AZ6: =ROUND(($D$6/$E$3*AX6)+($D$6/$H$2*AY6),0) -> 0 | BC6: =ROUND(($D$6/$E$3*BA6)+($D$6/$H$2*BB6),0) -> 0 | BF6: =ROUND(($D$6/$E$3*BD6)+($D$6/$H$2*BE6),0) -> 0 | BI6: =ROUND(($D$6/$E$3*BG6)+($D$6/$H$2*BH6),0) -> 0 | BL6: =ROUND(($D$6/$E$3*BJ6)+($D$6/$H$2*BK6),0) -> 0 | BO6: =ROUND(($D$6/$E$3*BM6)+($D$6/$H$2*BN6),0) -> 0 | BR6: =ROUND(($D$6/$E$3*BP6)+($D$6/$H$2*BQ6),0) -> 0 | BU6: =ROUND(($D$6/$E$3*BS6)+($D$6/$H$2*BT6),0) -> 0 | BX6: =ROUND(($D$6/$E$3*BV6)+($D$6/$H$2*BW6),0) -> 0 | CA6: =ROUND(($D$6/$E$3*BY6)+($D$6/$H$2*BZ6),0) -> 0 | CD6: =ROUND(($D$6/$E$3*CB6)+($D$6/$H$2*CC6),0) -> 0 | CG6: =ROUND(($D$6/$E$3*CE6)+($D$6/$H$2*CF6),0) -> 0 | CJ6: =ROUND(($D$6/$E$3*CH6)+($D$6/$H$2*CI6),0) -> 0 | CM6: =ROUND(($D$6/$E$3*CK6)+($D$6/$H$2*CL6),0) -> 0 | CP6: =ROUND(($D$6/$E$3*CN6)+($D$6/$H$2*CO6),0) -> 0 | CS6: =ROUND(($D$6/$E$3*CQ6)+($D$6/$H$2*CR6),0) -> 0 | CV6: =ROUND(($D$6/$E$3*CT6)+($D$6/$H$2*CU6),0) -> 0 | CY6: =ROUND(($D$6/$E$3*CW6)+($D$6/$H$2*CX6),0) -> 0 | DB6: =ROUND(($D$6/$E$3*CZ6)+($D$6/$H$2*DA6),0) -> 0
A7: 4 | B7: Raj Kumar | C7: Sup | D7: 40000 | E7: =K7+N7+Q7+T7+W7+Z7+AC7+AF7+AI7+AL7+AO7+AR7+AU7+AX7+BA7+BD7+BG7+BJ7+BM7+BP7+BS7+BV7+BY7+CB7+CE7+CH7+CK7+CN7+CQ7+CT7+CW7+CZ7 -> 7 | F7: =ROUND(D7/$F$2*E7,0) -> 9032 | G7: =L7+O7+R7+U7+X7+AA7+AD7+AG7+AJ7+AM7+AP7+AS7+AV7+AY7+BB7+BE7+BH7+BK7+BN7+BQ7+BT7+BW7+BZ7+CC7+CF7+CI7+CL7+CO7+CR7+CU7+CX7+DA6 -> 0 | H7: =ROUND(D7/$H$2*G7,0) -> 0 | I7: =F7+H7 -> 9032 | J7: =M7+P7+S7+V7+Y7+AB7+AE7+AH7+AK7+AN7+AQ7+AT7+AW7+AZ7+BC7+BF7+BI7+BL7+BO7+BR7+BU7+BX7+CA7+CD7+CG7+CJ7+CM7+CP7+CS7+CV7+CY7 -> 9030 | K7: 1 | M7: =ROUND(($D$7/$E$3*K7)+($D$7/$H$2*L7),0) -> 1290 | N7: 1 | P7: =ROUND(($D$7/$E$3*N7)+($D$7/$H$2*O7),0) -> 1290 | Q7: 1 | S7: =ROUND(($D$7/$E$3*Q7)+($D$7/$H$2*R7),0) -> 1290 | T7: 1 | V7: =ROUND(($D$7/$E$3*T7)+($D$7/$H$2*U7),0) -> 1290 | W7: 1 | Y7: =ROUND(($D$7/$E$3*W7)+($D$7/$H$2*X7),0) -> 1290 | Z7: 1 | AB7: =ROUND(($D$7/$E$3*Z7)+($D$7/$H$2*AA7),0) -> 1290 | AC7: 1 | AE7: =ROUND(($D$7/$E$3*AC7)+($D$7/$H$2*AD7),0) -> 1290 | AH7: =ROUND(($D$7/$E$3*AF7)+($D$7/$H$2*AG7),0) -> 0 | AK7: =ROUND(($D$7/$E$3*AI7)+($D$7/$H$2*AJ7),0) -> 0 | AN7: =ROUND(($D$7/$E$3*AL7)+($D$7/$H$2*AM7),0) -> 0 | AQ7: =ROUND(($D$7/$E$3*AO7)+($D$7/$H$2*AP7),0) -> 0 | AT7: =ROUND(($D$7/$E$3*AR7)+($D$7/$H$2*AS7),0) -> 0 | AW7: =ROUND(($D$7/$E$3*AU7)+($D$7/$H$2*AV7),0) -> 0 | AZ7: =ROUND(($D$7/$E$3*AX7)+($D$7/$H$2*AY7),0) -> 0 | BC7: =ROUND(($D$7/$E$3*BA7)+($D$7/$H$2*BB7),0) -> 0 | BF7: =ROUND(($D$7/$E$3*BD7)+($D$7/$H$2*BE7),0) -> 0 | BI7: =ROUND(($D$7/$E$3*BG7)+($D$7/$H$2*BH7),0) -> 0 | BL7: =ROUND(($D$7/$E$3*BJ7)+($D$7/$H$2*BK7),0) -> 0 | BO7: =ROUND(($D$7/$E$3*BM7)+($D$7/$H$2*BN7),0) -> 0 | BR7: =ROUND(($D$7/$E$3*BP7)+($D$7/$H$2*BQ7),0) -> 0 | BU7: =ROUND(($D$7/$E$3*BS7)+($D$7/$H$2*BT7),0) -> 0 | BX7: =ROUND(($D$7/$E$3*BV7)+($D$7/$H$2*BW7),0) -> 0 | CA7: =ROUND(($D$7/$E$3*BY7)+($D$7/$H$2*BZ7),0) -> 0 | CD7: =ROUND(($D$7/$E$3*CB7)+($D$7/$H$2*CC7),0) -> 0 | CG7: =ROUND(($D$7/$E$3*CE7)+($D$7/$H$2*CF7),0) -> 0 | CJ7: =ROUND(($D$7/$E$3*CH7)+($D$7/$H$2*CI7),0) -> 0 | CM7: =ROUND(($D$7/$E$3*CK7)+($D$7/$H$2*CL7),0) -> 0 | CP7: =ROUND(($D$7/$E$3*CN7)+($D$7/$H$2*CO7),0) -> 0 | CS7: =ROUND(($D$7/$E$3*CQ7)+($D$7/$H$2*CR7),0) -> 0 | CV7: =ROUND(($D$7/$E$3*CT7)+($D$7/$H$2*CU7),0) -> 0 | CY7: =ROUND(($D$7/$E$3*CW7)+($D$7/$H$2*CX7),0) -> 0 | DB7: =ROUND(($D$7/$E$3*CZ7)+($D$7/$H$2*DA7),0) -> 0
A8: 5 | B8: Devesh Chouhan | C8: Lifter/Disp. | D8: 20000 | E8: =K8+N8+Q8+T8+W8+Z8+AC8+AF8+AI8+AL8+AO8+AR8+AU8+AX8+BA8+BD8+BG8+BJ8+BM8+BP8+BS8+BV8+BY8+CB8+CE8+CH8+CK8+CN8+CQ8+CT8+CW8+CZ8 -> 7 | F8: =ROUND(D8/$F$2*E8,0) -> 4516 | G8: =L8+O8+R8+U8+X8+AA8+AD8+AG8+AJ8+AM8+AP8+AS8+AV8+AY8+BB8+BE8+BH8+BK8+BN8+BQ8+BT8+BW8+BZ8+CC8+CF8+CI8+CL8+CO8+CR8+CU8+CX8+DA7 -> 0 | H8: =ROUND(D8/$H$2*G8,0) -> 0 | I8: =F8+H8 -> 4516 | J8: =M8+P8+S8+V8+Y8+AB8+AE8+AH8+AK8+AN8+AQ8+AT8+AW8+AZ8+BC8+BF8+BI8+BL8+BO8+BR8+BU8+BX8+CA8+CD8+CG8+CJ8+CM8+CP8+CS8+CV8+CY8 -> 4515 | K8: 1 | M8: =ROUND(($D$8/$E$3*K8)+($D$8/$H$2*L8),0) -> 645 | N8: 1 | P8: =ROUND(($D$8/$E$3*N8)+($D$8/$H$2*O8),0) -> 645 | Q8: 1 | S8: =ROUND(($D$8/$E$3*Q8)+($D$8/$H$2*R8),0) -> 645 | T8: 1 | V8: =ROUND(($D$8/$E$3*T8)+($D$8/$H$2*U8),0) -> 645 | W8: 1 | Y8: =ROUND(($D$8/$E$3*W8)+($D$8/$H$2*X8),0) -> 645 | Z8: 1 | AB8: =ROUND(($D$8/$E$3*Z8)+($D$8/$H$2*AA8),0) -> 645 | AC8: 1 | AE8: =ROUND(($D$8/$E$3*AC8)+($D$8/$H$2*AD8),0) -> 645 | AH8: =ROUND(($D$8/$E$3*AF8)+($D$8/$H$2*AG8),0) -> 0 | AK8: =ROUND(($D$8/$E$3*AI8)+($D$8/$H$2*AJ8),0) -> 0 | AN8: =ROUND(($D$8/$E$3*AL8)+($D$8/$H$2*AM8),0) -> 0 | AQ8: =ROUND(($D$8/$E$3*AO8)+($D$8/$H$2*AP8),0) -> 0 | AT8: =ROUND(($D$8/$E$3*AR8)+($D$8/$H$2*AS8),0) -> 0 | AW8: =ROUND(($D$8/$E$3*AU8)+($D$8/$H$2*AV8),0) -> 0 | AZ8: =ROUND(($D$8/$E$3*AX8)+($D$8/$H$2*AY8),0) -> 0 | BC8: =ROUND(($D$8/$E$3*BA8)+($D$8/$H$2*BB8),0) -> 0 | BF8: =ROUND(($D$8/$E$3*BD8)+($D$8/$H$2*BE8),0) -> 0 | BI8: =ROUND(($D$8/$E$3*BG8)+($D$8/$H$2*BH8),0) -> 0 | BL8: =ROUND(($D$8/$E$3*BJ8)+($D$8/$H$2*BK8),0) -> 0 | BO8: =ROUND(($D$8/$E$3*BM8)+($D$8/$H$2*BN8),0) -> 0 | BR8: =ROUND(($D$8/$E$3*BP8)+($D$8/$H$2*BQ8),0) -> 0 | BU8: =ROUND(($D$8/$E$3*BS8)+($D$8/$H$2*BT8),0) -> 0 | BX8: =ROUND(($D$8/$E$3*BV8)+($D$8/$H$2*BW8),0) -> 0 | CA8: =ROUND(($D$8/$E$3*BY8)+($D$8/$H$2*BZ8),0) -> 0 | CD8: =ROUND(($D$8/$E$3*CB8)+($D$8/$H$2*CC8),0) -> 0 | CG8: =ROUND(($D$8/$E$3*CE8)+($D$8/$H$2*CF8),0) -> 0 | CJ8: =ROUND(($D$8/$E$3*CH8)+($D$8/$H$2*CI8),0) -> 0 | CM8: =ROUND(($D$8/$E$3*CK8)+($D$8/$H$2*CL8),0) -> 0 | CP8: =ROUND(($D$8/$E$3*CN8)+($D$8/$H$2*CO8),0) -> 0 | CS8: =ROUND(($D$8/$E$3*CQ8)+($D$8/$H$2*CR8),0) -> 0 | CV8: =ROUND(($D$8/$E$3*CT8)+($D$8/$H$2*CU8),0) -> 0 | CY8: =ROUND(($D$8/$E$3*CW8)+($D$8/$H$2*CX8),0) -> 0 | DB8: =ROUND(($D$8/$E$3*CZ8)+($D$8/$H$2*DA8),0) -> 0
A9: 6 | B9: Dharmender Noniya | C9: Stitching/Die | D9: 21400 | E9: =K9+N9+Q9+T9+W9+Z9+AC9+AF9+AI9+AL9+AO9+AR9+AU9+AX9+BA9+BD9+BG9+BJ9+BM9+BP9+BS9+BV9+BY9+CB9+CE9+CH9+CK9+CN9+CQ9+CT9+CW9+CZ9 -> 7 | F9: =ROUND(D9/$F$2*E9,0) -> 4832 | G9: =L9+O9+R9+U9+X9+AA9+AD9+AG9+AJ9+AM9+AP9+AS9+AV9+AY9+BB9+BE9+BH9+BK9+BN9+BQ9+BT9+BW9+BZ9+CC9+CF9+CI9+CL9+CO9+CR9+CU9+CX9+DA8 -> 41 | H9: =ROUND(D9/$H$2*G9,0) -> 3538 | I9: =F9+H9 -> 8370 | J9: =M9+P9+S9+V9+Y9+AB9+AE9+AH9+AK9+AN9+AQ9+AT9+AW9+AZ9+BC9+BF9+BI9+BL9+BO9+BR9+BU9+BX9+CA9+CD9+CG9+CJ9+CM9+CP9+CS9+CV9+CY9 -> 8371 | K9: 1 | L9: 3.5 | M9: =ROUND(($D$9/$E$3*K9)+($D$9/$H$2*L9),0) -> 992 | N9: 1 | O9: 8 | P9: =ROUND(($D$9/$E$3*N9)+($D$9/$H$2*O9),0) -> 1381 | Q9: 1 | R9: 7.5 | S9: =ROUND(($D$9/$E$3*Q9)+($D$9/$H$2*R9),0) -> 1338 | T9: 1 | U9: 3.5 | V9: =ROUND(($D$9/$E$3*T9)+($D$9/$H$2*U9),0) -> 992 | W9: 1 | X9: 7.5 | Y9: =ROUND(($D$9/$E$3*W9)+($D$9/$H$2*X9),0) -> 1338 | Z9: 1 | AA9: 7.5 | AB9: =ROUND(($D$9/$E$3*Z9)+($D$9/$H$2*AA9),0) -> 1338 | AC9: 1 | AD9: 3.5 | AE9: =ROUND(($D$9/$E$3*AC9)+($D$9/$H$2*AD9),0) -> 992 | AH9: =ROUND(($D$9/$E$3*AF9)+($D$9/$H$2*AG9),0) -> 0 | AK9: =ROUND(($D$9/$E$3*AI9)+($D$9/$H$2*AJ9),0) -> 0 | AN9: =ROUND(($D$9/$E$3*AL9)+($D$9/$H$2*AM9),0) -> 0 | AQ9: =ROUND(($D$9/$E$3*AO9)+($D$9/$H$2*AP9),0) -> 0 | AT9: =ROUND(($D$9/$E$3*AR9)+($D$9/$H$2*AS9),0) -> 0 | AW9: =ROUND(($D$9/$E$3*AU9)+($D$9/$H$2*AV9),0) -> 0 | AZ9: =ROUND(($D$9/$E$3*AX9)+($D$9/$H$2*AY9),0) -> 0 | BC9: =ROUND(($D$9/$E$3*BA9)+($D$9/$H$2*BB9),0) -> 0 | BF9: =ROUND(($D$9/$E$3*BD9)+($D$9/$H$2*BE9),0) -> 0 | BI9: =ROUND(($D$9/$E$3*BG9)+($D$9/$H$2*BH9),0) -> 0 | BL9: =ROUND(($D$9/$E$3*BJ9)+($D$9/$H$2*BK9),0) -> 0 | BO9: =ROUND(($D$9/$E$3*BM9)+($D$9/$H$2*BN9),0) -> 0 | BR9: =ROUND(($D$9/$E$3*BP9)+($D$9/$H$2*BQ9),0) -> 0 | BU9: =ROUND(($D$9/$E$3*BS9)+($D$9/$H$2*BT9),0) -> 0 | BX9: =ROUND(($D$9/$E$3*BV9)+($D$9/$H$2*BW9),0) -> 0 | CA9: =ROUND(($D$9/$E$3*BY9)+($D$9/$H$2*BZ9),0) -> 0 | CD9: =ROUND(($D$9/$E$3*CB9)+($D$9/$H$2*CC9),0) -> 0 | CG9: =ROUND(($D$9/$E$3*CE9)+($D$9/$H$2*CF9),0) -> 0 | CJ9: =ROUND(($D$9/$E$3*CH9)+($D$9/$H$2*CI9),0) -> 0 | CM9: =ROUND(($D$9/$E$3*CK9)+($D$9/$H$2*CL9),0) -> 0 | CP9: =ROUND(($D$9/$E$3*CN9)+($D$9/$H$2*CO9),0) -> 0 | CS9: =ROUND(($D$9/$E$3*CQ9)+($D$9/$H$2*CR9),0) -> 0 | CV9: =ROUND(($D$9/$E$3*CT9)+($D$9/$H$2*CU9),0) -> 0 | CY9: =ROUND(($D$9/$E$3*CW9)+($D$9/$H$2*CX9),0) -> 0 | DB9: =ROUND(($D$9/$E$3*CZ9)+($D$9/$H$2*DA9),0) -> 0
A10: 7 | B10: Vijay Shahni | C10: Rotary/RS4 | D10: 20400 | E10: =K10+N10+Q10+T10+W10+Z10+AC10+AF10+AI10+AL10+AO10+AR10+AU10+AX10+BA10+BD10+BG10+BJ10+BM10+BP10+BS10+BV10+BY10+CB10+CE10+CH10+CK10+CN10+CQ10+CT10+CW10+CZ10 -> 7 | F10: =ROUND(D10/$F$2*E10,0) -> 4606 | G10: =L10+O10+R10+U10+X10+AA10+AD10+AG10+AJ10+AM10+AP10+AS10+AV10+AY10+BB10+BE10+BH10+BK10+BN10+BQ10+BT10+BW10+BZ10+CC10+CF10+CI10+CL10+CO10+CR10+CU10+CX10+DA9 -> 22 | H10: =ROUND(D10/$H$2*G10,0) -> 1810 | I10: =F10+H10 -> 6416 | J10: =M10+P10+S10+V10+Y10+AB10+AE10+AH10+AK10+AN10+AQ10+AT10+AW10+AZ10+BC10+BF10+BI10+BL10+BO10+BR10+BU10+BX10+CA10+CD10+CG10+CJ10+CM10+CP10+CS10+CV10+CY10 -> 6416 | K10: 1 | L10: 3.5 | M10: =ROUND(($D$10/$E$3*K10)+($D$10/$H$2*L10),0) -> 946 | N10: 1 | P10: =ROUND(($D$10/$E$3*N10)+($D$10/$H$2*O10),0) -> 658 | Q10: 1 | R10: 3.5 | S10: =ROUND(($D$10/$E$3*Q10)+($D$10/$H$2*R10),0) -> 946 | T10: 1 | U10: 3 | V10: =ROUND(($D$10/$E$3*T10)+($D$10/$H$2*U10),0) -> 905 | W10: 1 | X10: 7.5 | Y10: =ROUND(($D$10/$E$3*W10)+($D$10/$H$2*X10),0) -> 1275 | Z10: 1 | AA10: 1 | AB10: =ROUND(($D$10/$E$3*Z10)+($D$10/$H$2*AA10),0) -> 740 | AC10: 1 | AD10: 3.5 | AE10: =ROUND(($D$10/$E$3*AC10)+($D$10/$H$2*AD10),0) -> 946 | AH10: =ROUND(($D$10/$E$3*AF10)+($D$10/$H$2*AG10),0) -> 0 | AK10: =ROUND(($D$10/$E$3*AI10)+($D$10/$H$2*AJ10),0) -> 0 | AN10: =ROUND(($D$10/$E$3*AL10)+($D$10/$H$2*AM10),0) -> 0 | AQ10: =ROUND(($D$10/$E$3*AO10)+($D$10/$H$2*AP10),0) -> 0 | AT10: =ROUND(($D$10/$E$3*AR10)+($D$10/$H$2*AS10),0) -> 0 | AW10: =ROUND(($D$10/$E$3*AU10)+($D$10/$H$2*AV10),0) -> 0 | AZ10: =ROUND(($D$10/$E$3*AX10)+($D$10/$H$2*AY10),0) -> 0 | BC10: =ROUND(($D$10/$E$3*BA10)+($D$10/$H$2*BB10),0) -> 0 | BF10: =ROUND(($D$10/$E$3*BD10)+($D$10/$H$2*BE10),0) -> 0 | BI10: =ROUND(($D$10/$E$3*BG10)+($D$10/$H$2*BH10),0) -> 0 | BL10: =ROUND(($D$10/$E$3*BJ10)+($D$10/$H$2*BK10),0) -> 0 | BO10: =ROUND(($D$10/$E$3*BM10)+($D$10/$H$2*BN10),0) -> 0 | BR10: =ROUND(($D$10/$E$3*BP10)+($D$10/$H$2*BQ10),0) -> 0 | BU10: =ROUND(($D$10/$E$3*BS10)+($D$10/$H$2*BT10),0) -> 0 | BX10: =ROUND(($D$10/$E$3*BV10)+($D$10/$H$2*BW10),0) -> 0 | CA10: =ROUND(($D$10/$E$3*BY10)+($D$10/$H$2*BZ10),0) -> 0 | CD10: =ROUND(($D$10/$E$3*CB10)+($D$10/$H$2*CC10),0) -> 0 | CG10: =ROUND(($D$10/$E$3*CE10)+($D$10/$H$2*CF10),0) -> 0 | CJ10: =ROUND(($D$10/$E$3*CH10)+($D$10/$H$2*CI10),0) -> 0 | CM10: =ROUND(($D$10/$E$3*CK10)+($D$10/$H$2*CL10),0) -> 0 | CP10: =ROUND(($D$10/$E$3*CN10)+($D$10/$H$2*CO10),0) -> 0 | CS10: =ROUND(($D$10/$E$3*CQ10)+($D$10/$H$2*CR10),0) -> 0 | CV10: =ROUND(($D$10/$E$3*CT10)+($D$10/$H$2*CU10),0) -> 0 | CY10: =ROUND(($D$10/$E$3*CW10)+($D$10/$H$2*CX10),0) -> 0 | DB10: =ROUND(($D$10/$E$3*CZ10)+($D$10/$H$2*DA10),0) -> 0
A11: 8 | B11: Suman | C11: Helper | D11: 13000 | E11: =K11+N11+Q11+T11+W11+Z11+AC11+AF11+AI11+AL11+AO11+AR11+AU11+AX11+BA11+BD11+BG11+BJ11+BM11+BP11+BS11+BV11+BY11+CB11+CE11+CH11+CK11+CN11+CQ11+CT11+CW11+CZ11 -> 5 | F11: =ROUND(D11/$F$2*E11,0) -> 2097 | G11: =L11+O11+R11+U11+X11+AA11+AD11+AG11+AJ11+AM11+AP11+AS11+AV11+AY11+BB11+BE11+BH11+BK11+BN11+BQ11+BT11+BW11+BZ11+CC11+CF11+CI11+CL11+CO11+CR11+CU11+CX11+DA10 -> 9 | H11: =ROUND(D11/$H$2*G11,0) -> 472 | I11: =F11+H11 -> 2569 | J11: =M11+P11+S11+V11+Y11+AB11+AE11+AH11+AK11+AN11+AQ11+AT11+AW11+AZ11+BC11+BF11+BI11+BL11+BO11+BR11+BU11+BX11+CA11+CD11+CG11+CJ11+CM11+CP11+CS11+CV11+CY11 -> 2567 | M11: =ROUND(($D$11/$E$3*K11)+($D$11/$H$2*L11),0) -> 0 | N11: 1 | P11: =ROUND(($D$11/$E$3*N11)+($D$11/$H$2*O11),0) -> 419 | S11: =ROUND(($D$11/$E$3*Q11)+($D$11/$H$2*R11),0) -> 0 | T11: 1 | U11: 2.5 | V11: =ROUND(($D$11/$E$3*T11)+($D$11/$H$2*U11),0) -> 550 | W11: 1 | X11: 2 | Y11: =ROUND(($D$11/$E$3*W11)+($D$11/$H$2*X11),0) -> 524 | Z11: 1 | AA11: 2.5 | AB11: =ROUND(($D$11/$E$3*Z11)+($D$11/$H$2*AA11),0) -> 550 | AC11: 1 | AD11: 2 | AE11: =ROUND(($D$11/$E$3*AC11)+($D$11/$H$2*AD11),0) -> 524 | AH11: =ROUND(($D$11/$E$3*AF11)+($D$11/$H$2*AG11),0) -> 0 | AK11: =ROUND(($D$11/$E$3*AI11)+($D$11/$H$2*AJ11),0) -> 0 | AN11: =ROUND(($D$11/$E$3*AL11)+($D$11/$H$2*AM11),0) -> 0 | AQ11: =ROUND(($D$11/$E$3*AO11)+($D$11/$H$2*AP11),0) -> 0 | AT11: =ROUND(($D$11/$E$3*AR11)+($D$11/$H$2*AS11),0) -> 0 | AW11: =ROUND(($D$11/$E$3*AU11)+($D$11/$H$2*AV11),0) -> 0 | AZ11: =ROUND(($D$11/$E$3*AX11)+($D$11/$H$2*AY11),0) -> 0 | BC11: =ROUND(($D$11/$E$3*BA11)+($D$11/$H$2*BB11),0) -> 0 | BF11: =ROUND(($D$11/$E$3*BD11)+($D$11/$H$2*BE11),0) -> 0 | BI11: =ROUND(($D$11/$E$3*BG11)+($D$11/$H$2*BH11),0) -> 0 | BL11: =ROUND(($D$11/$E$3*BJ11)+($D$11/$H$2*BK11),0) -> 0 | BO11: =ROUND(($D$11/$E$3*BM11)+($D$11/$H$2*BN11),0) -> 0 | BR11: =ROUND(($D$11/$E$3*BP11)+($D$11/$H$2*BQ11),0) -> 0 | BU11: =ROUND(($D$11/$E$3*BS11)+($D$11/$H$2*BT11),0) -> 0 | BX11: =ROUND(($D$11/$E$3*BV11)+($D$11/$H$2*BW11),0) -> 0 | CA11: =ROUND(($D$11/$E$3*BY11)+($D$11/$H$2*BZ11),0) -> 0 | CD11: =ROUND(($D$11/$E$3*CB11)+($D$11/$H$2*CC11),0) -> 0 | CG11: =ROUND(($D$11/$E$3*CE11)+($D$11/$H$2*CF11),0) -> 0 | CJ11: =ROUND(($D$11/$E$3*CH11)+($D$11/$H$2*CI11),0) -> 0 | CM11: =ROUND(($D$11/$E$3*CK11)+($D$11/$H$2*CL11),0) -> 0 | CP11: =ROUND(($D$11/$E$3*CN11)+($D$11/$H$2*CO11),0) -> 0 | CS11: =ROUND(($D$11/$E$3*CQ11)+($D$11/$H$2*CR11),0) -> 0 | CV11: =ROUND(($D$11/$E$3*CT11)+($D$11/$H$2*CU11),0) -> 0 | CY11: =ROUND(($D$11/$E$3*CW11)+($D$11/$H$2*CX11),0) -> 0 | DB11: =ROUND(($D$11/$E$3*CZ11)+($D$11/$H$2*DA11),0) -> 0
A12: 9 | B12: Surender (Pasting) | C12: Operator | D12: 16500 | E12: =K12+N12+Q12+T12+W12+Z12+AC12+AF12+AI12+AL12+AO12+AR12+AU12+AX12+BA12+BD12+BG12+BJ12+BM12+BP12+BS12+BV12+BY12+CB12+CE12+CH12+CK12+CN12+CQ12+CT12+CW12+CZ12 -> 7 | F12: =ROUND(D12/$F$2*E12,0) -> 3726 | G12: =L12+O12+R12+U12+X12+AA12+AD12+AG12+AJ12+AM12+AP12+AS12+AV12+AY12+BB12+BE12+BH12+BK12+BN12+BQ12+BT12+BW12+BZ12+CC12+CF12+CI12+CL12+CO12+CR12+CU12+CX12+DA11 -> 36.5 | H12: =ROUND(D12/$H$2*G12,0) -> 2428 | I12: =F12+H12 -> 6154 | J12: =M12+P12+S12+V12+Y12+AB12+AE12+AH12+AK12+AN12+AQ12+AT12+AW12+AZ12+BC12+BF12+BI12+BL12+BO12+BR12+BU12+BX12+CA12+CD12+CG12+CJ12+CM12+CP12+CS12+CV12+CY12 -> 6154 | K12: 1 | L12: 3.5 | M12: =ROUND(($D$12/$E$3*K12)+($D$12/$H$2*L12),0) -> 765 | N12: 1 | O12: 8 | P12: =ROUND(($D$12/$E$3*N12)+($D$12/$H$2*O12),0) -> 1065 | Q12: 1 | R12: 3.5 | S12: =ROUND(($D$12/$E$3*Q12)+($D$12/$H$2*R12),0) -> 765 | T12: 1 | U12: 7.5 | V12: =ROUND(($D$12/$E$3*T12)+($D$12/$H$2*U12),0) -> 1031 | W12: 1 | X12: 3 | Y12: =ROUND(($D$12/$E$3*W12)+($D$12/$H$2*X12),0) -> 732 | Z12: 1 | AA12: 7.5 | AB12: =ROUND(($D$12/$E$3*Z12)+($D$12/$H$2*AA12),0) -> 1031 | AC12: 1 | AD12: 3.5 | AE12: =ROUND(($D$12/$E$3*AC12)+($D$12/$H$2*AD12),0) -> 765 | AH12: =ROUND(($D$12/$E$3*AF12)+($D$12/$H$2*AG12),0) -> 0 | AK12: =ROUND(($D$12/$E$3*AI12)+($D$12/$H$2*AJ12),0) -> 0 | AN12: =ROUND(($D$12/$E$3*AL12)+($D$12/$H$2*AM12),0) -> 0 | AQ12: =ROUND(($D$12/$E$3*AO12)+($D$12/$H$2*AP12),0) -> 0 | AT12: =ROUND(($D$12/$E$3*AR12)+($D$12/$H$2*AS12),0) -> 0 | AW12: =ROUND(($D$12/$E$3*AU12)+($D$12/$H$2*AV12),0) -> 0 | AZ12: =ROUND(($D$12/$E$3*AX12)+($D$12/$H$2*AY12),0) -> 0 | BC12: =ROUND(($D$12/$E$3*BA12)+($D$12/$H$2*BB12),0) -> 0 | BF12: =ROUND(($D$12/$E$3*BD12)+($D$12/$H$2*BE12),0) -> 0 | BI12: =ROUND(($D$12/$E$3*BG12)+($D$12/$H$2*BH12),0) -> 0 | BL12: =ROUND(($D$12/$E$3*BJ12)+($D$12/$H$2*BK12),0) -> 0 | BO12: =ROUND(($D$12/$E$3*BM12)+($D$12/$H$2*BN12),0) -> 0 | BR12: =ROUND(($D$12/$E$3*BP12)+($D$12/$H$2*BQ12),0) -> 0 | BU12: =ROUND(($D$12/$E$3*BS12)+($D$12/$H$2*BT12),0) -> 0 | BX12: =ROUND(($D$12/$E$3*BV12)+($D$12/$H$2*BW12),0) -> 0 | CA12: =ROUND(($D$12/$E$3*BY12)+($D$12/$H$2*BZ12),0) -> 0 | CD12: =ROUND(($D$12/$E$3*CB12)+($D$12/$H$2*CC12),0) -> 0 | CG12: =ROUND(($D$12/$E$3*CE12)+($D$12/$H$2*CF12),0) -> 0 | CJ12: =ROUND(($D$12/$E$3*CH12)+($D$12/$H$2*CI12),0) -> 0 | CM12: =ROUND(($D$12/$E$3*CK12)+($D$12/$H$2*CL12),0) -> 0 | CP12: =ROUND(($D$12/$E$3*CN12)+($D$12/$H$2*CO12),0) -> 0 | CS12: =ROUND(($D$12/$E$3*CQ12)+($D$12/$H$2*CR12),0) -> 0 | CV12: =ROUND(($D$12/$E$3*CT12)+($D$12/$H$2*CU12),0) -> 0 | CY12: =ROUND(($D$12/$E$3*CW12)+($D$12/$H$2*CX12),0) -> 0 | DB12: =ROUND(($D$12/$E$3*CZ12)+($D$12/$H$2*DA12),0) -> 0
A13: 10 | B13: Kunwar Chand | C13: Die opr. | D13: 22000 | E13: =K13+N13+Q13+T13+W13+Z13+AC13+AF13+AI13+AL13+AO13+AR13+AU13+AX13+BA13+BD13+BG13+BJ13+BM13+BP13+BS13+BV13+BY13+CB13+CE13+CH13+CK13+CN13+CQ13+CT13+CW13+CZ13 -> 7 | F13: =ROUND(D13/$F$2*E13,0) -> 4968 | G13: =L13+O13+R13+U13+X13+AA13+AD13+AG13+AJ13+AM13+AP13+AS13+AV13+AY13+BB13+BE13+BH13+BK13+BN13+BQ13+BT13+BW13+BZ13+CC13+CF13+CI13+CL13+CO13+CR13+CU13+CX13+DA12 -> 21 | H13: =ROUND(D13/$H$2*G13,0) -> 1863 | I13: =F13+H13 -> 6831 | J13: =M13+P13+S13+V13+Y13+AB13+AE13+AH13+AK13+AN13+AQ13+AT13+AW13+AZ13+BC13+BF13+BI13+BL13+BO13+BR13+BU13+BX13+CA13+CD13+CG13+CJ13+CM13+CP13+CS13+CV13+CY13 -> 6830 | K13: 1 | L13: 3.5 | M13: =ROUND(($D$13/$E$3*K13)+($D$13/$H$2*L13),0) -> 1020 | N13: 1 | P13: =ROUND(($D$13/$E$3*N13)+($D$13/$H$2*O13),0) -> 710 | Q13: 1 | R13: 3.5 | S13: =ROUND(($D$13/$E$3*Q13)+($D$13/$H$2*R13),0) -> 1020 | T13: 1 | U13: 3.5 | V13: =ROUND(($D$13/$E$3*T13)+($D$13/$H$2*U13),0) -> 1020 | W13: 1 | X13: 3.5 | Y13: =ROUND(($D$13/$E$3*W13)+($D$13/$H$2*X13),0) -> 1020 | Z13: 1 | AA13: 3.5 | AB13: =ROUND(($D$13/$E$3*Z13)+($D$13/$H$2*AA13),0) -> 1020 | AC13: 1 | AD13: 3.5 | AE13: =ROUND(($D$13/$E$3*AC13)+($D$13/$H$2*AD13),0) -> 1020 | AH13: =ROUND(($D$13/$E$3*AF13)+($D$13/$H$2*AG13),0) -> 0 | AK13: =ROUND(($D$13/$E$3*AI13)+($D$13/$H$2*AJ13),0) -> 0 | AN13: =ROUND(($D$13/$E$3*AL13)+($D$13/$H$2*AM13),0) -> 0 | AQ13: =ROUND(($D$13/$E$3*AO13)+($D$13/$H$2*AP13),0) -> 0 | AT13: =ROUND(($D$13/$E$3*AR13)+($D$13/$H$2*AS13),0) -> 0 | AW13: =ROUND(($D$13/$E$3*AU13)+($D$13/$H$2*AV13),0) -> 0 | AZ13: =ROUND(($D$13/$E$3*AX13)+($D$13/$H$2*AY13),0) -> 0 | BC13: =ROUND(($D$13/$E$3*BA13)+($D$13/$H$2*BB13),0) -> 0 | BF13: =ROUND(($D$13/$E$3*BD13)+($D$13/$H$2*BE13),0) -> 0 | BI13: =ROUND(($D$13/$E$3*BG13)+($D$13/$H$2*BH13),0) -> 0 | BL13: =ROUND(($D$13/$E$3*BJ13)+($D$13/$H$2*BK13),0) -> 0 | BO13: =ROUND(($D$13/$E$3*BM13)+($D$13/$H$2*BN13),0) -> 0 | BR13: =ROUND(($D$13/$E$3*BP13)+($D$13/$H$2*BQ13),0) -> 0 | BU13: =ROUND(($D$13/$E$3*BS13)+($D$13/$H$2*BT13),0) -> 0 | BX13: =ROUND(($D$13/$E$3*BV13)+($D$13/$H$2*BW13),0) -> 0 | CA13: =ROUND(($D$13/$E$3*BY13)+($D$13/$H$2*BZ13),0) -> 0 | CD13: =ROUND(($D$13/$E$3*CB13)+($D$13/$H$2*CC13),0) -> 0 | CG13: =ROUND(($D$13/$E$3*CE13)+($D$13/$H$2*CF13),0) -> 0 | CJ13: =ROUND(($D$13/$E$3*CH13)+($D$13/$H$2*CI13),0) -> 0 | CM13: =ROUND(($D$13/$E$3*CK13)+($D$13/$H$2*CL13),0) -> 0 | CP13: =ROUND(($D$13/$E$3*CN13)+($D$13/$H$2*CO13),0) -> 0 | CS13: =ROUND(($D$13/$E$3*CQ13)+($D$13/$H$2*CR13),0) -> 0 | CV13: =ROUND(($D$13/$E$3*CT13)+($D$13/$H$2*CU13),0) -> 0 | CY13: =ROUND(($D$13/$E$3*CW13)+($D$13/$H$2*CX13),0) -> 0 | DB13: =ROUND(($D$13/$E$3*CZ13)+($D$13/$H$2*DA13),0) -> 0
A14: 11 | B14: Shahrukh | C14: Corr. Opr | D14: 23000 | E14: =K14+N14+Q14+T14+W14+Z14+AC14+AF14+AI14+AL14+AO14+AR14+AU14+AX14+BA14+BD14+BG14+BJ14+BM14+BP14+BS14+BV14+BY14+CB14+CE14+CH14+CK14+CN14+CQ14+CT14+CW14+CZ14 -> 6 | F14: =ROUND(D14/$F$2*E14,0) -> 4452 | G14: =L14+O14+R14+U14+X14+AA14+AD14+AG14+AJ14+AM14+AP14+AS14+AV14+AY14+BB14+BE14+BH14+BK14+BN14+BQ14+BT14+BW14+BZ14+CC14+CF14+CI14+CL14+CO14+CR14+CU14+CX14+DA13 -> 14 | H14: =ROUND(D14/$H$2*G14,0) -> 1298 | I14: =F14+H14 -> 5750 | J14: =M14+P14+S14+V14+Y14+AB14+AE14+AH14+AK14+AN14+AQ14+AT14+AW14+AZ14+BC14+BF14+BI14+BL14+BO14+BR14+BU14+BX14+CA14+CD14+CG14+CJ14+CM14+CP14+CS14+CV14+CY14 -> 5752 | M14: =ROUND(($D$14/$E$3*K14)+($D$14/$H$2*L14),0) -> 0 | N14: 1 | P14: =ROUND(($D$14/$E$3*N14)+($D$14/$H$2*O14),0) -> 742 | Q14: 1 | R14: 3.5 | S14: =ROUND(($D$14/$E$3*Q14)+($D$14/$H$2*R14),0) -> 1067 | T14: 1 | U14: 3.5 | V14: =ROUND(($D$14/$E$3*T14)+($D$14/$H$2*U14),0) -> 1067 | W14: 1 | X14: 3.5 | Y14: =ROUND(($D$14/$E$3*W14)+($D$14/$H$2*X14),0) -> 1067 | Z14: 1 | AA14: 3.5 | AB14: =ROUND(($D$14/$E$3*Z14)+($D$14/$H$2*AA14),0) -> 1067 | AC14: 1 | AE14: =ROUND(($D$14/$E$3*AC14)+($D$14/$H$2*AD14),0) -> 742 | AH14: =ROUND(($D$14/$E$3*AF14)+($D$14/$H$2*AG14),0) -> 0 | AK14: =ROUND(($D$14/$E$3*AI14)+($D$14/$H$2*AJ14),0) -> 0 | AN14: =ROUND(($D$14/$E$3*AL14)+($D$14/$H$2*AM14),0) -> 0 | AQ14: =ROUND(($D$14/$E$3*AO14)+($D$14/$H$2*AP14),0) -> 0 | AT14: =ROUND(($D$14/$E$3*AR14)+($D$14/$H$2*AS14),0) -> 0 | AW14: =ROUND(($D$14/$E$3*AU14)+($D$14/$H$2*AV14),0) -> 0 | AZ14: =ROUND(($D$14/$E$3*AX14)+($D$14/$H$2*AY14),0) -> 0 | BC14: =ROUND(($D$14/$E$3*BA14)+($D$14/$H$2*BB14),0) -> 0 | BF14: =ROUND(($D$14/$E$3*BD14)+($D$14/$H$2*BE14),0) -> 0 | BI14: =ROUND(($D$14/$E$3*BG14)+($D$14/$H$2*BH14),0) -> 0 | BL14: =ROUND(($D$14/$E$3*BJ14)+($D$14/$H$2*BK14),0) -> 0 | BO14: =ROUND(($D$14/$E$3*BM14)+($D$14/$H$2*BN14),0) -> 0 | BR14: =ROUND(($D$14/$E$3*BP14)+($D$14/$H$2*BQ14),0) -> 0 | BU14: =ROUND(($D$14/$E$3*BS14)+($D$14/$H$2*BT14),0) -> 0 | BX14: =ROUND(($D$14/$E$3*BV14)+($D$14/$H$2*BW14),0) -> 0 | CA14: =ROUND(($D$14/$E$3*BY14)+($D$14/$H$2*BZ14),0) -> 0 | CD14: =ROUND(($D$14/$E$3*CB14)+($D$14/$H$2*CC14),0) -> 0 | CG14: =ROUND(($D$14/$E$3*CE14)+($D$14/$H$2*CF14),0) -> 0 | CJ14: =ROUND(($D$14/$E$3*CH14)+($D$14/$H$2*CI14),0) -> 0 | CM14: =ROUND(($D$14/$E$3*CK14)+($D$14/$H$2*CL14),0) -> 0 | CP14: =ROUND(($D$14/$E$3*CN14)+($D$14/$H$2*CO14),0) -> 0 | CS14: =ROUND(($D$14/$E$3*CQ14)+($D$14/$H$2*CR14),0) -> 0 | CV14: =ROUND(($D$14/$E$3*CT14)+($D$14/$H$2*CU14),0) -> 0 | CY14: =ROUND(($D$14/$E$3*CW14)+($D$14/$H$2*CX14),0) -> 0 | DB14: =ROUND(($D$14/$E$3*CZ14)+($D$14/$H$2*DA14),0) -> 0
A15: 12 | B15: Sharafat | C15: Die opr. | D15: 15000 | E15: =K15+N15+Q15+T15+W15+Z15+AC15+AF15+AI15+AL15+AO15+AR15+AU15+AX15+BA15+BD15+BG15+BJ15+BM15+BP15+BS15+BV15+BY15+CB15+CE15+CH15+CK15+CN15+CQ15+CT15+CW15+CZ15 -> 7 | F15: =ROUND(D15/$F$2*E15,0) -> 3387 | G15: =L15+O15+R15+U15+X15+AA15+AD15+AG15+AJ15+AM15+AP15+AS15+AV15+AY15+BB15+BE15+BH15+BK15+BN15+BQ15+BT15+BW15+BZ15+CC15+CF15+CI15+CL15+CO15+CR15+CU15+CX15+DA14 -> 21 | H15: =ROUND(D15/$H$2*G15,0) -> 1270 | I15: =F15+H15 -> 4657 | J15: =M15+P15+S15+V15+Y15+AB15+AE15+AH15+AK15+AN15+AQ15+AT15+AW15+AZ15+BC15+BF15+BI15+BL15+BO15+BR15+BU15+BX15+CA15+CD15+CG15+CJ15+CM15+CP15+CS15+CV15+CY15 -> 4660 | K15: 1 | L15: 3.5 | M15: =ROUND(($D$15/$E$3*K15)+($D$15/$H$2*L15),0) -> 696 | N15: 1 | P15: =ROUND(($D$15/$E$3*N15)+($D$15/$H$2*O15),0) -> 484 | Q15: 1 | R15: 3.5 | S15: =ROUND(($D$15/$E$3*Q15)+($D$15/$H$2*R15),0) -> 696 | T15: 1 | U15: 3.5 | V15: =ROUND(($D$15/$E$3*T15)+($D$15/$H$2*U15),0) -> 696 | W15: 1 | X15: 3.5 | Y15: =ROUND(($D$15/$E$3*W15)+($D$15/$H$2*X15),0) -> 696 | Z15: 1 | AA15: 3.5 | AB15: =ROUND(($D$15/$E$3*Z15)+($D$15/$H$2*AA15),0) -> 696 | AC15: 1 | AD15: 3.5 | AE15: =ROUND(($D$15/$E$3*AC15)+($D$15/$H$2*AD15),0) -> 696 | AH15: =ROUND(($D$15/$E$3*AF15)+($D$15/$H$2*AG15),0) -> 0 | AK15: =ROUND(($D$15/$E$3*AI15)+($D$15/$H$2*AJ15),0) -> 0 | AN15: =ROUND(($D$15/$E$3*AL15)+($D$15/$H$2*AM15),0) -> 0 | AQ15: =ROUND(($D$15/$E$3*AO15)+($D$15/$H$2*AP15),0) -> 0 | AT15: =ROUND(($D$15/$E$3*AR15)+($D$15/$H$2*AS15),0) -> 0 | AW15: =ROUND(($D$15/$E$3*AU15)+($D$15/$H$2*AV15),0) -> 0 | AZ15: =ROUND(($D$15/$E$3*AX15)+($D$15/$H$2*AY15),0) -> 0 | BC15: =ROUND(($D$15/$E$3*BA15)+($D$15/$H$2*BB15),0) -> 0 | BF15: =ROUND(($D$15/$E$3*BD15)+($D$15/$H$2*BE15),0) -> 0 | BI15: =ROUND(($D$15/$E$3*BG15)+($D$15/$H$2*BH15),0) -> 0 | BL15: =ROUND(($D$15/$E$3*BJ15)+($D$15/$H$2*BK15),0) -> 0 | BO15: =ROUND(($D$15/$E$3*BM15)+($D$15/$H$2*BN15),0) -> 0 | BR15: =ROUND(($D$15/$E$3*BP15)+($D$15/$H$2*BQ15),0) -> 0 | BU15: =ROUND(($D$15/$E$3*BS15)+($D$15/$H$2*BT15),0) -> 0 | BX15: =ROUND(($D$15/$E$3*BV15)+($D$15/$H$2*BW15),0) -> 0 | CA15: =ROUND(($D$15/$E$3*BY15)+($D$15/$H$2*BZ15),0) -> 0 | CD15: =ROUND(($D$15/$E$3*CB15)+($D$15/$H$2*CC15),0) -> 0 | CG15: =ROUND(($D$15/$E$3*CE15)+($D$15/$H$2*CF15),0) -> 0 | CJ15: =ROUND(($D$15/$E$3*CH15)+($D$15/$H$2*CI15),0) -> 0 | CM15: =ROUND(($D$15/$E$3*CK15)+($D$15/$H$2*CL15),0) -> 0 | CP15: =ROUND(($D$15/$E$3*CN15)+($D$15/$H$2*CO15),0) -> 0 | CS15: =ROUND(($D$15/$E$3*CQ15)+($D$15/$H$2*CR15),0) -> 0 | CV15: =ROUND(($D$15/$E$3*CT15)+($D$15/$H$2*CU15),0) -> 0 | CY15: =ROUND(($D$15/$E$3*CW15)+($D$15/$H$2*CX15),0) -> 0 | DB15: =ROUND(($D$15/$E$3*CZ15)+($D$15/$H$2*DA15),0) -> 0
A16: 13 | B16: Sanjan | C16: Helper | D16: 13500 | E16: =K16+N16+Q16+T16+W16+Z16+AC16+AF16+AI16+AL16+AO16+AR16+AU16+AX16+BA16+BD16+BG16+BJ16+BM16+BP16+BS16+BV16+BY16+CB16+CE16+CH16+CK16+CN16+CQ16+CT16+CW16+CZ16 -> 7 | F16: =ROUND(D16/$F$2*E16,0) -> 3048 | G16: =L16+O16+R16+U16+X16+AA16+AD16+AG16+AJ16+AM16+AP16+AS16+AV16+AY16+BB16+BE16+BH16+BK16+BN16+BQ16+BT16+BW16+BZ16+CC16+CF16+CI16+CL16+CO16+CR16+CU16+CX16+DA15 -> 27.5 | H16: =ROUND(D16/$H$2*G16,0) -> 1497 | I16: =F16+H16 -> 4545 | J16: =M16+P16+S16+V16+Y16+AB16+AE16+AH16+AK16+AN16+AQ16+AT16+AW16+AZ16+BC16+BF16+BI16+BL16+BO16+BR16+BU16+BX16+CA16+CD16+CG16+CJ16+CM16+CP16+CS16+CV16+CY16 -> 4546 | K16: 1 | L16: 3 | M16: =ROUND(($D$16/$E$3*K16)+($D$16/$H$2*L16),0) -> 599 | N16: 1 | O16: 8 | P16: =ROUND(($D$16/$E$3*N16)+($D$16/$H$2*O16),0) -> 871 | Q16: 1 | R16: 2.5 | S16: =ROUND(($D$16/$E$3*Q16)+($D$16/$H$2*R16),0) -> 572 | T16: 1 | U16: 3.5 | V16: =ROUND(($D$16/$E$3*T16)+($D$16/$H$2*U16),0) -> 626 | W16: 1 | X16: 3.5 | Y16: =ROUND(($D$16/$E$3*W16)+($D$16/$H$2*X16),0) -> 626 | Z16: 1 | AA16: 3.5 | AB16: =ROUND(($D$16/$E$3*Z16)+($D$16/$H$2*AA16),0) -> 626 | AC16: 1 | AD16: 3.5 | AE16: =ROUND(($D$16/$E$3*AC16)+($D$16/$H$2*AD16),0) -> 626 | AH16: =ROUND(($D$16/$E$3*AF16)+($D$16/$H$2*AG16),0) -> 0 | AK16: =ROUND(($D$16/$E$3*AI16)+($D$16/$H$2*AJ16),0) -> 0 | AN16: =ROUND(($D$16/$E$3*AL16)+($D$16/$H$2*AM16),0) -> 0 | AQ16: =ROUND(($D$16/$E$3*AO16)+($D$16/$H$2*AP16),0) -> 0 | AT16: =ROUND(($D$16/$E$3*AR16)+($D$16/$H$2*AS16),0) -> 0 | AW16: =ROUND(($D$16/$E$3*AU16)+($D$16/$H$2*AV16),0) -> 0 | AZ16: =ROUND(($D$16/$E$3*AX16)+($D$16/$H$2*AY16),0) -> 0 | BC16: =ROUND(($D$16/$E$3*BA16)+($D$16/$H$2*BB16),0) -> 0 | BF16: =ROUND(($D$16/$E$3*BD16)+($D$16/$H$2*BE16),0) -> 0 | BI16: =ROUND(($D$16/$E$3*BG16)+($D$16/$H$2*BH16),0) -> 0 | BL16: =ROUND(($D$16/$E$3*BJ16)+($D$16/$H$2*BK16),0) -> 0 | BO16: =ROUND(($D$16/$E$3*BM16)+($D$16/$H$2*BN16),0) -> 0 | BR16: =ROUND(($D$16/$E$3*BP16)+($D$16/$H$2*BQ16),0) -> 0 | BU16: =ROUND(($D$16/$E$3*BS16)+($D$16/$H$2*BT16),0) -> 0 | BX16: =ROUND(($D$16/$E$3*BV16)+($D$16/$H$2*BW16),0) -> 0 | CA16: =ROUND(($D$16/$E$3*BY16)+($D$16/$H$2*BZ16),0) -> 0 | CD16: =ROUND(($D$16/$E$3*CB16)+($D$16/$H$2*CC16),0) -> 0 | CG16: =ROUND(($D$16/$E$3*CE16)+($D$16/$H$2*CF16),0) -> 0 | CJ16: =ROUND(($D$16/$E$3*CH16)+($D$16/$H$2*CI16),0) -> 0 | CM16: =ROUND(($D$16/$E$3*CK16)+($D$16/$H$2*CL16),0) -> 0 | CP16: =ROUND(($D$16/$E$3*CN16)+($D$16/$H$2*CO16),0) -> 0 | CS16: =ROUND(($D$16/$E$3*CQ16)+($D$16/$H$2*CR16),0) -> 0 | CV16: =ROUND(($D$16/$E$3*CT16)+($D$16/$H$2*CU16),0) -> 0 | CY16: =ROUND(($D$16/$E$3*CW16)+($D$16/$H$2*CX16),0) -> 0 | DB16: =ROUND(($D$16/$E$3*CZ16)+($D$16/$H$2*DA16),0) -> 0
A17: 14 | B17: Jubaida | C17: Helper | D17: 13000 | E17: =K17+N17+Q17+T17+W17+Z17+AC17+AF17+AI17+AL17+AO17+AR17+AU17+AX17+BA17+BD17+BG17+BJ17+BM17+BP17+BS17+BV17+BY17+CB17+CE17+CH17+CK17+CN17+CQ17+CT17+CW17+CZ17 -> 7 | F17: =ROUND(D17/$F$2*E17,0) -> 2935 | G17: =L17+O17+R17+U17+X17+AA17+AD17+AG17+AJ17+AM17+AP17+AS17+AV17+AY17+BB17+BE17+BH17+BK17+BN17+BQ17+BT17+BW17+BZ17+CC17+CF17+CI17+CL17+CO17+CR17+CU17+CX17+DA16 -> 25 | H17: =ROUND(D17/$H$2*G17,0) -> 1310 | I17: =F17+H17 -> 4245 | J17: =M17+P17+S17+V17+Y17+AB17+AE17+AH17+AK17+AN17+AQ17+AT17+AW17+AZ17+BC17+BF17+BI17+BL17+BO17+BR17+BU17+BX17+CA17+CD17+CG17+CJ17+CM17+CP17+CS17+CV17+CY17 -> 4248 | K17: 1 | L17: 3 | M17: =ROUND(($D$17/$E$3*K17)+($D$17/$H$2*L17),0) -> 577 | N17: 1 | O17: 8 | P17: =ROUND(($D$17/$E$3*N17)+($D$17/$H$2*O17),0) -> 839 | Q17: 1 | R17: 3 | S17: =ROUND(($D$17/$E$3*Q17)+($D$17/$H$2*R17),0) -> 577 | T17: 1 | U17: 3 | V17: =ROUND(($D$17/$E$3*T17)+($D$17/$H$2*U17),0) -> 577 | W17: 1 | X17: 3 | Y17: =ROUND(($D$17/$E$3*W17)+($D$17/$H$2*X17),0) -> 577 | Z17: 1 | AA17: 3 | AB17: =ROUND(($D$17/$E$3*Z17)+($D$17/$H$2*AA17),0) -> 577 | AC17: 1 | AD17: 2 | AE17: =ROUND(($D$17/$E$3*AC17)+($D$17/$H$2*AD17),0) -> 524 | AH17: =ROUND(($D$17/$E$3*AF17)+($D$17/$H$2*AG17),0) -> 0 | AK17: =ROUND(($D$17/$E$3*AI17)+($D$17/$H$2*AJ17),0) -> 0 | AN17: =ROUND(($D$17/$E$3*AL17)+($D$17/$H$2*AM17),0) -> 0 | AQ17: =ROUND(($D$17/$E$3*AO17)+($D$17/$H$2*AP17),0) -> 0 | AT17: =ROUND(($D$17/$E$3*AR17)+($D$17/$H$2*AS17),0) -> 0 | AW17: =ROUND(($D$17/$E$3*AU17)+($D$17/$H$2*AV17),0) -> 0 | AZ17: =ROUND(($D$17/$E$3*AX17)+($D$17/$H$2*AY17),0) -> 0 | BC17: =ROUND(($D$17/$E$3*BA17)+($D$17/$H$2*BB17),0) -> 0 | BF17: =ROUND(($D$17/$E$3*BD17)+($D$17/$H$2*BE17),0) -> 0 | BI17: =ROUND(($D$17/$E$3*BG17)+($D$17/$H$2*BH17),0) -> 0 | BL17: =ROUND(($D$17/$E$3*BJ17)+($D$17/$H$2*BK17),0) -> 0 | BO17: =ROUND(($D$17/$E$3*BM17)+($D$17/$H$2*BN17),0) -> 0 | BR17: =ROUND(($D$17/$E$3*BP17)+($D$17/$H$2*BQ17),0) -> 0 | BU17: =ROUND(($D$17/$E$3*BS17)+($D$17/$H$2*BT17),0) -> 0 | BX17: =ROUND(($D$17/$E$3*BV17)+($D$17/$H$2*BW17),0) -> 0 | CA17: =ROUND(($D$17/$E$3*BY17)+($D$17/$H$2*BZ17),0) -> 0 | CD17: =ROUND(($D$17/$E$3*CB17)+($D$17/$H$2*CC17),0) -> 0 | CG17: =ROUND(($D$17/$E$3*CE17)+($D$17/$H$2*CF17),0) -> 0 | CJ17: =ROUND(($D$17/$E$3*CH17)+($D$17/$H$2*CI17),0) -> 0 | CM17: =ROUND(($D$17/$E$3*CK17)+($D$17/$H$2*CL17),0) -> 0 | CP17: =ROUND(($D$17/$E$3*CN17)+($D$17/$H$2*CO17),0) -> 0 | CS17: =ROUND(($D$17/$E$3*CQ17)+($D$17/$H$2*CR17),0) -> 0 | CV17: =ROUND(($D$17/$E$3*CT17)+($D$17/$H$2*CU17),0) -> 0 | CY17: =ROUND(($D$17/$E$3*CW17)+($D$17/$H$2*CX17),0) -> 0 | DB17: =ROUND(($D$17/$E$3*CZ17)+($D$17/$H$2*DA17),0) -> 0
A18: 15 | B18: Nitish | C18: Helper | D18: 13500 | E18: =K18+N18+Q18+T18+W18+Z18+AC18+AF18+AI18+AL18+AO18+AR18+AU18+AX18+BA18+BD18+BG18+BJ18+BM18+BP18+BS18+BV18+BY18+CB18+CE18+CH18+CK18+CN18+CQ18+CT18+CW18+CZ18 -> 6 | F18: =ROUND(D18/$F$2*E18,0) -> 2613 | G18: =L18+O18+R18+U18+X18+AA18+AD18+AG18+AJ18+AM18+AP18+AS18+AV18+AY18+BB18+BE18+BH18+BK18+BN18+BQ18+BT18+BW18+BZ18+CC18+CF18+CI18+CL18+CO18+CR18+CU18+CX18+DA17 -> 18.5 | H18: =ROUND(D18/$H$2*G18,0) -> 1007 | I18: =F18+H18 -> 3620 | J18: =M18+P18+S18+V18+Y18+AB18+AE18+AH18+AK18+AN18+AQ18+AT18+AW18+AZ18+BC18+BF18+BI18+BL18+BO18+BR18+BU18+BX18+CA18+CD18+CG18+CJ18+CM18+CP18+CS18+CV18+CY18 -> 3619 | K18: 1 | L18: 3.5 | M18: =ROUND(($D$18/$E$3*K18)+($D$18/$H$2*L18),0) -> 626 | N18: 1 | P18: =ROUND(($D$18/$E$3*N18)+($D$18/$H$2*O18),0) -> 435 | S18: =ROUND(($D$18/$E$3*Q18)+($D$18/$H$2*R18),0) -> 0 | T18: 1 | U18: 3.5 | V18: =ROUND(($D$18/$E$3*T18)+($D$18/$H$2*U18),0) -> 626 | W18: 1 | X18: 3.5 | Y18: =ROUND(($D$18/$E$3*W18)+($D$18/$H$2*X18),0) -> 626 | Z18: 1 | AA18: 3.5 | AB18: =ROUND(($D$18/$E$3*Z18)+($D$18/$H$2*AA18),0) -> 626 | AC18: 1 | AD18: 4.5 | AE18: =ROUND(($D$18/$E$3*AC18)+($D$18/$H$2*AD18),0) -> 680 | AH18: =ROUND(($D$18/$E$3*AF18)+($D$18/$H$2*AG18),0) -> 0 | AK18: =ROUND(($D$18/$E$3*AI18)+($D$18/$H$2*AJ18),0) -> 0 | AN18: =ROUND(($D$18/$E$3*AL18)+($D$18/$H$2*AM18),0) -> 0 | AQ18: =ROUND(($D$18/$E$3*AO18)+($D$18/$H$2*AP18),0) -> 0 | AT18: =ROUND(($D$18/$E$3*AR18)+($D$18/$H$2*AS18),0) -> 0 | AW18: =ROUND(($D$18/$E$3*AU18)+($D$18/$H$2*AV18),0) -> 0 | AZ18: =ROUND(($D$18/$E$3*AX18)+($D$18/$H$2*AY18),0) -> 0 | BC18: =ROUND(($D$18/$E$3*BA18)+($D$18/$H$2*BB18),0) -> 0 | BF18: =ROUND(($D$18/$E$3*BD18)+($D$18/$H$2*BE18),0) -> 0 | BI18: =ROUND(($D$18/$E$3*BG18)+($D$18/$H$2*BH18),0) -> 0 | BL18: =ROUND(($D$18/$E$3*BJ18)+($D$18/$H$2*BK18),0) -> 0 | BO18: =ROUND(($D$18/$E$3*BM18)+($D$18/$H$2*BN18),0) -> 0 | BR18: =ROUND(($D$18/$E$3*BP18)+($D$18/$H$2*BQ18),0) -> 0 | BU18: =ROUND(($D$18/$E$3*BS18)+($D$18/$H$2*BT18),0) -> 0 | BX18: =ROUND(($D$18/$E$3*BV18)+($D$18/$H$2*BW18),0) -> 0 | CA18: =ROUND(($D$18/$E$3*BY18)+($D$18/$H$2*BZ18),0) -> 0 | CD18: =ROUND(($D$18/$E$3*CB18)+($D$18/$H$2*CC18),0) -> 0 | CG18: =ROUND(($D$18/$E$3*CE18)+($D$18/$H$2*CF18),0) -> 0 | CJ18: =ROUND(($D$18/$E$3*CH18)+($D$18/$H$2*CI18),0) -> 0 | CM18: =ROUND(($D$18/$E$3*CK18)+($D$18/$H$2*CL18),0) -> 0 | CP18: =ROUND(($D$18/$E$3*CN18)+($D$18/$H$2*CO18),0) -> 0 | CS18: =ROUND(($D$18/$E$3*CQ18)+($D$18/$H$2*CR18),0) -> 0 | CV18: =ROUND(($D$18/$E$3*CT18)+($D$18/$H$2*CU18),0) -> 0 | CY18: =ROUND(($D$18/$E$3*CW18)+($D$18/$H$2*CX18),0) -> 0 | DB18: =ROUND(($D$18/$E$3*CZ18)+($D$18/$H$2*DA18),0) -> 0
A19: 16 | B19: Priti | C19: Helper | D19: 13000 | E19: =K19+N19+Q19+T19+W19+Z19+AC19+AF19+AI19+AL19+AO19+AR19+AU19+AX19+BA19+BD19+BG19+BJ19+BM19+BP19+BS19+BV19+BY19+CB19+CE19+CH19+CK19+CN19+CQ19+CT19+CW19+CZ19 -> 1 | F19: =ROUND(D19/$F$2*E19,0) -> 419 | G19: =L19+O19+R19+U19+X19+AA19+AD19+AG19+AJ19+AM19+AP19+AS19+AV19+AY19+BB19+BE19+BH19+BK19+BN19+BQ19+BT19+BW19+BZ19+CC19+CF19+CI19+CL19+CO19+CR19+CU19+CX19+DA18 -> 3 | H19: =ROUND(D19/$H$2*G19,0) -> 157 | I19: =F19+H19 -> 576 | J19: =M19+P19+S19+V19+Y19+AB19+AE19+AH19+AK19+AN19+AQ19+AT19+AW19+AZ19+BC19+BF19+BI19+BL19+BO19+BR19+BU19+BX19+CA19+CD19+CG19+CJ19+CM19+CP19+CS19+CV19+CY19 -> 576 | M19: =ROUND(($D$19/$E$3*K19)+($D$19/$H$2*L19),0) -> 0 | N19: 1 | P19: =ROUND(($D$19/$E$3*N19)+($D$19/$H$2*O19),0) -> 419 | R19: 3 | S19: =ROUND(($D$19/$E$3*Q19)+($D$19/$H$2*R19),0) -> 157 | V19: =ROUND(($D$19/$E$3*T19)+($D$19/$H$2*U19),0) -> 0 | Y19: =ROUND(($D$19/$E$3*W19)+($D$19/$H$2*X19),0) -> 0 | AB19: =ROUND(($D$19/$E$3*Z19)+($D$19/$H$2*AA19),0) -> 0 | AE19: =ROUND(($D$19/$E$3*AC19)+($D$19/$H$2*AD19),0) -> 0 | AH19: =ROUND(($D$19/$E$3*AF19)+($D$19/$H$2*AG19),0) -> 0 | AK19: =ROUND(($D$19/$E$3*AI19)+($D$19/$H$2*AJ19),0) -> 0 | AN19: =ROUND(($D$19/$E$3*AL19)+($D$19/$H$2*AM19),0) -> 0 | AQ19: =ROUND(($D$19/$E$3*AO19)+($D$19/$H$2*AP19),0) -> 0 | AT19: =ROUND(($D$19/$E$3*AR19)+($D$19/$H$2*AS19),0) -> 0 | AW19: =ROUND(($D$19/$E$3*AU19)+($D$19/$H$2*AV19),0) -> 0 | AZ19: =ROUND(($D$19/$E$3*AX19)+($D$19/$H$2*AY19),0) -> 0 | BC19: =ROUND(($D$19/$E$3*BA19)+($D$19/$H$2*BB19),0) -> 0 | BF19: =ROUND(($D$19/$E$3*BD19)+($D$19/$H$2*BE19),0) -> 0 | BI19: =ROUND(($D$19/$E$3*BG19)+($D$19/$H$2*BH19),0) -> 0 | BL19: =ROUND(($D$19/$E$3*BJ19)+($D$19/$H$2*BK19),0) -> 0 | BO19: =ROUND(($D$19/$E$3*BM19)+($D$19/$H$2*BN19),0) -> 0 | BR19: =ROUND(($D$19/$E$3*BP19)+($D$19/$H$2*BQ19),0) -> 0 | BU19: =ROUND(($D$19/$E$3*BS19)+($D$19/$H$2*BT19),0) -> 0 | BX19: =ROUND(($D$19/$E$3*BV19)+($D$19/$H$2*BW19),0) -> 0 | CA19: =ROUND(($D$19/$E$3*BY19)+($D$19/$H$2*BZ19),0) -> 0 | CD19: =ROUND(($D$19/$E$3*CB19)+($D$19/$H$2*CC19),0) -> 0 | CG19: =ROUND(($D$19/$E$3*CE19)+($D$19/$H$2*CF19),0) -> 0 | CJ19: =ROUND(($D$19/$E$3*CH19)+($D$19/$H$2*CI19),0) -> 0 | CM19: =ROUND(($D$19/$E$3*CK19)+($D$19/$H$2*CL19),0) -> 0 | CP19: =ROUND(($D$19/$E$3*CN19)+($D$19/$H$2*CO19),0) -> 0 | CS19: =ROUND(($D$19/$E$3*CQ19)+($D$19/$H$2*CR19),0) -> 0 | CV19: =ROUND(($D$19/$E$3*CT19)+($D$19/$H$2*CU19),0) -> 0 | CY19: =ROUND(($D$19/$E$3*CW19)+($D$19/$H$2*CX19),0) -> 0 | DB19: =ROUND(($D$19/$E$3*CZ19)+($D$19/$H$2*DA19),0) -> 0
A20: 17 | B20: Rohit | C20: Helper | D20: 14500 | E20: =K20+N20+Q20+T20+W20+Z20+AC20+AF20+AI20+AL20+AO20+AR20+AU20+AX20+BA20+BD20+BG20+BJ20+BM20+BP20+BS20+BV20+BY20+CB20+CE20+CH20+CK20+CN20+CQ20+CT20+CW20+CZ20 -> 6 | F20: =ROUND(D20/$F$2*E20,0) -> 2806 | G20: =L20+O20+R20+U20+X20+AA20+AD20+AG20+AJ20+AM20+AP20+AS20+AV20+AY20+BB20+BE20+BH20+BK20+BN20+BQ20+BT20+BW20+BZ20+CC20+CF20+CI20+CL20+CO20+CR20+CU20+CX20+DA19 -> 16.5 | H20: =ROUND(D20/$H$2*G20,0) -> 965 | I20: =F20+H20 -> 3771 | J20: =M20+P20+S20+V20+Y20+AB20+AE20+AH20+AK20+AN20+AQ20+AT20+AW20+AZ20+BC20+BF20+BI20+BL20+BO20+BR20+BU20+BX20+CA20+CD20+CG20+CJ20+CM20+CP20+CS20+CV20+CY20 -> 3770 | K20: 1 | L20: 3.5 | M20: =ROUND(($D$20/$E$3*K20)+($D$20/$H$2*L20),0) -> 672 | N20: 1 | P20: =ROUND(($D$20/$E$3*N20)+($D$20/$H$2*O20),0) -> 468 | Q20: 1 | R20: 3.5 | S20: =ROUND(($D$20/$E$3*Q20)+($D$20/$H$2*R20),0) -> 672 | T20: 1 | U20: 3.5 | V20: =ROUND(($D$20/$E$3*T20)+($D$20/$H$2*U20),0) -> 672 | W20: 1 | X20: 3.5 | Y20: =ROUND(($D$20/$E$3*W20)+($D$20/$H$2*X20),0) -> 672 | AB20: =ROUND(($D$20/$E$3*Z20)+($D$20/$H$2*AA20),0) -> 0 | AC20: 1 | AD20: 2.5 | AE20: =ROUND(($D$20/$E$3*AC20)+($D$20/$H$2*AD20),0) -> 614 | AH20: =ROUND(($D$20/$E$3*AF20)+($D$20/$H$2*AG20),0) -> 0 | AK20: =ROUND(($D$20/$E$3*AI20)+($D$20/$H$2*AJ20),0) -> 0 | AN20: =ROUND(($D$20/$E$3*AL20)+($D$20/$H$2*AM20),0) -> 0 | AQ20: =ROUND(($D$20/$E$3*AO20)+($D$20/$H$2*AP20),0) -> 0 | AT20: =ROUND(($D$20/$E$3*AR20)+($D$20/$H$2*AS20),0) -> 0 | AW20: =ROUND(($D$20/$E$3*AU20)+($D$20/$H$2*AV20),0) -> 0 | AZ20: =ROUND(($D$20/$E$3*AX20)+($D$20/$H$2*AY20),0) -> 0 | BC20: =ROUND(($D$20/$E$3*BA20)+($D$20/$H$2*BB20),0) -> 0 | BF20: =ROUND(($D$20/$E$3*BD20)+($D$20/$H$2*BE20),0) -> 0 | BI20: =ROUND(($D$20/$E$3*BG20)+($D$20/$H$2*BH20),0) -> 0 | BL20: =ROUND(($D$20/$E$3*BJ20)+($D$20/$H$2*BK20),0) -> 0 | BO20: =ROUND(($D$20/$E$3*BM20)+($D$20/$H$2*BN20),0) -> 0 | BR20: =ROUND(($D$20/$E$3*BP20)+($D$20/$H$2*BQ20),0) -> 0 | BU20: =ROUND(($D$20/$E$3*BS20)+($D$20/$H$2*BT20),0) -> 0 | BX20: =ROUND(($D$20/$E$3*BV20)+($D$20/$H$2*BW20),0) -> 0 | CA20: =ROUND(($D$20/$E$3*BY20)+($D$20/$H$2*BZ20),0) -> 0 | CD20: =ROUND(($D$20/$E$3*CB20)+($D$20/$H$2*CC20),0) -> 0 | CG20: =ROUND(($D$20/$E$3*CE20)+($D$20/$H$2*CF20),0) -> 0 | CJ20: =ROUND(($D$20/$E$3*CH20)+($D$20/$H$2*CI20),0) -> 0 | CM20: =ROUND(($D$20/$E$3*CK20)+($D$20/$H$2*CL20),0) -> 0 | CP20: =ROUND(($D$20/$E$3*CN20)+($D$20/$H$2*CO20),0) -> 0 | CS20: =ROUND(($D$20/$E$3*CQ20)+($D$20/$H$2*CR20),0) -> 0 | CV20: =ROUND(($D$20/$E$3*CT20)+($D$20/$H$2*CU20),0) -> 0 | CY20: =ROUND(($D$20/$E$3*CW20)+($D$20/$H$2*CX20),0) -> 0 | DB20: =ROUND(($D$20/$E$3*CZ20)+($D$20/$H$2*DA20),0) -> 0
A21: 18 | B21: Sandeep | C21: Operator | D21: 16500 | E21: =K21+N21+Q21+T21+W21+Z21+AC21+AF21+AI21+AL21+AO21+AR21+AU21+AX21+BA21+BD21+BG21+BJ21+BM21+BP21+BS21+BV21+BY21+CB21+CE21+CH21+CK21+CN21+CQ21+CT21+CW21+CZ21 -> 7 | F21: =ROUND(D21/$F$2*E21,0) -> 3726 | G21: =L21+O21+R21+U21+X21+AA21+AD21+AG21+AJ21+AM21+AP21+AS21+AV21+AY21+BB21+BE21+BH21+BK21+BN21+BQ21+BT21+BW21+BZ21+CC21+CF21+CI21+CL21+CO21+CR21+CU21+CX21+DA20 -> 20.5 | H21: =ROUND(D21/$H$2*G21,0) -> 1364 | I21: =F21+H21 -> 5090 | J21: =M21+P21+S21+V21+Y21+AB21+AE21+AH21+AK21+AN21+AQ21+AT21+AW21+AZ21+BC21+BF21+BI21+BL21+BO21+BR21+BU21+BX21+CA21+CD21+CG21+CJ21+CM21+CP21+CS21+CV21+CY21 -> 5089 | K21: 1 | L21: 7.5 | M21: =ROUND(($D$21/$E$3*K21)+($D$21/$H$2*L21),0) -> 1031 | N21: 1 | P21: =ROUND(($D$21/$E$3*N21)+($D$21/$H$2*O21),0) -> 532 | Q21: 1 | S21: =ROUND(($D$21/$E$3*Q21)+($D$21/$H$2*R21),0) -> 532 | T21: 1 | U21: 3.5 | V21: =ROUND(($D$21/$E$3*T21)+($D$21/$H$2*U21),0) -> 765 | W21: 1 | X21: 3.5 | Y21: =ROUND(($D$21/$E$3*W21)+($D$21/$H$2*X21),0) -> 765 | Z21: 1 | AA21: 3.5 | AB21: =ROUND(($D$21/$E$3*Z21)+($D$21/$H$2*AA21),0) -> 765 | AC21: 1 | AD21: 2.5 | AE21: =ROUND(($D$21/$E$3*AC21)+($D$21/$H$2*AD21),0) -> 699 | AH21: =ROUND(($D$21/$E$3*AF21)+($D$21/$H$2*AG21),0) -> 0 | AK21: =ROUND(($D$21/$E$3*AI21)+($D$21/$H$2*AJ21),0) -> 0 | AN21: =ROUND(($D$21/$E$3*AL21)+($D$21/$H$2*AM21),0) -> 0 | AQ21: =ROUND(($D$21/$E$3*AO21)+($D$21/$H$2*AP21),0) -> 0 | AT21: =ROUND(($D$21/$E$3*AR21)+($D$21/$H$2*AS21),0) -> 0 | AW21: =ROUND(($D$21/$E$3*AU21)+($D$21/$H$2*AV21),0) -> 0 | AZ21: =ROUND(($D$21/$E$3*AX21)+($D$21/$H$2*AY21),0) -> 0 | BC21: =ROUND(($D$21/$E$3*BA21)+($D$21/$H$2*BB21),0) -> 0 | BF21: =ROUND(($D$21/$E$3*BD21)+($D$21/$H$2*BE21),0) -> 0 | BI21: =ROUND(($D$21/$E$3*BG21)+($D$21/$H$2*BH21),0) -> 0 | BL21: =ROUND(($D$21/$E$3*BJ21)+($D$21/$H$2*BK21),0) -> 0 | BO21: =ROUND(($D$21/$E$3*BM21)+($D$21/$H$2*BN21),0) -> 0 | BR21: =ROUND(($D$21/$E$3*BP21)+($D$21/$H$2*BQ21),0) -> 0 | BU21: =ROUND(($D$21/$E$3*BS21)+($D$21/$H$2*BT21),0) -> 0 | BX21: =ROUND(($D$21/$E$3*BV21)+($D$21/$H$2*BW21),0) -> 0 | CA21: =ROUND(($D$21/$E$3*BY21)+($D$21/$H$2*BZ21),0) -> 0 | CD21: =ROUND(($D$21/$E$3*CB21)+($D$21/$H$2*CC21),0) -> 0 | CG21: =ROUND(($D$21/$E$3*CE21)+($D$21/$H$2*CF21),0) -> 0 | CJ21: =ROUND(($D$21/$E$3*CH21)+($D$21/$H$2*CI21),0) -> 0 | CM21: =ROUND(($D$21/$E$3*CK21)+($D$21/$H$2*CL21),0) -> 0 | CP21: =ROUND(($D$21/$E$3*CN21)+($D$21/$H$2*CO21),0) -> 0 | CS21: =ROUND(($D$21/$E$3*CQ21)+($D$21/$H$2*CR21),0) -> 0 | CV21: =ROUND(($D$21/$E$3*CT21)+($D$21/$H$2*CU21),0) -> 0 | CY21: =ROUND(($D$21/$E$3*CW21)+($D$21/$H$2*CX21),0) -> 0 | DB21: =ROUND(($D$21/$E$3*CZ21)+($D$21/$H$2*DA21),0) -> 0
A22: 19 | B22: Sonu | C22: Stitching Opr | D22: 18500 | E22: =K22+N22+Q22+T22+W22+Z22+AC22+AF22+AI22+AL22+AO22+AR22+AU22+AX22+BA22+BD22+BG22+BJ22+BM22+BP22+BS22+BV22+BY22+CB22+CE22+CH22+CK22+CN22+CQ22+CT22+CW22+CZ22 -> 7 | F22: =ROUND(D22/$F$2*E22,0) -> 4177 | G22: =L22+O22+R22+U22+X22+AA22+AD22+AG22+AJ22+AM22+AP22+AS22+AV22+AY22+BB22+BE22+BH22+BK22+BN22+BQ22+BT22+BW22+BZ22+CC22+CF22+CI22+CL22+CO22+CR22+CU22+CX22+DA21 -> 33 | H22: =ROUND(D22/$H$2*G22,0) -> 2462 | I22: =F22+H22 -> 6639 | J22: =M22+P22+S22+V22+Y22+AB22+AE22+AH22+AK22+AN22+AQ22+AT22+AW22+AZ22+BC22+BF22+BI22+BL22+BO22+BR22+BU22+BX22+CA22+CD22+CG22+CJ22+CM22+CP22+CS22+CV22+CY22 -> 6639 | K22: 1 | L22: 3.5 | M22: =ROUND(($D$22/$E$3*K22)+($D$22/$H$2*L22),0) -> 858 | N22: 1 | P22: =ROUND(($D$22/$E$3*N22)+($D$22/$H$2*O22),0) -> 597 | Q22: 1 | R22: 7.5 | S22: =ROUND(($D$22/$E$3*Q22)+($D$22/$H$2*R22),0) -> 1156 | T22: 1 | U22: 7.5 | V22: =ROUND(($D$22/$E$3*T22)+($D$22/$H$2*U22),0) -> 1156 | W22: 1 | X22: 3.5 | Y22: =ROUND(($D$22/$E$3*W22)+($D$22/$H$2*X22),0) -> 858 | Z22: 1 | AA22: 7.5 | AB22: =ROUND(($D$22/$E$3*Z22)+($D$22/$H$2*AA22),0) -> 1156 | AC22: 1 | AD22: 3.5 | AE22: =ROUND(($D$22/$E$3*AC22)+($D$22/$H$2*AD22),0) -> 858 | AH22: =ROUND(($D$22/$E$3*AF22)+($D$22/$H$2*AG22),0) -> 0 | AK22: =ROUND(($D$22/$E$3*AI22)+($D$22/$H$2*AJ22),0) -> 0 | AN22: =ROUND(($D$22/$E$3*AL22)+($D$22/$H$2*AM22),0) -> 0 | AQ22: =ROUND(($D$22/$E$3*AO22)+($D$22/$H$2*AP22),0) -> 0 | AT22: =ROUND(($D$22/$E$3*AR22)+($D$22/$H$2*AS22),0) -> 0 | AW22: =ROUND(($D$22/$E$3*AU22)+($D$22/$H$2*AV22),0) -> 0 | AZ22: =ROUND(($D$22/$E$3*AX22)+($D$22/$H$2*AY22),0) -> 0 | BC22: =ROUND(($D$22/$E$3*BA22)+($D$22/$H$2*BB22),0) -> 0 | BF22: =ROUND(($D$22/$E$3*BD22)+($D$22/$H$2*BE22),0) -> 0 | BI22: =ROUND(($D$22/$E$3*BG22)+($D$22/$H$2*BH22),0) -> 0 | BL22: =ROUND(($D$22/$E$3*BJ22)+($D$22/$H$2*BK22),0) -> 0 | BO22: =ROUND(($D$22/$E$3*BM22)+($D$22/$H$2*BN22),0) -> 0 | BR22: =ROUND(($D$22/$E$3*BP22)+($D$22/$H$2*BQ22),0) -> 0 | BU22: =ROUND(($D$22/$E$3*BS22)+($D$22/$H$2*BT22),0) -> 0 | BX22: =ROUND(($D$22/$E$3*BV22)+($D$22/$H$2*BW22),0) -> 0 | CA22: =ROUND(($D$22/$E$3*BY22)+($D$22/$H$2*BZ22),0) -> 0 | CD22: =ROUND(($D$22/$E$3*CB22)+($D$22/$H$2*CC22),0) -> 0 | CG22: =ROUND(($D$22/$E$3*CE22)+($D$22/$H$2*CF22),0) -> 0 | CJ22: =ROUND(($D$22/$E$3*CH22)+($D$22/$H$2*CI22),0) -> 0 | CM22: =ROUND(($D$22/$E$3*CK22)+($D$22/$H$2*CL22),0) -> 0 | CP22: =ROUND(($D$22/$E$3*CN22)+($D$22/$H$2*CO22),0) -> 0 | CS22: =ROUND(($D$22/$E$3*CQ22)+($D$22/$H$2*CR22),0) -> 0 | CV22: =ROUND(($D$22/$E$3*CT22)+($D$22/$H$2*CU22),0) -> 0 | CY22: =ROUND(($D$22/$E$3*CW22)+($D$22/$H$2*CX22),0) -> 0 | DB22: =ROUND(($D$22/$E$3*CZ22)+($D$22/$H$2*DA22),0) -> 0
A23: 20 | B23: Dhiraj | C23: Helper | D23: 14500 | E23: =K23+N23+Q23+T23+W23+Z23+AC23+AF23+AI23+AL23+AO23+AR23+AU23+AX23+BA23+BD23+BG23+BJ23+BM23+BP23+BS23+BV23+BY23+CB23+CE23+CH23+CK23+CN23+CQ23+CT23+CW23+CZ23 -> 6 | F23: =ROUND(D23/$F$2*E23,0) -> 2806 | G23: =L23+O23+R23+U23+X23+AA23+AD23+AG23+AJ23+AM23+AP23+AS23+AV23+AY23+BB23+BE23+BH23+BK23+BN23+BQ23+BT23+BW23+BZ23+CC23+CF23+CI23+CL23+CO23+CR23+CU23+CX23+DA22 -> 25 | H23: =ROUND(D23/$H$2*G23,0) -> 1462 | I23: =F23+H23 -> 4268 | J23: =M23+P23+S23+V23+Y23+AB23+AE23+AH23+AK23+AN23+AQ23+AT23+AW23+AZ23+BC23+BF23+BI23+BL23+BO23+BR23+BU23+BX23+CA23+CD23+CG23+CJ23+CM23+CP23+CS23+CV23+CY23 -> 4268 | K23: 1 | L23: 3 | M23: =ROUND(($D$23/$E$3*K23)+($D$23/$H$2*L23),0) -> 643 | N23: 1 | P23: =ROUND(($D$23/$E$3*N23)+($D$23/$H$2*O23),0) -> 468 | S23: =ROUND(($D$23/$E$3*Q23)+($D$23/$H$2*R23),0) -> 0 | T23: 1 | U23: 7.5 | V23: =ROUND(($D$23/$E$3*T23)+($D$23/$H$2*U23),0) -> 906 | W23: 1 | X23: 6.5 | Y23: =ROUND(($D$23/$E$3*W23)+($D$23/$H$2*X23),0) -> 848 | Z23: 1 | AA23: 3.5 | AB23: =ROUND(($D$23/$E$3*Z23)+($D$23/$H$2*AA23),0) -> 672 | AC23: 1 | AD23: 4.5 | AE23: =ROUND(($D$23/$E$3*AC23)+($D$23/$H$2*AD23),0) -> 731 | AH23: =ROUND(($D$23/$E$3*AF23)+($D$23/$H$2*AG23),0) -> 0 | AK23: =ROUND(($D$23/$E$3*AI23)+($D$23/$H$2*AJ23),0) -> 0 | AN23: =ROUND(($D$23/$E$3*AL23)+($D$23/$H$2*AM23),0) -> 0 | AQ23: =ROUND(($D$23/$E$3*AO23)+($D$23/$H$2*AP23),0) -> 0 | AT23: =ROUND(($D$23/$E$3*AR23)+($D$23/$H$2*AS23),0) -> 0 | AW23: =ROUND(($D$23/$E$3*AU23)+($D$23/$H$2*AV23),0) -> 0 | AZ23: =ROUND(($D$23/$E$3*AX23)+($D$23/$H$2*AY23),0) -> 0 | BC23: =ROUND(($D$23/$E$3*BA23)+($D$23/$H$2*BB23),0) -> 0 | BF23: =ROUND(($D$23/$E$3*BD23)+($D$23/$H$2*BE23),0) -> 0 | BI23: =ROUND(($D$23/$E$3*BG23)+($D$23/$H$2*BH23),0) -> 0 | BL23: =ROUND(($D$23/$E$3*BJ23)+($D$23/$H$2*BK23),0) -> 0 | BO23: =ROUND(($D$23/$E$3*BM23)+($D$23/$H$2*BN23),0) -> 0 | BR23: =ROUND(($D$23/$E$3*BP23)+($D$23/$H$2*BQ23),0) -> 0 | BU23: =ROUND(($D$23/$E$3*BS23)+($D$23/$H$2*BT23),0) -> 0 | BX23: =ROUND(($D$23/$E$3*BV23)+($D$23/$H$2*BW23),0) -> 0 | CA23: =ROUND(($D$23/$E$3*BY23)+($D$23/$H$2*BZ23),0) -> 0 | CD23: =ROUND(($D$23/$E$3*CB23)+($D$23/$H$2*CC23),0) -> 0 | CG23: =ROUND(($D$23/$E$3*CE23)+($D$23/$H$2*CF23),0) -> 0 | CJ23: =ROUND(($D$23/$E$3*CH23)+($D$23/$H$2*CI23),0) -> 0 | CM23: =ROUND(($D$23/$E$3*CK23)+($D$23/$H$2*CL23),0) -> 0 | CP23: =ROUND(($D$23/$E$3*CN23)+($D$23/$H$2*CO23),0) -> 0 | CS23: =ROUND(($D$23/$E$3*CQ23)+($D$23/$H$2*CR23),0) -> 0 | CV23: =ROUND(($D$23/$E$3*CT23)+($D$23/$H$2*CU23),0) -> 0 | CY23: =ROUND(($D$23/$E$3*CW23)+($D$23/$H$2*CX23),0) -> 0 | DB23: =ROUND(($D$23/$E$3*CZ23)+($D$23/$H$2*DA23),0) -> 0
A24: 21 | B24: Nand Kishore | C24: Corr. Opr | D24: 21400 | E24: =K24+N24+Q24+T24+W24+Z24+AC24+AF24+AI24+AL24+AO24+AR24+AU24+AX24+BA24+BD24+BG24+BJ24+BM24+BP24+BS24+BV24+BY24+CB24+CE24+CH24+CK24+CN24+CQ24+CT24+CW24+CZ24 -> 7 | F24: =ROUND(D24/$F$2*E24,0) -> 4832 | G24: =L24+O24+R24+U24+X24+AA24+AD24+AG24+AJ24+AM24+AP24+AS24+AV24+AY24+BB24+BE24+BH24+BK24+BN24+BQ24+BT24+BW24+BZ24+CC24+CF24+CI24+CL24+CO24+CR24+CU24+CX24+DA23 -> 17 | H24: =ROUND(D24/$H$2*G24,0) -> 1467 | I24: =F24+H24 -> 6299 | J24: =M24+P24+S24+V24+Y24+AB24+AE24+AH24+AK24+AN24+AQ24+AT24+AW24+AZ24+BC24+BF24+BI24+BL24+BO24+BR24+BU24+BX24+CA24+CD24+CG24+CJ24+CM24+CP24+CS24+CV24+CY24 -> 6298 | K24: 1 | L24: 7.5 | M24: =ROUND(($D$24/$E$3*K24)+($D$24/$H$2*L24),0) -> 1338 | N24: 1 | O24: 4 | P24: =ROUND(($D$24/$E$3*N24)+($D$24/$H$2*O24),0) -> 1035 | Q24: 1 | R24: 6.5 | S24: =ROUND(($D$24/$E$3*Q24)+($D$24/$H$2*R24),0) -> 1251 | T24: 1 | U24: 3.5 | V24: =ROUND(($D$24/$E$3*T24)+($D$24/$H$2*U24),0) -> 992 | W24: 1 | X24: 3.5 | Y24: =ROUND(($D$24/$E$3*W24)+($D$24/$H$2*X24),0) -> 992 | Z24: 1 | AA24: -4 | AB24: =ROUND(($D$24/$E$3*Z24)+($D$24/$H$2*AA24),0) -> 345 | AC24: 1 | AD24: -4 | AE24: =ROUND(($D$24/$E$3*AC24)+($D$24/$H$2*AD24),0) -> 345 | AH24: =ROUND(($D$24/$E$3*AF24)+($D$24/$H$2*AG24),0) -> 0 | AK24: =ROUND(($D$24/$E$3*AI24)+($D$24/$H$2*AJ24),0) -> 0 | AN24: =ROUND(($D$24/$E$3*AL24)+($D$24/$H$2*AM24),0) -> 0 | AQ24: =ROUND(($D$24/$E$3*AO24)+($D$24/$H$2*AP24),0) -> 0 | AT24: =ROUND(($D$24/$E$3*AR24)+($D$24/$H$2*AS24),0) -> 0 | AW24: =ROUND(($D$24/$E$3*AU24)+($D$24/$H$2*AV24),0) -> 0 | AZ24: =ROUND(($D$24/$E$3*AX24)+($D$24/$H$2*AY24),0) -> 0 | BC24: =ROUND(($D$24/$E$3*BA24)+($D$24/$H$2*BB24),0) -> 0 | BF24: =ROUND(($D$24/$E$3*BD24)+($D$24/$H$2*BE24),0) -> 0 | BI24: =ROUND(($D$24/$E$3*BG24)+($D$24/$H$2*BH24),0) -> 0 | BL24: =ROUND(($D$24/$E$3*BJ24)+($D$24/$H$2*BK24),0) -> 0 | BO24: =ROUND(($D$24/$E$3*BM24)+($D$24/$H$2*BN24),0) -> 0 | BR24: =ROUND(($D$24/$E$3*BP24)+($D$24/$H$2*BQ24),0) -> 0 | BU24: =ROUND(($D$24/$E$3*BS24)+($D$24/$H$2*BT24),0) -> 0 | BX24: =ROUND(($D$24/$E$3*BV24)+($D$24/$H$2*BW24),0) -> 0 | CA24: =ROUND(($D$24/$E$3*BY24)+($D$24/$H$2*BZ24),0) -> 0 | CD24: =ROUND(($D$24/$E$3*CB24)+($D$24/$H$2*CC24),0) -> 0 | CG24: =ROUND(($D$24/$E$3*CE24)+($D$24/$H$2*CF24),0) -> 0 | CJ24: =ROUND(($D$24/$E$3*CH24)+($D$24/$H$2*CI24),0) -> 0 | CM24: =ROUND(($D$24/$E$3*CK24)+($D$24/$H$2*CL24),0) -> 0 | CP24: =ROUND(($D$24/$E$3*CN24)+($D$24/$H$2*CO24),0) -> 0 | CS24: =ROUND(($D$24/$E$3*CQ24)+($D$24/$H$2*CR24),0) -> 0 | CV24: =ROUND(($D$24/$E$3*CT24)+($D$24/$H$2*CU24),0) -> 0 | CY24: =ROUND(($D$24/$E$3*CW24)+($D$24/$H$2*CX24),0) -> 0 | DB24: =ROUND(($D$24/$E$3*CZ24)+($D$24/$H$2*DA24),0) -> 0
A25: 22 | B25: Vishjeet | C25: RS4 Opr | D25: 21000 | E25: =K25+N25+Q25+T25+W25+Z25+AC25+AF25+AI25+AL25+AO25+AR25+AU25+AX25+BA25+BD25+BG25+BJ25+BM25+BP25+BS25+BV25+BY25+CB25+CE25+CH25+CK25+CN25+CQ25+CT25+CW25+CZ25 -> 7 | F25: =ROUND(D25/$F$2*E25,0) -> 4742 | G25: =L25+O25+R25+U25+X25+AA25+AD25+AG25+AJ25+AM25+AP25+AS25+AV25+AY25+BB25+BE25+BH25+BK25+BN25+BQ25+BT25+BW25+BZ25+CC25+CF25+CI25+CL25+CO25+CR25+CU25+CX25+DA24 -> 14.5 | H25: =ROUND(D25/$H$2*G25,0) -> 1228 | I25: =F25+H25 -> 5970 | J25: =M25+P25+S25+V25+Y25+AB25+AE25+AH25+AK25+AN25+AQ25+AT25+AW25+AZ25+BC25+BF25+BI25+BL25+BO25+BR25+BU25+BX25+CA25+CD25+CG25+CJ25+CM25+CP25+CS25+CV25+CY25 -> 5969 | K25: 1 | L25: 1.5 | M25: =ROUND(($D$25/$E$3*K25)+($D$25/$H$2*L25),0) -> 804 | N25: 1 | P25: =ROUND(($D$25/$E$3*N25)+($D$25/$H$2*O25),0) -> 677 | Q25: 1 | R25: 2.5 | S25: =ROUND(($D$25/$E$3*Q25)+($D$25/$H$2*R25),0) -> 889 | T25: 1 | U25: 3.5 | V25: =ROUND(($D$25/$E$3*T25)+($D$25/$H$2*U25),0) -> 974 | W25: 1 | X25: 3.5 | Y25: =ROUND(($D$25/$E$3*W25)+($D$25/$H$2*X25),0) -> 974 | Z25: 1 | AA25: 3.5 | AB25: =ROUND(($D$25/$E$3*Z25)+($D$25/$H$2*AA25),0) -> 974 | AC25: 1 | AE25: =ROUND(($D$25/$E$3*AC25)+($D$25/$H$2*AD25),0) -> 677 | AH25: =ROUND(($D$25/$E$3*AF25)+($D$25/$H$2*AG25),0) -> 0 | AK25: =ROUND(($D$25/$E$3*AI25)+($D$25/$H$2*AJ25),0) -> 0 | AN25: =ROUND(($D$25/$E$3*AL25)+($D$25/$H$2*AM25),0) -> 0 | AQ25: =ROUND(($D$25/$E$3*AO25)+($D$25/$H$2*AP25),0) -> 0 | AT25: =ROUND(($D$25/$E$3*AR25)+($D$25/$H$2*AS25),0) -> 0 | AW25: =ROUND(($D$25/$E$3*AU25)+($D$25/$H$2*AV25),0) -> 0 | AZ25: =ROUND(($D$25/$E$3*AX25)+($D$25/$H$2*AY25),0) -> 0 | BC25: =ROUND(($D$25/$E$3*BA25)+($D$25/$H$2*BB25),0) -> 0 | BF25: =ROUND(($D$25/$E$3*BD25)+($D$25/$H$2*BE25),0) -> 0 | BI25: =ROUND(($D$25/$E$3*BG25)+($D$25/$H$2*BH25),0) -> 0 | BL25: =ROUND(($D$25/$E$3*BJ25)+($D$25/$H$2*BK25),0) -> 0 | BO25: =ROUND(($D$25/$E$3*BM25)+($D$25/$H$2*BN25),0) -> 0 | BR25: =ROUND(($D$25/$E$3*BP25)+($D$25/$H$2*BQ25),0) -> 0 | BU25: =ROUND(($D$25/$E$3*BS25)+($D$25/$H$2*BT25),0) -> 0 | BX25: =ROUND(($D$25/$E$3*BV25)+($D$25/$H$2*BW25),0) -> 0 | CA25: =ROUND(($D$25/$E$3*BY25)+($D$25/$H$2*BZ25),0) -> 0 | CD25: =ROUND(($D$25/$E$3*CB25)+($D$25/$H$2*CC25),0) -> 0 | CG25: =ROUND(($D$25/$E$3*CE25)+($D$25/$H$2*CF25),0) -> 0 | CJ25: =ROUND(($D$25/$E$3*CH25)+($D$25/$H$2*CI25),0) -> 0 | CM25: =ROUND(($D$25/$E$3*CK25)+($D$25/$H$2*CL25),0) -> 0 | CP25: =ROUND(($D$25/$E$3*CN25)+($D$25/$H$2*CO25),0) -> 0 | CS25: =ROUND(($D$25/$E$3*CQ25)+($D$25/$H$2*CR25),0) -> 0 | CV25: =ROUND(($D$25/$E$3*CT25)+($D$25/$H$2*CU25),0) -> 0 | CY25: =ROUND(($D$25/$E$3*CW25)+($D$25/$H$2*CX25),0) -> 0 | DB25: =ROUND(($D$25/$E$3*CZ25)+($D$25/$H$2*DA25),0) -> 0
A26: 23 | B26: Sukesh | C26: Operator | D26: 19500 | E26: =K26+N26+Q26+T26+W26+Z26+AC26+AF26+AI26+AL26+AO26+AR26+AU26+AX26+BA26+BD26+BG26+BJ26+BM26+BP26+BS26+BV26+BY26+CB26+CE26+CH26+CK26+CN26+CQ26+CT26+CW26+CZ26 -> 7 | F26: =ROUND(D26/$F$2*E26,0) -> 4403 | G26: =L26+O26+R26+U26+X26+AA26+AD26+AG26+AJ26+AM26+AP26+AS26+AV26+AY26+BB26+BE26+BH26+BK26+BN26+BQ26+BT26+BW26+BZ26+CC26+CF26+CI26+CL26+CO26+CR26+CU26+CX26+DA25 -> 21.5 | H26: =ROUND(D26/$H$2*G26,0) -> 1691 | I26: =F26+H26 -> 6094 | J26: =M26+P26+S26+V26+Y26+AB26+AE26+AH26+AK26+AN26+AQ26+AT26+AW26+AZ26+BC26+BF26+BI26+BL26+BO26+BR26+BU26+BX26+CA26+CD26+CG26+CJ26+CM26+CP26+CS26+CV26+CY26 -> 6163 | K26: 1 | L26: 3.5 | M26: =ROUND(($D$26/$E$3*K26)+($D$26/$H$2*L26),0) -> 904 | N26: 1 | P26: =ROUND(($D$26/$E$3*N26)+($D$26/$H$2*O26),0) -> 629 | Q26: 1 | S26: =ROUND(($D$26/$E$3*Q26)+($D$26/$H$2*R26),0) -> 629 | T26: 1 | U26: 3.5 | V26: =ROUND(($D$26/$E$3*T26)+($D$26/$H$2*U26),0) -> 904 | W26: 1 | X26: 7.5 | Y26: =ROUND(($D$26/$E$3*W26)+($D$26/$H$2*X26),0) -> 1219 | Z26: 1 | AA26: 3.5 | AB26: =ROUND(($D$25/$E$3*Z26)+($D$25/$H$2*AA26),0) -> 974 | AC26: 1 | AD26: 3.5 | AE26: =ROUND(($D$26/$E$3*AC26)+($D$26/$H$2*AD26),0) -> 904 | AH26: =ROUND(($D$26/$E$3*AF26)+($D$26/$H$2*AG26),0) -> 0 | AK26: =ROUND(($D$26/$E$3*AI26)+($D$26/$H$2*AJ26),0) -> 0 | AN26: =ROUND(($D$26/$E$3*AL26)+($D$26/$H$2*AM26),0) -> 0 | AQ26: =ROUND(($D$26/$E$3*AO26)+($D$26/$H$2*AP26),0) -> 0 | AT26: =ROUND(($D$26/$E$3*AR26)+($D$26/$H$2*AS26),0) -> 0 | AW26: =ROUND(($D$26/$E$3*AU26)+($D$26/$H$2*AV26),0) -> 0 | AZ26: =ROUND(($D$26/$E$3*AX26)+($D$26/$H$2*AY26),0) -> 0 | BC26: =ROUND(($D$26/$E$3*BA26)+($D$26/$H$2*BB26),0) -> 0 | BF26: =ROUND(($D$26/$E$3*BD26)+($D$26/$H$2*BE26),0) -> 0 | BI26: =ROUND(($D$26/$E$3*BG26)+($D$26/$H$2*BH26),0) -> 0 | BL26: =ROUND(($D$26/$E$3*BJ26)+($D$26/$H$2*BK26),0) -> 0 | BO26: =ROUND(($D$26/$E$3*BM26)+($D$26/$H$2*BN26),0) -> 0 | BR26: =ROUND(($D$26/$E$3*BP26)+($D$26/$H$2*BQ26),0) -> 0 | BU26: =ROUND(($D$26/$E$3*BS26)+($D$26/$H$2*BT26),0) -> 0 | BX26: =ROUND(($D$26/$E$3*BV26)+($D$26/$H$2*BW26),0) -> 0 | CA26: =ROUND(($D$26/$E$3*BY26)+($D$26/$H$2*BZ26),0) -> 0 | CD26: =ROUND(($D$26/$E$3*CB26)+($D$26/$H$2*CC26),0) -> 0 | CG26: =ROUND(($D$26/$E$3*CE26)+($D$26/$H$2*CF26),0) -> 0 | CJ26: =ROUND(($D$26/$E$3*CH26)+($D$26/$H$2*CI26),0) -> 0 | CM26: =ROUND(($D$26/$E$3*CK26)+($D$26/$H$2*CL26),0) -> 0 | CP26: =ROUND(($D$26/$E$3*CN26)+($D$26/$H$2*CO26),0) -> 0 | CS26: =ROUND(($D$26/$E$3*CQ26)+($D$26/$H$2*CR26),0) -> 0 | CV26: =ROUND(($D$26/$E$3*CT26)+($D$26/$H$2*CU26),0) -> 0 | CY26: =ROUND(($D$26/$E$3*CW26)+($D$26/$H$2*CX26),0) -> 0 | DB26: =ROUND(($D$26/$E$3*CZ26)+($D$26/$H$2*DA26),0) -> 0
A27: 24 | B27: Dharmesh | C27: Pasting | D27: 16000 | E27: =K27+N27+Q27+T27+W27+Z27+AC27+AF27+AI27+AL27+AO27+AR27+AU27+AX27+BA27+BD27+BG27+BJ27+BM27+BP27+BS27+BV27+BY27+CB27+CE27+CH27+CK27+CN27+CQ27+CT27+CW27+CZ27 -> 7 | F27: =ROUND(D27/$F$2*E27,0) -> 3613 | G27: =L27+O27+R27+U27+X27+AA27+AD27+AG27+AJ27+AM27+AP27+AS27+AV27+AY27+BB27+BE27+BH27+BK27+BN27+BQ27+BT27+BW27+BZ27+CC27+CF27+CI27+CL27+CO27+CR27+CU27+CX27+DA26 -> 21.5 | H27: =ROUND(D27/$H$2*G27,0) -> 1387 | I27: =F27+H27 -> 5000 | J27: =M27+P27+S27+V27+Y27+AB27+AE27+AH27+AK27+AN27+AQ27+AT27+AW27+AZ27+BC27+BF27+BI27+BL27+BO27+BR27+BU27+BX27+CA27+CD27+CG27+CJ27+CM27+CP27+CS27+CV27+CY27 -> 5000 | K27: 1 | L27: 7.5 | M27: =ROUND(($D$27/$E$3*K27)+($D$27/$H$2*L27),0) -> 1000 | N27: 1 | P27: =ROUND(($D$27/$E$3*N27)+($D$27/$H$2*O27),0) -> 516 | Q27: 1 | S27: =ROUND(($D$27/$E$3*Q27)+($D$27/$H$2*R27),0) -> 516 | T27: 1 | U27: 3.5 | V27: =ROUND(($D$27/$E$3*T27)+($D$27/$H$2*U27),0) -> 742 | W27: 1 | X27: 3.5 | Y27: =ROUND(($D$27/$E$3*W27)+($D$27/$H$2*X27),0) -> 742 | Z27: 1 | AA27: 3.5 | AB27: =ROUND(($D$27/$E$3*Z27)+($D$27/$H$2*AA27),0) -> 742 | AC27: 1 | AD27: 3.5 | AE27: =ROUND(($D$27/$E$3*AC27)+($D$27/$H$2*AD27),0) -> 742 | AH27: =ROUND(($D$27/$E$3*AF27)+($D$27/$H$2*AG27),0) -> 0 | AK27: =ROUND(($D$27/$E$3*AI27)+($D$27/$H$2*AJ27),0) -> 0 | AN27: =ROUND(($D$27/$E$3*AL27)+($D$27/$H$2*AM27),0) -> 0 | AQ27: =ROUND(($D$27/$E$3*AO27)+($D$27/$H$2*AP27),0) -> 0 | AT27: =ROUND(($D$27/$E$3*AR27)+($D$27/$H$2*AS27),0) -> 0 | AW27: =ROUND(($D$27/$E$3*AU27)+($D$27/$H$2*AV27),0) -> 0 | AZ27: =ROUND(($D$27/$E$3*AX27)+($D$27/$H$2*AY27),0) -> 0 | BC27: =ROUND(($D$27/$E$3*BA27)+($D$27/$H$2*BB27),0) -> 0 | BF27: =ROUND(($D$27/$E$3*BD27)+($D$27/$H$2*BE27),0) -> 0 | BI27: =ROUND(($D$27/$E$3*BG27)+($D$27/$H$2*BH27),0) -> 0 | BL27: =ROUND(($D$27/$E$3*BJ27)+($D$27/$H$2*BK27),0) -> 0 | BO27: =ROUND(($D$27/$E$3*BM27)+($D$27/$H$2*BN27),0) -> 0 | BR27: =ROUND(($D$27/$E$3*BP27)+($D$27/$H$2*BQ27),0) -> 0 | BU27: =ROUND(($D$27/$E$3*BS27)+($D$27/$H$2*BT27),0) -> 0 | BX27: =ROUND(($D$27/$E$3*BV27)+($D$27/$H$2*BW27),0) -> 0 | CA27: =ROUND(($D$27/$E$3*BY27)+($D$27/$H$2*BZ27),0) -> 0 | CD27: =ROUND(($D$27/$E$3*CB27)+($D$27/$H$2*CC27),0) -> 0 | CG27: =ROUND(($D$27/$E$3*CE27)+($D$27/$H$2*CF27),0) -> 0 | CJ27: =ROUND(($D$27/$E$3*CH27)+($D$27/$H$2*CI27),0) -> 0 | CM27: =ROUND(($D$27/$E$3*CK27)+($D$27/$H$2*CL27),0) -> 0 | CP27: =ROUND(($D$27/$E$3*CN27)+($D$27/$H$2*CO27),0) -> 0 | CS27: =ROUND(($D$27/$E$3*CQ27)+($D$27/$H$2*CR27),0) -> 0 | CV27: =ROUND(($D$27/$E$3*CT27)+($D$27/$H$2*CU27),0) -> 0 | CY27: =ROUND(($D$27/$E$3*CW27)+($D$27/$H$2*CX27),0) -> 0 | DB27: =ROUND(($D$27/$E$3*CZ27)+($D$27/$H$2*DA27),0) -> 0
A28: 25 | B28: Mohit | C28: Pasting | D28: 16000 | E28: =K28+N28+Q28+T28+W28+Z28+AC28+AF28+AI28+AL28+AO28+AR28+AU28+AX28+BA28+BD28+BG28+BJ28+BM28+BP28+BS28+BV28+BY28+CB28+CE28+CH28+CK28+CN28+CQ28+CT28+CW28+CZ28 -> 7 | F28: =ROUND(D28/$F$2*E28,0) -> 3613 | G28: =L28+O28+R28+U28+X28+AA28+AD28+AG28+AJ28+AM28+AP28+AS28+AV28+AY28+BB28+BE28+BH28+BK28+BN28+BQ28+BT28+BW28+BZ28+CC28+CF28+CI28+CL28+CO28+CR28+CU28+CX28+DA27 -> 17.5 | H28: =ROUND(D28/$H$2*G28,0) -> 1129 | I28: =F28+H28 -> 4742 | J28: =M28+P28+S28+V28+Y28+AB28+AE28+AH28+AK28+AN28+AQ28+AT28+AW28+AZ28+BC28+BF28+BI28+BL28+BO28+BR28+BU28+BX28+CA28+CD28+CG28+CJ28+CM28+CP28+CS28+CV28+CY28 -> 4742 | K28: 1 | L28: 3.5 | M28: =ROUND(($D$28/$E$3*K28)+($D$28/$H$2*L28),0) -> 742 | N28: 1 | P28: =ROUND(($D$28/$E$3*N28)+($D$28/$H$2*O28),0) -> 516 | Q28: 1 | R28: 3.5 | S28: =ROUND(($D$28/$E$3*Q28)+($D$28/$H$2*R28),0) -> 742 | T28: 1 | V28: =ROUND(($D$28/$E$3*T28)+($D$28/$H$2*U28),0) -> 516 | W28: 1 | X28: 3.5 | Y28: =ROUND(($D$28/$E$3*W28)+($D$28/$H$2*X28),0) -> 742 | Z28: 1 | AA28: 3.5 | AB28: =ROUND(($D$28/$E$3*Z28)+($D$28/$H$2*AA28),0) -> 742 | AC28: 1 | AD28: 3.5 | AE28: =ROUND(($D$28/$E$3*AC28)+($D$28/$H$2*AD28),0) -> 742 | AH28: =ROUND(($D$28/$E$3*AF28)+($D$28/$H$2*AG28),0) -> 0 | AK28: =ROUND(($D$28/$E$3*AI28)+($D$28/$H$2*AJ28),0) -> 0 | AN28: =ROUND(($D$28/$E$3*AL28)+($D$28/$H$2*AM28),0) -> 0 | AQ28: =ROUND(($D$28/$E$3*AO28)+($D$28/$H$2*AP28),0) -> 0 | AT28: =ROUND(($D$28/$E$3*AR28)+($D$28/$H$2*AS28),0) -> 0 | AW28: =ROUND(($D$28/$E$3*AU28)+($D$28/$H$2*AV28),0) -> 0 | AZ28: =ROUND(($D$28/$E$3*AX28)+($D$28/$H$2*AY28),0) -> 0 | BC28: =ROUND(($D$28/$E$3*BA28)+($D$28/$H$2*BB28),0) -> 0 | BF28: =ROUND(($D$28/$E$3*BD28)+($D$28/$H$2*BE28),0) -> 0 | BI28: =ROUND(($D$28/$E$3*BG28)+($D$28/$H$2*BH28),0) -> 0 | BL28: =ROUND(($D$28/$E$3*BJ28)+($D$28/$H$2*BK28),0) -> 0 | BO28: =ROUND(($D$28/$E$3*BM28)+($D$28/$H$2*BN28),0) -> 0 | BR28: =ROUND(($D$28/$E$3*BP28)+($D$28/$H$2*BQ28),0) -> 0 | BU28: =ROUND(($D$28/$E$3*BS28)+($D$28/$H$2*BT28),0) -> 0 | BX28: =ROUND(($D$28/$E$3*BV28)+($D$28/$H$2*BW28),0) -> 0 | CA28: =ROUND(($D$28/$E$3*BY28)+($D$28/$H$2*BZ28),0) -> 0 | CD28: =ROUND(($D$28/$E$3*CB28)+($D$28/$H$2*CC28),0) -> 0 | CG28: =ROUND(($D$28/$E$3*CE28)+($D$28/$H$2*CF28),0) -> 0 | CJ28: =ROUND(($D$28/$E$3*CH28)+($D$28/$H$2*CI28),0) -> 0 | CM28: =ROUND(($D$28/$E$3*CK28)+($D$28/$H$2*CL28),0) -> 0 | CP28: =ROUND(($D$28/$E$3*CN28)+($D$28/$H$2*CO28),0) -> 0 | CS28: =ROUND(($D$28/$E$3*CQ28)+($D$28/$H$2*CR28),0) -> 0 | CV28: =ROUND(($D$28/$E$3*CT28)+($D$28/$H$2*CU28),0) -> 0 | CY28: =ROUND(($D$28/$E$3*CW28)+($D$28/$H$2*CX28),0) -> 0 | DB28: =ROUND(($D$28/$E$3*CZ28)+($D$28/$H$2*DA28),0) -> 0
A29: 26 | B29: Ramu | C29: Die opr. | D29: 19000 | E29: =K29+N29+Q29+T29+W29+Z29+AC29+AF29+AI29+AL29+AO29+AR29+AU29+AX29+BA29+BD29+BG29+BJ29+BM29+BP29+BS29+BV29+BY29+CB29+CE29+CH29+CK29+CN29+CQ29+CT29+CW29+CZ29 -> 7 | F29: =ROUND(D29/$F$2*E29,0) -> 4290 | G29: =L29+O29+R29+U29+X29+AA29+AD29+AG29+AJ29+AM29+AP29+AS29+AV29+AY29+BB29+BE29+BH29+BK29+BN29+BQ29+BT29+BW29+BZ29+CC29+CF29+CI29+CL29+CO29+CR29+CU29+CX29+DA28 -> 18.5 | H29: =ROUND(D29/$H$2*G29,0) -> 1417 | I29: =F29+H29 -> 5707 | J29: =M29+P29+S29+V29+Y29+AB29+AE29+AH29+AK29+AN29+AQ29+AT29+AW29+AZ29+BC29+BF29+BI29+BL29+BO29+BR29+BU29+BX29+CA29+CD29+CG29+CJ29+CM29+CP29+CS29+CV29+CY29 -> 5707 | K29: 1 | L29: 3.5 | M29: =ROUND(($D$29/$E$3*K29)+($D$29/$H$2*L29),0) -> 881 | N29: 1 | P29: =ROUND(($D$29/$E$3*N29)+($D$29/$H$2*O29),0) -> 613 | Q29: 1 | R29: 3.5 | S29: =ROUND(($D$29/$E$3*Q29)+($D$29/$H$2*R29),0) -> 881 | T29: 1 | U29: 3.5 | V29: =ROUND(($D$29/$E$3*T29)+($D$29/$H$2*U29),0) -> 881 | W29: 1 | X29: 3.5 | Y29: =ROUND(($D$29/$E$3*W29)+($D$29/$H$2*X29),0) -> 881 | Z29: 1 | AA29: 2.5 | AB29: =ROUND(($D$29/$E$3*Z29)+($D$29/$H$2*AA29),0) -> 804 | AC29: 1 | AD29: 2 | AE29: =ROUND(($D$29/$E$3*AC29)+($D$29/$H$2*AD29),0) -> 766 | AH29: =ROUND(($D$29/$E$3*AF29)+($D$29/$H$2*AG29),0) -> 0 | AK29: =ROUND(($D$29/$E$3*AI29)+($D$29/$H$2*AJ29),0) -> 0 | AN29: =ROUND(($D$29/$E$3*AL29)+($D$29/$H$2*AM29),0) -> 0 | AQ29: =ROUND(($D$29/$E$3*AO29)+($D$29/$H$2*AP29),0) -> 0 | AT29: =ROUND(($D$29/$E$3*AR29)+($D$29/$H$2*AS29),0) -> 0 | AW29: =ROUND(($D$29/$E$3*AU29)+($D$29/$H$2*AV29),0) -> 0 | AZ29: =ROUND(($D$29/$E$3*AX29)+($D$29/$H$2*AY29),0) -> 0 | BC29: =ROUND(($D$29/$E$3*BA29)+($D$29/$H$2*BB29),0) -> 0 | BF29: =ROUND(($D$29/$E$3*BD29)+($D$29/$H$2*BE29),0) -> 0 | BI29: =ROUND(($D$29/$E$3*BG29)+($D$29/$H$2*BH29),0) -> 0 | BL29: =ROUND(($D$29/$E$3*BJ29)+($D$29/$H$2*BK29),0) -> 0 | BO29: =ROUND(($D$29/$E$3*BM29)+($D$29/$H$2*BN29),0) -> 0 | BR29: =ROUND(($D$29/$E$3*BP29)+($D$29/$H$2*BQ29),0) -> 0 | BU29: =ROUND(($D$29/$E$3*BS29)+($D$29/$H$2*BT29),0) -> 0 | BX29: =ROUND(($D$29/$E$3*BV29)+($D$29/$H$2*BW29),0) -> 0 | CA29: =ROUND(($D$29/$E$3*BY29)+($D$29/$H$2*BZ29),0) -> 0 | CD29: =ROUND(($D$29/$E$3*CB29)+($D$29/$H$2*CC29),0) -> 0 | CG29: =ROUND(($D$29/$E$3*CE29)+($D$29/$H$2*CF29),0) -> 0 | CJ29: =ROUND(($D$29/$E$3*CH29)+($D$29/$H$2*CI29),0) -> 0 | CM29: =ROUND(($D$29/$E$3*CK29)+($D$29/$H$2*CL29),0) -> 0 | CP29: =ROUND(($D$29/$E$3*CN29)+($D$29/$H$2*CO29),0) -> 0 | CS29: =ROUND(($D$29/$E$3*CQ29)+($D$29/$H$2*CR29),0) -> 0 | CV29: =ROUND(($D$29/$E$3*CT29)+($D$29/$H$2*CU29),0) -> 0 | CY29: =ROUND(($D$29/$E$3*CW29)+($D$29/$H$2*CX29),0) -> 0 | DB29: =ROUND(($D$29/$E$3*CZ29)+($D$29/$H$2*DA29),0) -> 0
A30: 27 | B30: Mukesh | C30: Helper | D30: 13500 | E30: =K30+N30+Q30+T30+W30+Z30+AC30+AF30+AI30+AL30+AO30+AR30+AU30+AX30+BA30+BD30+BG30+BJ30+BM30+BP30+BS30+BV30+BY30+CB30+CE30+CH30+CK30+CN30+CQ30+CT30+CW30+CZ30 -> 7 | F30: =ROUND(D30/$F$2*E30,0) -> 3048 | G30: =L30+O30+R30+U30+X30+AA30+AD30+AG30+AJ30+AM30+AP30+AS30+AV30+AY30+BB30+BE30+BH30+BK30+BN30+BQ30+BT30+BW30+BZ30+CC30+CF30+CI30+CL30+CO30+CR30+CU30+CX30+DA29 -> 17.5 | H30: =ROUND(D30/$H$2*G30,0) -> 953 | I30: =F30+H30 -> 4001 | J30: =M30+P30+S30+V30+Y30+AB30+AE30+AH30+AK30+AN30+AQ30+AT30+AW30+AZ30+BC30+BF30+BI30+BL30+BO30+BR30+BU30+BX30+CA30+CD30+CG30+CJ30+CM30+CP30+CS30+CV30+CY30 -> 4000 | K30: 1 | L30: 3.5 | M30: =ROUND(($D$30/$E$3*K30)+($D$30/$H$2*L30),0) -> 626 | N30: 1 | P30: =ROUND(($D$30/$E$3*N30)+($D$30/$H$2*O30),0) -> 435 | Q30: 1 | R30: 3.5 | S30: =ROUND(($D$30/$E$3*Q30)+($D$30/$H$2*R30),0) -> 626 | T30: 1 | U30: 3.5 | V30: =ROUND(($D$30/$E$3*T30)+($D$30/$H$2*U30),0) -> 626 | W30: 1 | X30: 3.5 | Y30: =ROUND(($D$30/$E$3*W30)+($D$30/$H$2*X30),0) -> 626 | Z30: 1 | AA30: 3.5 | AB30: =ROUND(($D$30/$E$3*Z30)+($D$30/$H$2*AA30),0) -> 626 | AC30: 1 | AE30: =ROUND(($D$30/$E$3*AC30)+($D$30/$H$2*AD30),0) -> 435 | AH30: =ROUND(($D$30/$E$3*AF30)+($D$30/$H$2*AG30),0) -> 0 | AK30: =ROUND(($D$30/$E$3*AI30)+($D$30/$H$2*AJ30),0) -> 0 | AN30: =ROUND(($D$30/$E$3*AL30)+($D$30/$H$2*AM30),0) -> 0 | AQ30: =ROUND(($D$30/$E$3*AO30)+($D$30/$H$2*AP30),0) -> 0 | AT30: =ROUND(($D$30/$E$3*AR30)+($D$30/$H$2*AS30),0) -> 0 | AW30: =ROUND(($D$30/$E$3*AU30)+($D$30/$H$2*AV30),0) -> 0 | AZ30: =ROUND(($D$30/$E$3*AX30)+($D$30/$H$2*AY30),0) -> 0 | BC30: =ROUND(($D$30/$E$3*BA30)+($D$30/$H$2*BB30),0) -> 0 | BF30: =ROUND(($D$30/$E$3*BD30)+($D$30/$H$2*BE30),0) -> 0 | BI30: =ROUND(($D$30/$E$3*BG30)+($D$30/$H$2*BH30),0) -> 0 | BL30: =ROUND(($D$30/$E$3*BJ30)+($D$30/$H$2*BK30),0) -> 0 | BO30: =ROUND(($D$30/$E$3*BM30)+($D$30/$H$2*BN30),0) -> 0 | BR30: =ROUND(($D$30/$E$3*BP30)+($D$30/$H$2*BQ30),0) -> 0 | BU30: =ROUND(($D$30/$E$3*BS30)+($D$30/$H$2*BT30),0) -> 0 | BX30: =ROUND(($D$30/$E$3*BV30)+($D$30/$H$2*BW30),0) -> 0 | CA30: =ROUND(($D$30/$E$3*BY30)+($D$30/$H$2*BZ30),0) -> 0 | CD30: =ROUND(($D$30/$E$3*CB30)+($D$30/$H$2*CC30),0) -> 0 | CG30: =ROUND(($D$30/$E$3*CE30)+($D$30/$H$2*CF30),0) -> 0 | CJ30: =ROUND(($D$30/$E$3*CH30)+($D$30/$H$2*CI30),0) -> 0 | CM30: =ROUND(($D$30/$E$3*CK30)+($D$30/$H$2*CL30),0) -> 0 | CP30: =ROUND(($D$30/$E$3*CN30)+($D$30/$H$2*CO30),0) -> 0 | CS30: =ROUND(($D$30/$E$3*CQ30)+($D$30/$H$2*CR30),0) -> 0 | CV30: =ROUND(($D$30/$E$3*CT30)+($D$30/$H$2*CU30),0) -> 0 | CY30: =ROUND(($D$30/$E$3*CW30)+($D$30/$H$2*CX30),0) -> 0 | DB30: =ROUND(($D$30/$E$3*CZ30)+($D$30/$H$2*DA30),0) -> 0
A31: 28 | B31: Sachin | C31: Helper | D31: 13500 | E31: =K31+N31+Q31+T31+W31+Z31+AC31+AF31+AI31+AL31+AO31+AR31+AU31+AX31+BA31+BD31+BG31+BJ31+BM31+BP31+BS31+BV31+BY31+CB31+CE31+CH31+CK31+CN31+CQ31+CT31+CW31+CZ31 -> 7 | F31: =ROUND(D31/$F$2*E31,0) -> 3048 | G31: =L31+O31+R31+U31+X31+AA31+AD31+AG31+AJ31+AM31+AP31+AS31+AV31+AY31+BB31+BE31+BH31+BK31+BN31+BQ31+BT31+BW31+BZ31+CC31+CF31+CI31+CL31+CO31+CR31+CU31+CX31+DA30 -> 21.5 | H31: =ROUND(D31/$H$2*G31,0) -> 1170 | I31: =F31+H31 -> 4218 | J31: =M31+P31+S31+V31+Y31+AB31+AE31+AH31+AK31+AN31+AQ31+AT31+AW31+AZ31+BC31+BF31+BI31+BL31+BO31+BR31+BU31+BX31+CA31+CD31+CG31+CJ31+CM31+CP31+CS31+CV31+CY31 -> 4218 | K31: 1 | L31: 7.5 | M31: =ROUND(($D$31/$E$3*K31)+($D$31/$H$2*L31),0) -> 844 | N31: 1 | P31: =ROUND(($D$31/$E$3*N31)+($D$31/$H$2*O31),0) -> 435 | Q31: 1 | S31: =ROUND(($D$31/$E$3*Q31)+($D$31/$H$2*R31),0) -> 435 | T31: 1 | U31: 3.5 | V31: =ROUND(($D$31/$E$3*T31)+($D$31/$H$2*U31),0) -> 626 | W31: 1 | X31: 3.5 | Y31: =ROUND(($D$31/$E$3*W31)+($D$31/$H$2*X31),0) -> 626 | Z31: 1 | AA31: 3.5 | AB31: =ROUND(($D$31/$E$3*Z31)+($D$31/$H$2*AA31),0) -> 626 | AC31: 1 | AD31: 3.5 | AE31: =ROUND(($D$31/$E$3*AC31)+($D$31/$H$2*AD31),0) -> 626 | AH31: =ROUND(($D$31/$E$3*AF31)+($D$31/$H$2*AG31),0) -> 0 | AK31: =ROUND(($D$31/$E$3*AI31)+($D$31/$H$2*AJ31),0) -> 0 | AN31: =ROUND(($D$31/$E$3*AL31)+($D$31/$H$2*AM31),0) -> 0 | AQ31: =ROUND(($D$31/$E$3*AO31)+($D$31/$H$2*AP31),0) -> 0 | AT31: =ROUND(($D$31/$E$3*AR31)+($D$31/$H$2*AS31),0) -> 0 | AW31: =ROUND(($D$31/$E$3*AU31)+($D$31/$H$2*AV31),0) -> 0 | AZ31: =ROUND(($D$31/$E$3*AX31)+($D$31/$H$2*AY31),0) -> 0 | BC31: =ROUND(($D$31/$E$3*BA31)+($D$31/$H$2*BB31),0) -> 0 | BF31: =ROUND(($D$31/$E$3*BD31)+($D$31/$H$2*BE31),0) -> 0 | BI31: =ROUND(($D$31/$E$3*BG31)+($D$31/$H$2*BH31),0) -> 0 | BL31: =ROUND(($D$31/$E$3*BJ31)+($D$31/$H$2*BK31),0) -> 0 | BO31: =ROUND(($D$31/$E$3*BM31)+($D$31/$H$2*BN31),0) -> 0 | BR31: =ROUND(($D$31/$E$3*BP31)+($D$31/$H$2*BQ31),0) -> 0 | BU31: =ROUND(($D$31/$E$3*BS31)+($D$31/$H$2*BT31),0) -> 0 | BX31: =ROUND(($D$31/$E$3*BV31)+($D$31/$H$2*BW31),0) -> 0 | CA31: =ROUND(($D$31/$E$3*BY31)+($D$31/$H$2*BZ31),0) -> 0 | CD31: =ROUND(($D$31/$E$3*CB31)+($D$31/$H$2*CC31),0) -> 0 | CG31: =ROUND(($D$31/$E$3*CE31)+($D$31/$H$2*CF31),0) -> 0 | CJ31: =ROUND(($D$31/$E$3*CH31)+($D$31/$H$2*CI31),0) -> 0 | CM31: =ROUND(($D$31/$E$3*CK31)+($D$31/$H$2*CL31),0) -> 0 | CP31: =ROUND(($D$31/$E$3*CN31)+($D$31/$H$2*CO31),0) -> 0 | CS31: =ROUND(($D$31/$E$3*CQ31)+($D$31/$H$2*CR31),0) -> 0 | CV31: =ROUND(($D$31/$E$3*CT31)+($D$31/$H$2*CU31),0) -> 0 | CY31: =ROUND(($D$31/$E$3*CW31)+($D$31/$H$2*CX31),0) -> 0 | DB31: =ROUND(($D$31/$E$3*CZ31)+($D$31/$H$2*DA31),0) -> 0
A32: 29 | B32: Kartik | C32: Helper | D32: 13500 | E32: =K32+N32+Q32+T32+W32+Z32+AC32+AF32+AI32+AL32+AO32+AR32+AU32+AX32+BA32+BD32+BG32+BJ32+BM32+BP32+BS32+BV32+BY32+CB32+CE32+CH32+CK32+CN32+CQ32+CT32+CW32+CZ32 -> 7 | F32: =ROUND(D32/$F$2*E32,0) -> 3048 | G32: =L32+O32+R32+U32+X32+AA32+AD32+AG32+AJ32+AM32+AP32+AS32+AV32+AY32+BB32+BE32+BH32+BK32+BN32+BQ32+BT32+BW32+BZ32+CC32+CF32+CI32+CL32+CO32+CR32+CU32+CX32+DA31 -> 25 | H32: =ROUND(D32/$H$2*G32,0) -> 1361 | I32: =F32+H32 -> 4409 | J32: =M32+P32+S32+V32+Y32+AB32+AE32+AH32+AK32+AN32+AQ32+AT32+AW32+AZ32+BC32+BF32+BI32+BL32+BO32+BR32+BU32+BX32+CA32+CD32+CG32+CJ32+CM32+CP32+CS32+CV32+CY32 -> 4409 | K32: 1 | L32: 3.5 | M32: =ROUND(($D$32/$E$3*K32)+($D$32/$H$2*L32),0) -> 626 | N32: 1 | P32: =ROUND(($D$32/$E$3*N32)+($D$32/$H$2*O32),0) -> 435 | Q32: 1 | R32: 7.5 | S32: =ROUND(($D$32/$E$3*Q32)+($D$32/$H$2*R32),0) -> 844 | T32: 1 | U32: 3.5 | V32: =ROUND(($D$32/$E$3*T32)+($D$32/$H$2*U32),0) -> 626 | W32: 1 | X32: 3.5 | Y32: =ROUND(($D$32/$E$3*W32)+($D$32/$H$2*X32),0) -> 626 | Z32: 1 | AA32: 3.5 | AB32: =ROUND(($D$32/$E$3*Z32)+($D$32/$H$2*AA32),0) -> 626 | AC32: 1 | AD32: 3.5 | AE32: =ROUND(($D$32/$E$3*AC32)+($D$32/$H$2*AD32),0) -> 626 | AH32: =ROUND(($D$32/$E$3*AF32)+($D$32/$H$2*AG32),0) -> 0 | AK32: =ROUND(($D$32/$E$3*AI32)+($D$32/$H$2*AJ32),0) -> 0 | AN32: =ROUND(($D$32/$E$3*AL32)+($D$32/$H$2*AM32),0) -> 0 | AQ32: =ROUND(($D$32/$E$3*AO32)+($D$32/$H$2*AP32),0) -> 0 | AT32: =ROUND(($D$32/$E$3*AR32)+($D$32/$H$2*AS32),0) -> 0 | AW32: =ROUND(($D$32/$E$3*AU32)+($D$32/$H$2*AV32),0) -> 0 | AZ32: =ROUND(($D$32/$E$3*AX32)+($D$32/$H$2*AY32),0) -> 0 | BC32: =ROUND(($D$32/$E$3*BA32)+($D$32/$H$2*BB32),0) -> 0 | BF32: =ROUND(($D$32/$E$3*BD32)+($D$32/$H$2*BE32),0) -> 0 | BI32: =ROUND(($D$32/$E$3*BG32)+($D$32/$H$2*BH32),0) -> 0 | BL32: =ROUND(($D$32/$E$3*BJ32)+($D$32/$H$2*BK32),0) -> 0 | BO32: =ROUND(($D$32/$E$3*BM32)+($D$32/$H$2*BN32),0) -> 0 | BR32: =ROUND(($D$32/$E$3*BP32)+($D$32/$H$2*BQ32),0) -> 0 | BU32: =ROUND(($D$32/$E$3*BS32)+($D$32/$H$2*BT32),0) -> 0 | BX32: =ROUND(($D$32/$E$3*BV32)+($D$32/$H$2*BW32),0) -> 0 | CA32: =ROUND(($D$32/$E$3*BY32)+($D$32/$H$2*BZ32),0) -> 0 | CD32: =ROUND(($D$32/$E$3*CB32)+($D$32/$H$2*CC32),0) -> 0 | CG32: =ROUND(($D$32/$E$3*CE32)+($D$32/$H$2*CF32),0) -> 0 | CJ32: =ROUND(($D$32/$E$3*CH32)+($D$32/$H$2*CI32),0) -> 0 | CM32: =ROUND(($D$32/$E$3*CK32)+($D$32/$H$2*CL32),0) -> 0 | CP32: =ROUND(($D$32/$E$3*CN32)+($D$32/$H$2*CO32),0) -> 0 | CS32: =ROUND(($D$32/$E$3*CQ32)+($D$32/$H$2*CR32),0) -> 0 | CV32: =ROUND(($D$32/$E$3*CT32)+($D$32/$H$2*CU32),0) -> 0 | CY32: =ROUND(($D$32/$E$3*CW32)+($D$32/$H$2*CX32),0) -> 0 | DB32: =ROUND(($D$32/$E$3*CZ32)+($D$32/$H$2*DA32),0) -> 0
A33: 30 | B33: Dilip | C33: Helper | D33: 16000 | E33: =K33+N33+Q33+T33+W33+Z33+AC33+AF33+AI33+AL33+AO33+AR33+AU33+AX33+BA33+BD33+BG33+BJ33+BM33+BP33+BS33+BV33+BY33+CB33+CE33+CH33+CK33+CN33+CQ33+CT33+CW33+CZ33 -> 6 | F33: =ROUND(D33/$F$2*E33,0) -> 3097 | G33: =L33+O33+R33+U33+X33+AA33+AD33+AG33+AJ33+AM33+AP33+AS33+AV33+AY33+BB33+BE33+BH33+BK33+BN33+BQ33+BT33+BW33+BZ33+CC33+CF33+CI33+CL33+CO33+CR33+CU33+CX33+DA32 -> 17.5 | H33: =ROUND(D33/$H$2*G33,0) -> 1129 | I33: =F33+H33 -> 4226 | J33: =M33+P33+S33+V33+Y33+AB33+AE33+AH33+AK33+AN33+AQ33+AT33+AW33+AZ33+BC33+BF33+BI33+BL33+BO33+BR33+BU33+BX33+CA33+CD33+CG33+CJ33+CM33+CP33+CS33+CV33+CY33 -> 4226 | K33: 1 | L33: 3.5 | M33: =ROUND(($D$33/$E$3*K33)+($D$33/$H$2*L33),0) -> 742 | N33: 1 | P33: =ROUND(($D$33/$E$3*N33)+($D$33/$H$2*O33),0) -> 516 | S33: =ROUND(($D$33/$E$3*Q33)+($D$33/$H$2*R33),0) -> 0 | T33: 1 | U33: 3.5 | V33: =ROUND(($D$33/$E$3*T33)+($D$33/$H$2*U33),0) -> 742 | W33: 1 | X33: 3.5 | Y33: =ROUND(($D$33/$E$3*W33)+($D$33/$H$2*X33),0) -> 742 | Z33: 1 | AA33: 3.5 | AB33: =ROUND(($D$33/$E$3*Z33)+($D$33/$H$2*AA33),0) -> 742 | AC33: 1 | AD33: 3.5 | AE33: =ROUND(($D$33/$E$3*AC33)+($D$33/$H$2*AD33),0) -> 742 | AH33: =ROUND(($D$33/$E$3*AF33)+($D$33/$H$2*AG33),0) -> 0 | AK33: =ROUND(($D$33/$E$3*AI33)+($D$33/$H$2*AJ33),0) -> 0 | AN33: =ROUND(($D$33/$E$3*AL33)+($D$33/$H$2*AM33),0) -> 0 | AQ33: =ROUND(($D$33/$E$3*AO33)+($D$33/$H$2*AP33),0) -> 0 | AT33: =ROUND(($D$33/$E$3*AR33)+($D$33/$H$2*AS33),0) -> 0 | AW33: =ROUND(($D$33/$E$3*AU33)+($D$33/$H$2*AV33),0) -> 0 | AZ33: =ROUND(($D$33/$E$3*AX33)+($D$33/$H$2*AY33),0) -> 0 | BC33: =ROUND(($D$33/$E$3*BA33)+($D$33/$H$2*BB33),0) -> 0 | BF33: =ROUND(($D$33/$E$3*BD33)+($D$33/$H$2*BE33),0) -> 0 | BI33: =ROUND(($D$33/$E$3*BG33)+($D$33/$H$2*BH33),0) -> 0 | BL33: =ROUND(($D$33/$E$3*BJ33)+($D$33/$H$2*BK33),0) -> 0 | BO33: =ROUND(($D$33/$E$3*BM33)+($D$33/$H$2*BN33),0) -> 0 | BR33: =ROUND(($D$33/$E$3*BP33)+($D$33/$H$2*BQ33),0) -> 0 | BU33: =ROUND(($D$33/$E$3*BS33)+($D$33/$H$2*BT33),0) -> 0 | BX33: =ROUND(($D$33/$E$3*BV33)+($D$33/$H$2*BW33),0) -> 0 | CA33: =ROUND(($D$33/$E$3*BY33)+($D$33/$H$2*BZ33),0) -> 0 | CD33: =ROUND(($D$33/$E$3*CB33)+($D$33/$H$2*CC33),0) -> 0 | CG33: =ROUND(($D$33/$E$3*CE33)+($D$33/$H$2*CF33),0) -> 0 | CJ33: =ROUND(($D$33/$E$3*CH33)+($D$33/$H$2*CI33),0) -> 0 | CM33: =ROUND(($D$33/$E$3*CK33)+($D$33/$H$2*CL33),0) -> 0 | CP33: =ROUND(($D$33/$E$3*CN33)+($D$33/$H$2*CO33),0) -> 0 | CS33: =ROUND(($D$33/$E$3*CQ33)+($D$33/$H$2*CR33),0) -> 0 | CV33: =ROUND(($D$33/$E$3*CT33)+($D$33/$H$2*CU33),0) -> 0 | CY33: =ROUND(($D$33/$E$3*CW33)+($D$33/$H$2*CX33),0) -> 0 | DB33: =ROUND(($D$33/$E$3*CZ33)+($D$33/$H$2*DA33),0) -> 0
A34: 31 | B34: Ravindra | C34: Pasting | D34: 16500 | E34: =K34+N34+Q34+T34+W34+Z34+AC34+AF34+AI34+AL34+AO34+AR34+AU34+AX34+BA34+BD34+BG34+BJ34+BM34+BP34+BS34+BV34+BY34+CB34+CE34+CH34+CK34+CN34+CQ34+CT34+CW34+CZ34 -> 7 | F34: =ROUND(D34/$F$2*E34,0) -> 3726 | G34: =L34+O34+R34+U34+X34+AA34+AD34+AG34+AJ34+AM34+AP34+AS34+AV34+AY34+BB34+BE34+BH34+BK34+BN34+BQ34+BT34+BW34+BZ34+CC34+CF34+CI34+CL34+CO34+CR34+CU34+CX34+DA33 -> 30 | H34: =ROUND(D34/$H$2*G34,0) -> 1996 | I34: =F34+H34 -> 5722 | J34: =M34+P34+S34+V34+Y34+AB34+AE34+AH34+AK34+AN34+AQ34+AT34+AW34+AZ34+BC34+BF34+BI34+BL34+BO34+BR34+BU34+BX34+CA34+CD34+CG34+CJ34+CM34+CP34+CS34+CV34+CY34 -> 5721 | K34: 1 | L34: 3.5 | M34: =ROUND(($D$34/$E$3*K34)+($D$34/$H$2*L34),0) -> 765 | N34: 1 | O34: 8 | P34: =ROUND(($D$34/$E$3*N34)+($D$34/$H$2*O34),0) -> 1065 | Q34: 1 | R34: 7.5 | S34: =ROUND(($D$34/$E$3*Q34)+($D$34/$H$2*R34),0) -> 1031 | T34: 1 | U34: 3.5 | V34: =ROUND(($D$34/$E$3*T34)+($D$34/$H$2*U34),0) -> 765 | W34: 1 | X34: -3.5 | Y34: =ROUND(($D$34/$E$3*W34)+($D$34/$H$2*X34),0) -> 299 | Z34: 1 | AA34: 7.5 | AB34: =ROUND(($D$34/$E$3*Z34)+($D$34/$H$2*AA34),0) -> 1031 | AC34: 1 | AD34: 3.5 | AE34: =ROUND(($D$34/$E$3*AC34)+($D$34/$H$2*AD34),0) -> 765 | AH34: =ROUND(($D$34/$E$3*AF34)+($D$34/$H$2*AG34),0) -> 0 | AK34: =ROUND(($D$34/$E$3*AI34)+($D$34/$H$2*AJ34),0) -> 0 | AN34: =ROUND(($D$34/$E$3*AL34)+($D$34/$H$2*AM34),0) -> 0 | AQ34: =ROUND(($D$34/$E$3*AO34)+($D$34/$H$2*AP34),0) -> 0 | AT34: =ROUND(($D$34/$E$3*AR34)+($D$34/$H$2*AS34),0) -> 0 | AW34: =ROUND(($D$34/$E$3*AU34)+($D$34/$H$2*AV34),0) -> 0 | AZ34: =ROUND(($D$34/$E$3*AX34)+($D$34/$H$2*AY34),0) -> 0 | BC34: =ROUND(($D$34/$E$3*BA34)+($D$34/$H$2*BB34),0) -> 0 | BF34: =ROUND(($D$34/$E$3*BD34)+($D$34/$H$2*BE34),0) -> 0 | BI34: =ROUND(($D$34/$E$3*BG34)+($D$34/$H$2*BH34),0) -> 0 | BL34: =ROUND(($D$34/$E$3*BJ34)+($D$34/$H$2*BK34),0) -> 0 | BO34: =ROUND(($D$34/$E$3*BM34)+($D$34/$H$2*BN34),0) -> 0 | BR34: =ROUND(($D$34/$E$3*BP34)+($D$34/$H$2*BQ34),0) -> 0 | BU34: =ROUND(($D$34/$E$3*BS34)+($D$34/$H$2*BT34),0) -> 0 | BX34: =ROUND(($D$34/$E$3*BV34)+($D$34/$H$2*BW34),0) -> 0 | CA34: =ROUND(($D$34/$E$3*BY34)+($D$34/$H$2*BZ34),0) -> 0 | CD34: =ROUND(($D$34/$E$3*CB34)+($D$34/$H$2*CC34),0) -> 0 | CG34: =ROUND(($D$34/$E$3*CE34)+($D$34/$H$2*CF34),0) -> 0 | CJ34: =ROUND(($D$34/$E$3*CH34)+($D$34/$H$2*CI34),0) -> 0 | CM34: =ROUND(($D$34/$E$3*CK34)+($D$34/$H$2*CL34),0) -> 0 | CP34: =ROUND(($D$34/$E$3*CN34)+($D$34/$H$2*CO34),0) -> 0 | CS34: =ROUND(($D$34/$E$3*CQ34)+($D$34/$H$2*CR34),0) -> 0 | CV34: =ROUND(($D$34/$E$3*CT34)+($D$34/$H$2*CU34),0) -> 0 | CY34: =ROUND(($D$34/$E$3*CW34)+($D$34/$H$2*CX34),0) -> 0 | DB34: =ROUND(($D$34/$E$3*CZ34)+($D$34/$H$2*DA34),0) -> 0
A35: 32 | B35: Meena | C35: Helper | D35: 11500 | E35: =K35+N35+Q35+T35+W35+Z35+AC35+AF35+AI35+AL35+AO35+AR35+AU35+AX35+BA35+BD35+BG35+BJ35+BM35+BP35+BS35+BV35+BY35+CB35+CE35+CH35+CK35+CN35+CQ35+CT35+CW35+CZ35 -> 7 | F35: =ROUND(D35/$F$2*E35,0) -> 2597 | G35: =L35+O35+R35+U35+X35+AA35+AD35+AG35+AJ35+AM35+AP35+AS35+AV35+AY35+BB35+BE35+BH35+BK35+BN35+BQ35+BT35+BW35+BZ35+CC35+CF35+CI35+CL35+CO35+CR35+CU35+CX35+DA34 -> 25 | H35: =ROUND(D35/$H$2*G35,0) -> 1159 | I35: =F35+H35 -> 3756 | J35: =M35+P35+S35+V35+Y35+AB35+AE35+AH35+AK35+AN35+AQ35+AT35+AW35+AZ35+BC35+BF35+BI35+BL35+BO35+BR35+BU35+BX35+CA35+CD35+CG35+CJ35+CM35+CP35+CS35+CV35+CY35 -> 3755 | K35: 1 | L35: 3.5 | M35: =ROUND(($D$35/$E$3*K35)+($D$35/$H$2*L35),0) -> 533 | N35: 1 | O35: 8 | P35: =ROUND(($D$35/$E$3*N35)+($D$35/$H$2*O35),0) -> 742 | Q35: 1 | R35: 3.5 | S35: =ROUND(($D$35/$E$3*Q35)+($D$35/$H$2*R35),0) -> 533 | T35: 1 | U35: 3.5 | V35: =ROUND(($D$35/$E$3*T35)+($D$35/$H$2*U35),0) -> 533 | W35: 1 | X35: -0.5 | Y35: =ROUND(($D$35/$E$3*W35)+($D$35/$H$2*X35),0) -> 348 | Z35: 1 | AA35: 3.5 | AB35: =ROUND(($D$35/$E$3*Z35)+($D$35/$H$2*AA35),0) -> 533 | AC35: 1 | AD35: 3.5 | AE35: =ROUND(($D$35/$E$3*AC35)+($D$35/$H$2*AD35),0) -> 533 | AH35: =ROUND(($D$35/$E$3*AF35)+($D$35/$H$2*AG35),0) -> 0 | AK35: =ROUND(($D$35/$E$3*AI35)+($D$35/$H$2*AJ35),0) -> 0 | AN35: =ROUND(($D$35/$E$3*AL35)+($D$35/$H$2*AM35),0) -> 0 | AQ35: =ROUND(($D$35/$E$3*AO35)+($D$35/$H$2*AP35),0) -> 0 | AT35: =ROUND(($D$35/$E$3*AR35)+($D$35/$H$2*AS35),0) -> 0 | AW35: =ROUND(($D$35/$E$3*AU35)+($D$35/$H$2*AV35),0) -> 0 | AZ35: =ROUND(($D$35/$E$3*AX35)+($D$35/$H$2*AY35),0) -> 0 | BC35: =ROUND(($D$35/$E$3*BA35)+($D$35/$H$2*BB35),0) -> 0 | BF35: =ROUND(($D$35/$E$3*BD35)+($D$35/$H$2*BE35),0) -> 0 | BI35: =ROUND(($D$35/$E$3*BG35)+($D$35/$H$2*BH35),0) -> 0 | BL35: =ROUND(($D$35/$E$3*BJ35)+($D$35/$H$2*BK35),0) -> 0 | BO35: =ROUND(($D$35/$E$3*BM35)+($D$35/$H$2*BN35),0) -> 0 | BR35: =ROUND(($D$35/$E$3*BP35)+($D$35/$H$2*BQ35),0) -> 0 | BU35: =ROUND(($D$35/$E$3*BS35)+($D$35/$H$2*BT35),0) -> 0 | BX35: =ROUND(($D$35/$E$3*BV35)+($D$35/$H$2*BW35),0) -> 0 | CA35: =ROUND(($D$35/$E$3*BY35)+($D$35/$H$2*BZ35),0) -> 0 | CD35: =ROUND(($D$35/$E$3*CB35)+($D$35/$H$2*CC35),0) -> 0 | CG35: =ROUND(($D$35/$E$3*CE35)+($D$35/$H$2*CF35),0) -> 0 | CJ35: =ROUND(($D$35/$E$3*CH35)+($D$35/$H$2*CI35),0) -> 0 | CM35: =ROUND(($D$35/$E$3*CK35)+($D$35/$H$2*CL35),0) -> 0 | CP35: =ROUND(($D$35/$E$3*CN35)+($D$35/$H$2*CO35),0) -> 0 | CS35: =ROUND(($D$35/$E$3*CQ35)+($D$35/$H$2*CR35),0) -> 0 | CV35: =ROUND(($D$35/$E$3*CT35)+($D$35/$H$2*CU35),0) -> 0 | CY35: =ROUND(($D$35/$E$3*CW35)+($D$35/$H$2*CX35),0) -> 0 | DB35: =ROUND(($D$35/$E$3*CZ35)+($D$35/$H$2*DA35),0) -> 0
A36: 33 | B36: Phekan Mandal | C36: Sweeper | D36: 14500 | E36: =K36+N36+Q36+T36+W36+Z36+AC36+AF36+AI36+AL36+AO36+AR36+AU36+AX36+BA36+BD36+BG36+BJ36+BM36+BP36+BS36+BV36+BY36+CB36+CE36+CH36+CK36+CN36+CQ36+CT36+CW36+CZ36 -> 7 | F36: =ROUND(D36/$F$2*E36,0) -> 3274 | G36: =L36+O36+R36+U36+X36+AA36+AD36+AG36+AJ36+AM36+AP36+AS36+AV36+AY36+BB36+BE36+BH36+BK36+BN36+BQ36+BT36+BW36+BZ36+CC36+CF36+CI36+CL36+CO36+CR36+CU36+CX36+DA35 -> 9 | H36: =ROUND(D36/$H$2*G36,0) -> 526 | I36: =F36+H36 -> 3800 | J36: =M36+P36+S36+V36+Y36+AB36+AE36+AH36+AK36+AN36+AQ36+AT36+AW36+AZ36+BC36+BF36+BI36+BL36+BO36+BR36+BU36+BX36+CA36+CD36+CG36+CJ36+CM36+CP36+CS36+CV36+CY36 -> 3799 | K36: 1 | L36: 3.5 | M36: =ROUND(($D$36/$E$3*K36)+($D$36/$H$2*L36),0) -> 672 | N36: 1 | P36: =ROUND(($D$36/$E$3*N36)+($D$36/$H$2*O36),0) -> 468 | Q36: 1 | R36: 3.5 | S36: =ROUND(($D$36/$E$3*Q36)+($D$36/$H$2*R36),0) -> 672 | T36: 1 | U36: 3.5 | V36: =ROUND(($D$36/$E$3*T36)+($D$36/$H$2*U36),0) -> 672 | W36: 1 | X36: 3.5 | Y36: =ROUND(($D$36/$E$3*W36)+($D$36/$H$2*X36),0) -> 672 | Z36: 1 | AA36: -2 | AB36: =ROUND(($D$36/$E$3*Z36)+($D$36/$H$2*AA36),0) -> 351 | AC36: 1 | AD36: -3 | AE36: =ROUND(($D$36/$E$3*AC36)+($D$36/$H$2*AD36),0) -> 292 | AH36: =ROUND(($D$36/$E$3*AF36)+($D$36/$H$2*AG36),0) -> 0 | AK36: =ROUND(($D$36/$E$3*AI36)+($D$36/$H$2*AJ36),0) -> 0 | AN36: =ROUND(($D$36/$E$3*AL36)+($D$36/$H$2*AM36),0) -> 0 | AQ36: =ROUND(($D$36/$E$3*AO36)+($D$36/$H$2*AP36),0) -> 0 | AT36: =ROUND(($D$36/$E$3*AR36)+($D$36/$H$2*AS36),0) -> 0 | AW36: =ROUND(($D$36/$E$3*AU36)+($D$36/$H$2*AV36),0) -> 0 | AZ36: =ROUND(($D$36/$E$3*AX36)+($D$36/$H$2*AY36),0) -> 0 | BC36: =ROUND(($D$36/$E$3*BA36)+($D$36/$H$2*BB36),0) -> 0 | BF36: =ROUND(($D$36/$E$3*BD36)+($D$36/$H$2*BE36),0) -> 0 | BI36: =ROUND(($D$36/$E$3*BG36)+($D$36/$H$2*BH36),0) -> 0 | BL36: =ROUND(($D$36/$E$3*BJ36)+($D$36/$H$2*BK36),0) -> 0 | BO36: =ROUND(($D$36/$E$3*BM36)+($D$36/$H$2*BN36),0) -> 0 | BR36: =ROUND(($D$36/$E$3*BP36)+($D$36/$H$2*BQ36),0) -> 0 | BU36: =ROUND(($D$36/$E$3*BS36)+($D$36/$H$2*BT36),0) -> 0 | BX36: =ROUND(($D$36/$E$3*BV36)+($D$36/$H$2*BW36),0) -> 0 | CA36: =ROUND(($D$36/$E$3*BY36)+($D$36/$H$2*BZ36),0) -> 0 | CD36: =ROUND(($D$36/$E$3*CB36)+($D$36/$H$2*CC36),0) -> 0 | CG36: =ROUND(($D$36/$E$3*CE36)+($D$36/$H$2*CF36),0) -> 0 | CJ36: =ROUND(($D$36/$E$3*CH36)+($D$36/$H$2*CI36),0) -> 0 | CM36: =ROUND(($D$36/$E$3*CK36)+($D$36/$H$2*CL36),0) -> 0 | CP36: =ROUND(($D$36/$E$3*CN36)+($D$36/$H$2*CO36),0) -> 0 | CS36: =ROUND(($D$36/$E$3*CQ36)+($D$36/$H$2*CR36),0) -> 0 | CV36: =ROUND(($D$36/$E$3*CT36)+($D$36/$H$2*CU36),0) -> 0 | CY36: =ROUND(($D$36/$E$3*CW36)+($D$36/$H$2*CX36),0) -> 0 | DB36: =ROUND(($D$36/$E$3*CZ36)+($D$36/$H$2*DA36),0) -> 0
A37: 34 | B37: Raju | C37: Helper | D37: 14500 | E37: =K37+N37+Q37+T37+W37+Z37+AC37+AF37+AI37+AL37+AO37+AR37+AU37+AX37+BA37+BD37+BG37+BJ37+BM37+BP37+BS37+BV37+BY37+CB37+CE37+CH37+CK37+CN37+CQ37+CT37+CW37+CZ37 -> 6 | F37: =ROUND(D37/$F$2*E37,0) -> 2806 | G37: =L37+O37+R37+U37+X37+AA37+AD37+AG37+AJ37+AM37+AP37+AS37+AV37+AY37+BB37+BE37+BH37+BK37+BN37+BQ37+BT37+BW37+BZ37+CC37+CF37+CI37+CL37+CO37+CR37+CU37+CX37+DA36 -> 17.5 | H37: =ROUND(D37/$H$2*G37,0) -> 1023 | I37: =F37+H37 -> 3829 | J37: =M37+P37+S37+V37+Y37+AB37+AE37+AH37+AK37+AN37+AQ37+AT37+AW37+AZ37+BC37+BF37+BI37+BL37+BO37+BR37+BU37+BX37+CA37+CD37+CG37+CJ37+CM37+CP37+CS37+CV37+CY37 -> 3828 | M37: =ROUND(($D$37/$E$3*K37)+($D$37/$H$2*L37),0) -> 0 | N37: 1 | P37: =ROUND(($D$37/$E$3*N37)+($D$37/$H$2*O37),0) -> 468 | Q37: 1 | R37: 3.5 | S37: =ROUND(($D$37/$E$3*Q37)+($D$37/$H$2*R37),0) -> 672 | T37: 1 | U37: 3.5 | V37: =ROUND(($D$37/$E$3*T37)+($D$37/$H$2*U37),0) -> 672 | W37: 1 | X37: 3.5 | Y37: =ROUND(($D$37/$E$3*W37)+($D$37/$H$2*X37),0) -> 672 | Z37: 1 | AA37: 3.5 | AB37: =ROUND(($D$37/$E$3*Z37)+($D$37/$H$2*AA37),0) -> 672 | AC37: 1 | AD37: 3.5 | AE37: =ROUND(($D$37/$E$3*AC37)+($D$37/$H$2*AD37),0) -> 672 | AH37: =ROUND(($D$37/$E$3*AF37)+($D$37/$H$2*AG37),0) -> 0 | AK37: =ROUND(($D$37/$E$3*AI37)+($D$37/$H$2*AJ37),0) -> 0 | AN37: =ROUND(($D$37/$E$3*AL37)+($D$37/$H$2*AM37),0) -> 0 | AQ37: =ROUND(($D$37/$E$3*AO37)+($D$37/$H$2*AP37),0) -> 0 | AT37: =ROUND(($D$37/$E$3*AR37)+($D$37/$H$2*AS37),0) -> 0 | AW37: =ROUND(($D$37/$E$3*AU37)+($D$37/$H$2*AV37),0) -> 0 | AZ37: =ROUND(($D$37/$E$3*AX37)+($D$37/$H$2*AY37),0) -> 0 | BC37: =ROUND(($D$37/$E$3*BA37)+($D$37/$H$2*BB37),0) -> 0 | BF37: =ROUND(($D$37/$E$3*BD37)+($D$37/$H$2*BE37),0) -> 0 | BI37: =ROUND(($D$37/$E$3*BG37)+($D$37/$H$2*BH37),0) -> 0 | BL37: =ROUND(($D$37/$E$3*BJ37)+($D$37/$H$2*BK37),0) -> 0 | BO37: =ROUND(($D$37/$E$3*BM37)+($D$37/$H$2*BN37),0) -> 0 | BR37: =ROUND(($D$37/$E$3*BP37)+($D$37/$H$2*BQ37),0) -> 0 | BU37: =ROUND(($D$37/$E$3*BS37)+($D$37/$H$2*BT37),0) -> 0 | BX37: =ROUND(($D$37/$E$3*BV37)+($D$37/$H$2*BW37),0) -> 0 | CA37: =ROUND(($D$37/$E$3*BY37)+($D$37/$H$2*BZ37),0) -> 0 | CD37: =ROUND(($D$37/$E$3*CB37)+($D$37/$H$2*CC37),0) -> 0 | CG37: =ROUND(($D$37/$E$3*CE37)+($D$37/$H$2*CF37),0) -> 0 | CJ37: =ROUND(($D$37/$E$3*CH37)+($D$37/$H$2*CI37),0) -> 0 | CM37: =ROUND(($D$37/$E$3*CK37)+($D$37/$H$2*CL37),0) -> 0 | CP37: =ROUND(($D$37/$E$3*CN37)+($D$37/$H$2*CO37),0) -> 0 | CS37: =ROUND(($D$37/$E$3*CQ37)+($D$37/$H$2*CR37),0) -> 0 | CV37: =ROUND(($D$37/$E$3*CT37)+($D$37/$H$2*CU37),0) -> 0 | CY37: =ROUND(($D$37/$E$3*CW37)+($D$37/$H$2*CX37),0) -> 0 | DB37: =ROUND(($D$37/$E$3*CZ37)+($D$37/$H$2*DA37),0) -> 0
A38: 6 | B38: Amit Sahni | C38: Operator | D38: 17000 | E38: =K38+N38+Q38+T38+W38+Z38+AC38+AF38+AI38+AL38+AO38+AR38+AU38+AX38+BA38+BD38+BG38+BJ38+BM38+BP38+BS38+BV38+BY38+CB38+CE38+CH38+CK38+CN38+CQ38+CT38+CW38+CZ38 -> 7 | F38: =ROUND(D38/$F$2*E38,0) -> 3839 | G38: =L38+O38+R38+U38+X38+AA38+AD38+AG38+AJ38+AM38+AP38+AS38+AV38+AY38+BB38+BE38+BH38+BK38+BN38+BQ38+BT38+BW38+BZ38+CC38+CF38+CI38+CL38+CO38+CR38+CU38+CX38+DA38 -> 37 | H38: =ROUND(D38/$H$2*G38,0) -> 2536 | I38: =F38+H38 -> 6375 | J38: =M38+P38+S38+V38+Y38+AB38+AE38+AH38+AK38+AN38+AQ38+AT38+AW38+AZ38+BC38+BF38+BI38+BL38+BO38+BR38+BU38+BX38+CA38+CD38+CG38+CJ38+CM38+CP38+CS38+CV38+CY38 -> 6375 | K38: 1 | L38: 3.5 | M38: =round(($D$38/$F$2)*K38+($D$38/$H$2)*L38,0) -> 788 | N38: 1 | O38: 8 | P38: =round(($D$38/$F$2)*N38+($D$38/$H$2)*O38,0) -> 1097 | Q38: 1 | R38: 3.5 | S38: =round(($D$38/$F$2)*Q38+($D$38/$H$2)*R38,0) -> 788 | T38: 1 | U38: 7.5 | V38: =round(($D$38/$F$2)*T38+($D$38/$H$2)*U38,0) -> 1063 | W38: 1 | X38: 3.5 | Y38: =round(($D$38/$F$2)*W38+($D$38/$H$2)*X38,0) -> 788 | Z38: 1 | AA38: 7.5 | AB38: =round(($D$38/$F$2)*Z38+($D$38/$H$2)*AA38,0) -> 1063 | AC38: 1 | AD38: 3.5 | AE38: =round(($D$38/$F$2)*AC38+($D$38/$H$2)*AD38,0) -> 788 | AH38: =round(($D$38/$F$2)*AF38+($D$38/$H$2)*AG38,0) -> 0 | AK38: =round(($D$38/$F$2)*AI38+($D$38/$H$2)*AJ38,0) -> 0 | AN38: =round(($D$38/$F$2)*AL38+($D$38/$H$2)*AM38,0) -> 0 | AQ38: =round(($D$38/$F$2)*AO38+($D$38/$H$2)*AP38,0) -> 0 | AT38: =round(($D$38/$F$2)*AR38+($D$38/$H$2)*AS38,0) -> 0 | AW38: =round(($D$38/$F$2)*AU38+($D$38/$H$2)*AV38,0) -> 0 | AZ38: =round(($D$38/$F$2)*AX38+($D$38/$H$2)*AY38,0) -> 0 | BC38: =round(($D$38/$F$2)*BA38+($D$38/$H$2)*BB38,0) -> 0 | BF38: =round(($D$38/$F$2)*BD38+($D$38/$H$2)*BE38,0) -> 0 | BI38: =round(($D$38/$F$2)*BG38+($D$38/$H$2)*BH38,0) -> 0 | BL38: =round(($D$38/$F$2)*BJ38+($D$38/$H$2)*BK38,0) -> 0 | BO38: =round(($D$38/$F$2)*BM38+($D$38/$H$2)*BN38,0) -> 0 | BR38: =round(($D$38/$F$2)*BP38+($D$38/$H$2)*BQ38,0) -> 0 | BU38: =round(($D$38/$F$2)*BS38+($D$38/$H$2)*BT38,0) -> 0 | BX38: =round(($D$38/$F$2)*BV38+($D$38/$H$2)*BW38,0) -> 0 | CA38: =round(($D$38/$F$2)*BY38+($D$38/$H$2)*BZ38,0) -> 0 | CD38: =round(($D$38/$F$2)*CB38+($D$38/$H$2)*CC38,0) -> 0 | CG38: =round(($D$38/$F$2)*CE38+($D$38/$H$2)*CF38,0) -> 0 | CJ38: =round(($D$38/$F$2)*CH38+($D$38/$H$2)*CI38,0) -> 0 | CM38: =round(($D$38/$F$2)*CK38+($D$38/$H$2)*CL38,0) -> 0 | CP38: =round(($D$38/$F$2)*CN38+($D$38/$H$2)*CO38,0) -> 0 | CS38: =round(($D$38/$F$2)*CQ38+($D$38/$H$2)*CR38,0) -> 0 | CV38: =round(($D$38/$F$2)*CT38+($D$38/$H$2)*CU38,0) -> 0 | CY38: =round(($D$38/$F$2)*CW38+($D$38/$H$2)*CX38,0) -> 0 | DB38: =round(($D$38/$F$2)*CZ38+($D$38/$H$2)*DA38,0) -> 0
A39: 7 | B39: Ravita | C39: Helper | D39: 11500 | E39: =K39+N39+Q39+T39+W39+Z39+AC39+AF39+AI39+AL39+AO39+AR39+AU39+AX39+BA39+BD39+BG39+BJ39+BM39+BP39+BS39+BV39+BY39+CB39+CE39+CH39+CK39+CN39+CQ39+CT39+CW39+CZ39 -> 7 | F39: =ROUND(D39/$F$2*E39,0) -> 2597 | G39: =L39+O39+R39+U39+X39+AA39+AD39+AG39+AJ39+AM39+AP39+AS39+AV39+AY39+BB39+BE39+BH39+BK39+BN39+BQ39+BT39+BW39+BZ39+CC39+CF39+CI39+CL39+CO39+CR39+CU39+CX39+DA39 -> 29 | H39: =ROUND(D39/$H$2*G39,0) -> 1345 | I39: =F39+H39 -> 3942 | J39: =M39+P39+S39+V39+Y39+AB39+AE39+AH39+AK39+AN39+AQ39+AT39+AW39+AZ39+BC39+BF39+BI39+BL39+BO39+BR39+BU39+BX39+CA39+CD39+CG39+CJ39+CM39+CP39+CS39+CV39+CY39 -> 3940 | K39: 1 | L39: 3.5 | M39: =round((D39/$F$2)*K39+(D39/$H$2)*L39,0) -> 533 | N39: 1 | O39: 8 | P39: =round((D39/$F$2)*N39+(D39/$H$2)*O39,0) -> 742 | Q39: 1 | R39: 3.5 | S39: =round((D39/$F$2)*Q39+(D39/$H$2)*R39,0) -> 533 | T39: 1 | U39: 3.5 | V39: =round(($D$39/$F$2)*T39+($D$39/$H$2)*U39,0) -> 533 | W39: 1 | X39: 3.5 | Y39: =round(($D$39/$F$2)*W39+($D$39/$H$2)*X39,0) -> 533 | Z39: 1 | AA39: 3.5 | AB39: =round(($D$39/$F$2)*Z39+($D$39/$H$2)*AA39,0) -> 533 | AC39: 1 | AD39: 3.5 | AE39: =round(($D$39/$F$2)*AC39+($D$39/$H$2)*AD39,0) -> 533 | AH39: =round(($D$39/$F$2)*AF39+($D$39/$H$2)*AG39,0) -> 0 | AK39: =round(($D$39/$F$2)*AI39+($D$39/$H$2)*AJ39,0) -> 0 | AN39: =round(($D$39/$F$2)*AL39+($D$39/$H$2)*AM39,0) -> 0 | AQ39: =round(($D$39/$F$2)*AO39+($D$39/$H$2)*AP39,0) -> 0 | AT39: =round(($D$39/$F$2)*AR39+($D$39/$H$2)*AS39,0) -> 0 | AW39: =round(($D$39/$F$2)*AU39+($D$39/$H$2)*AV39,0) -> 0 | AZ39: =round(($D$39/$F$2)*AX39+($D$39/$H$2)*AY39,0) -> 0 | BC39: =round(($D$39/$F$2)*BA39+($D$39/$H$2)*BB39,0) -> 0 | BF39: =round(($D$39/$F$2)*BD39+($D$39/$H$2)*BE39,0) -> 0 | BI39: =round(($D$39/$F$2)*BG39+($D$39/$H$2)*BH39,0) -> 0 | BL39: =round(($D$39/$F$2)*BJ39+($D$39/$H$2)*BK39,0) -> 0 | BO39: =round(($D$39/$F$2)*BM39+($D$39/$H$2)*BN39,0) -> 0 | BR39: =round(($D$39/$F$2)*BP39+($D$39/$H$2)*BQ39,0) -> 0 | BU39: =round(($D$39/$F$2)*BS39+($D$39/$H$2)*BT39,0) -> 0 | BX39: =round(($D$39/$F$2)*BV39+($D$39/$H$2)*BW39,0) -> 0 | CA39: =round(($D$39/$F$2)*BY39+($D$39/$H$2)*BZ39,0) -> 0 | CD39: =round(($D$39/$F$2)*CB39+($D$39/$H$2)*CC39,0) -> 0 | CG39: =round(($D$39/$F$2)*CE39+($D$39/$H$2)*CF39,0) -> 0 | CJ39: =round(($D$39/$F$2)*CH39+($D$39/$H$2)*CI39,0) -> 0 | CM39: =round(($D$39/$F$2)*CK39+($D$39/$H$2)*CL39,0) -> 0 | CP39: =round(($D$39/$F$2)*CN39+($D$39/$H$2)*CO39,0) -> 0 | CS39: =round(($D$39/$F$2)*CQ39+($D$39/$H$2)*CR39,0) -> 0 | CV39: =round(($D$39/$F$2)*CT39+($D$39/$H$2)*CU39,0) -> 0 | CY39: =round(($D$39/$F$2)*CW39+($D$39/$H$2)*CX39,0) -> 0 | DB39: =round(($D$39/$F$2)*CZ39+($D$39/$H$2)*DA39,0) -> 0
A40: 8 | B40: Amarjeet | C40: Helper | D40: 13500 | E40: =K40+N40+Q40+T40+W40+Z40+AC40+AF40+AI40+AL40+AO40+AR40+AU40+AX40+BA40+BD40+BG40+BJ40+BM40+BP40+BS40+BV40+BY40+CB40+CE40+CH40+CK40+CN40+CQ40+CT40+CW40+CZ40 -> 7 | F40: =ROUND(D40/$F$2*E40,0) -> 3048 | G40: =L40+O40+R40+U40+X40+AA40+AD40+AG40+AJ40+AM40+AP40+AS40+AV40+AY40+BB40+BE40+BH40+BK40+BN40+BQ40+BT40+BW40+BZ40+CC40+CF40+CI40+CL40+CO40+CR40+CU40+CX40+DA40 -> 25 | H40: =ROUND(D40/$H$2*G40,0) -> 1361 | I40: =F40+H40 -> 4409 | J40: =M40+P40+S40+V40+Y40+AB40+AE40+AH40+AK40+AN40+AQ40+AT40+AW40+AZ40+BC40+BF40+BI40+BL40+BO40+BR40+BU40+BX40+CA40+CD40+CG40+CJ40+CM40+CP40+CS40+CV40+CY40 -> 4409 | K40: 1 | L40: 3.5 | M40: =round((D40/$F$2)*K40+(D40/$H$2)*L40,0) -> 626 | N40: 1 | P40: =round((D40/$F$2)*N40+(D40/$H$2)*O40,0) -> 435 | Q40: 1 | R40: 3.5 | S40: =round((D40/$F$2)*Q40+(D40/$H$2)*R40,0) -> 626 | T40: 1 | U40: 7.5 | V40: =round(($D$40/$F$2)*T40+($D$40/$H$2)*U40,0) -> 844 | W40: 1 | X40: 3.5 | Y40: =round(($D$40/$F$2)*W40+($D$40/$H$2)*X40,0) -> 626 | Z40: 1 | AA40: 3.5 | AB40: =round(($D$40/$F$2)*Z40+($D$40/$H$2)*AA40,0) -> 626 | AC40: 1 | AD40: 3.5 | AE40: =round(($D$40/$F$2)*AC40+($D$40/$H$2)*AD40,0) -> 626 | AH40: =round(($D$40/$F$2)*AF40+($D$40/$H$2)*AG40,0) -> 0 | AK40: =round(($D$40/$F$2)*AI40+($D$40/$H$2)*AJ40,0) -> 0 | AN40: =round(($D$40/$F$2)*AL40+($D$40/$H$2)*AM40,0) -> 0 | AQ40: =round(($D$40/$F$2)*AO40+($D$40/$H$2)*AP40,0) -> 0 | AT40: =round(($D$40/$F$2)*AR40+($D$40/$H$2)*AS40,0) -> 0 | AW40: =round(($D$40/$F$2)*AU40+($D$40/$H$2)*AV40,0) -> 0 | AZ40: =round(($D$40/$F$2)*AX40+($D$40/$H$2)*AY40,0) -> 0 | BC40: =round(($D$40/$F$2)*BA40+($D$40/$H$2)*BB40,0) -> 0 | BF40: =round(($D$40/$F$2)*BD40+($D$40/$H$2)*BE40,0) -> 0 | BI40: =round(($D$40/$F$2)*BG40+($D$40/$H$2)*BH40,0) -> 0 | BL40: =round(($D$40/$F$2)*BJ40+($D$40/$H$2)*BK40,0) -> 0 | BO40: =round(($D$40/$F$2)*BM40+($D$40/$H$2)*BN40,0) -> 0 | BR40: =round(($D$40/$F$2)*BP40+($D$40/$H$2)*BQ40,0) -> 0 | BU40: =round(($D$40/$F$2)*BS40+($D$40/$H$2)*BT40,0) -> 0 | BX40: =round(($D$40/$F$2)*BV40+($D$40/$H$2)*BW40,0) -> 0 | CA40: =round(($D$40/$F$2)*BY40+($D$40/$H$2)*BZ40,0) -> 0 | CD40: =round(($D$40/$F$2)*CB40+($D$40/$H$2)*CC40,0) -> 0 | CG40: =round(($D$40/$F$2)*CE40+($D$40/$H$2)*CF40,0) -> 0 | CJ40: =round(($D$40/$F$2)*CH40+($D$40/$H$2)*CI40,0) -> 0 | CM40: =round(($D$40/$F$2)*CK40+($D$40/$H$2)*CL40,0) -> 0 | CP40: =round(($D$40/$F$2)*CN40+($D$40/$H$2)*CO40,0) -> 0 | CS40: =round(($D$40/$F$2)*CQ40+($D$40/$H$2)*CR40,0) -> 0 | CV40: =round(($D$40/$F$2)*CT40+($D$40/$H$2)*CU40,0) -> 0 | CY40: =round(($D$40/$F$2)*CW40+($D$40/$H$2)*CX40,0) -> 0 | DB40: =round(($D$40/$F$2)*CZ40+($D$40/$H$2)*DA40,0) -> 0
A41: 9 | B41: Poonam | C41: Helper | D41: 12500 | E41: =K41+N41+Q41+T41+W41+Z41+AC41+AF41+AI41+AL41+AO41+AR41+AU41+AX41+BA41+BD41+BG41+BJ41+BM41+BP41+BS41+BV41+BY41+CB41+CE41+CH41+CK41+CN41+CQ41+CT41+CW41+CZ41 -> 5 | F41: =ROUND(D41/$F$2*E41,0) -> 2016 | G41: =L41+O41+R41+U41+X41+AA41+AD41+AG41+AJ41+AM41+AP41+AS41+AV41+AY41+BB41+BE41+BH41+BK41+BN41+BQ41+BT41+BW41+BZ41+CC41+CF41+CI41+CL41+CO41+CR41+CU41+CX41+DA41 -> 15 | H41: =ROUND(D41/$H$2*G41,0) -> 756 | I41: =F41+H41 -> 2772 | J41: =M41+P41+S41+V41+Y41+AB41+AE41+AH41+AK41+AN41+AQ41+AT41+AW41+AZ41+BC41+BF41+BI41+BL41+BO41+BR41+BU41+BX41+CA41+CD41+CG41+CJ41+CM41+CP41+CS41+CV41+CY41 -> 2773 | M41: =round(($D$41/$F$2)*K41+($D$41/$H$2)*L41,0) -> 0 | P41: =round(($D$41/$F$2)*N41+($D$41/$H$2)*O41,0) -> 0 | Q41: 1 | R41: 3.5 | S41: =round(($D$41/$F$2)*Q41+($D$41/$H$2)*R41,0) -> 580 | T41: 1 | U41: 4.5 | V41: =round(($D$41/$F$2)*T41+($D$41/$H$2)*U41,0) -> 630 | W41: 1 | X41: 3.5 | Y41: =round(($D$41/$F$2)*W41+($D$41/$H$2)*X41,0) -> 580 | Z41: 1 | AA41: 3.5 | AB41: =round(($D$41/$F$2)*Z41+($D$41/$H$2)*AA41,0) -> 580 | AC41: 1 | AE41: =round(($D$41/$F$2)*AC41+($D$41/$H$2)*AD41,0) -> 403 | AH41: =round(($D$41/$F$2)*AF41+($D$41/$H$2)*AG41,0) -> 0 | AK41: =round(($D$41/$F$2)*AI41+($D$41/$H$2)*AJ41,0) -> 0 | AN41: =round(($D$41/$F$2)*AL41+($D$41/$H$2)*AM41,0) -> 0 | AQ41: =round(($D$41/$F$2)*AO41+($D$41/$H$2)*AP41,0) -> 0 | AT41: =round(($D$41/$F$2)*AR41+($D$41/$H$2)*AS41,0) -> 0 | AW41: =round(($D$41/$F$2)*AU41+($D$41/$H$2)*AV41,0) -> 0 | AZ41: =round(($D$41/$F$2)*AX41+($D$41/$H$2)*AY41,0) -> 0 | BC41: =round(($D$41/$F$2)*BA41+($D$41/$H$2)*BB41,0) -> 0 | BF41: =round(($D$41/$F$2)*BD41+($D$41/$H$2)*BE41,0) -> 0 | BI41: =round(($D$41/$F$2)*BG41+($D$41/$H$2)*BH41,0) -> 0 | BL41: =round(($D$41/$F$2)*BJ41+($D$41/$H$2)*BK41,0) -> 0 | BO41: =round(($D$41/$F$2)*BM41+($D$41/$H$2)*BN41,0) -> 0 | BR41: =round(($D$41/$F$2)*BP41+($D$41/$H$2)*BQ41,0) -> 0 | BU41: =round(($D$41/$F$2)*BS41+($D$41/$H$2)*BT41,0) -> 0 | BX41: =round(($D$41/$F$2)*BV41+($D$41/$H$2)*BW41,0) -> 0 | CA41: =round(($D$41/$F$2)*BY41+($D$41/$H$2)*BZ41,0) -> 0 | CD41: =round(($D$41/$F$2)*CB41+($D$41/$H$2)*CC41,0) -> 0 | CG41: =round(($D$41/$F$2)*CE41+($D$41/$H$2)*CF41,0) -> 0 | CJ41: =round(($D$41/$F$2)*CH41+($D$41/$H$2)*CI41,0) -> 0 | CM41: =round(($D$41/$F$2)*CK41+($D$41/$H$2)*CL41,0) -> 0 | CP41: =round(($D$41/$F$2)*CN41+($D$41/$H$2)*CO41,0) -> 0 | CS41: =round(($D$41/$F$2)*CQ41+($D$41/$H$2)*CR41,0) -> 0 | CV41: =round(($D$41/$F$2)*CT41+($D$41/$H$2)*CU41,0) -> 0 | CY41: =round(($D$41/$F$2)*CW41+($D$41/$H$2)*CX41,0) -> 0 | DB41: =round(($D$41/$F$2)*CZ41+($D$41/$H$2)*DA41,0) -> 0
A42: 10 | B42: NADEEM | C42: Helper | D42: 13500 | E42: =K42+N42+Q42+T42+W42+Z42+AC42+AF42+AI42+AL42+AO42+AR42+AU42+AX42+BA42+BD42+BG42+BJ42+BM42+BP42+BS42+BV42+BY42+CB42+CE42+CH42+CK42+CN42+CQ42+CT42+CW42+CZ42 -> 2 | F42: =ROUND(D42/$F$2*E42,0) -> 871 | G42: =L42+O42+R42+U42+X42+AA42+AD42+AG42+AJ42+AM42+AP42+AS42+AV42+AY42+BB42+BE42+BH42+BK42+BN42+BQ42+BT42+BW42+BZ42+CC42+CF42+CI42+CL42+CO42+CR42+CU42+CX42+DA42 -> 7 | H42: =ROUND(D42/$H$2*G42,0) -> 381 | I42: =F42+H42 -> 1252 | J42: =M42+P42+S42+V42+Y42+AB42+AE42+AH42+AK42+AN42+AQ42+AT42+AW42+AZ42+BC42+BF42+BI42+BL42+BO42+BR42+BU42+BX42+CA42+CD42+CG42+CJ42+CM42+CP42+CS42+CV42+CY42 -> 1252 | M42: =round(($D$42/$F$2)*K42+($D$42/$H$2)*L42,0) -> 0 | P42: =round(($D$42/$F$2)*N42+($D$42/$H$2)*O42,0) -> 0 | S42: =round(($D$42/$F$2)*Q42+($D$42/$H$2)*R42,0) -> 0 | V42: =round(($D$42/$F$2)*T42+($D$42/$H$2)*U42,0) -> 0 | Y42: =round(($D$42/$F$2)*W42+($D$42/$H$2)*X42,0) -> 0 | Z42: 1 | AA42: 3.5 | AB42: =round(($D$42/$F$2)*Z42+($D$42/$H$2)*AA42,0) -> 626 | AC42: 1 | AD42: 3.5 | AE42: =round(($D$42/$F$2)*AC42+($D$42/$H$2)*AD42,0) -> 626 | AH42: =round(($D$42/$F$2)*AF42+($D$42/$H$2)*AG42,0) -> 0 | AK42: =round(($D$42/$F$2)*AI42+($D$42/$H$2)*AJ42,0) -> 0 | AN42: =round(($D$42/$F$2)*AL42+($D$42/$H$2)*AM42,0) -> 0 | AQ42: =round(($D$42/$F$2)*AO42+($D$42/$H$2)*AP42,0) -> 0 | AT42: =round(($D$42/$F$2)*AR42+($D$42/$H$2)*AS42,0) -> 0 | AW42: =round(($D$42/$F$2)*AU42+($D$42/$H$2)*AV42,0) -> 0 | AZ42: =round(($D$42/$F$2)*AX42+($D$42/$H$2)*AY42,0) -> 0 | BC42: =round(($D$42/$F$2)*BA42+($D$42/$H$2)*BB42,0) -> 0 | BF42: =round(($D$42/$F$2)*BD42+($D$42/$H$2)*BE42,0) -> 0 | BI42: =round(($D$42/$F$2)*BG42+($D$42/$H$2)*BH42,0) -> 0 | BL42: =round(($D$42/$F$2)*BJ42+($D$42/$H$2)*BK42,0) -> 0 | BO42: =round(($D$42/$F$2)*BM42+($D$42/$H$2)*BN42,0) -> 0 | BR42: =round(($D$42/$F$2)*BP42+($D$42/$H$2)*BQ42,0) -> 0 | BU42: =round(($D$42/$F$2)*BS42+($D$42/$H$2)*BT42,0) -> 0 | BX42: =round(($D$42/$F$2)*BV42+($D$42/$H$2)*BW42,0) -> 0 | CA42: =round(($D$42/$F$2)*BY42+($D$42/$H$2)*BZ42,0) -> 0 | CD42: =round(($D$42/$F$2)*CB42+($D$42/$H$2)*CC42,0) -> 0 | CG42: =round(($D$42/$F$2)*CE42+($D$42/$H$2)*CF42,0) -> 0 | CJ42: =round(($D$42/$F$2)*CH42+($D$42/$H$2)*CI42,0) -> 0 | CM42: =round(($D$42/$F$2)*CK42+($D$42/$H$2)*CL42,0) -> 0 | CP42: =round(($D$42/$F$2)*CN42+($D$42/$H$2)*CO42,0) -> 0 | CS42: =round(($D$42/$F$2)*CQ42+($D$42/$H$2)*CR42,0) -> 0 | CV42: =round(($D$42/$F$2)*CT42+($D$42/$H$2)*CU42,0) -> 0 | CY42: =round(($D$42/$F$2)*CW42+($D$42/$H$2)*CX42,0) -> 0 | DB42: =round(($D$42/$F$2)*CZ42+($D$42/$H$2)*DA42,0) -> 0
A43: 11 | E43: =K43+N43+Q43+T43+W43+Z43+AC43+AF43+AI43+AL43+AO43+AR43+AU43+AX43+BA43+BD43+BG43+BJ43+BM43+BP43+BS43+BV43+BY43+CB43+CE43+CH43+CK43+CN43+CQ43+CT43+CW43+CZ43 -> 0 | F43: =ROUND(D43/$F$2*E43,0) -> 0 | G43: =L43+O43+R43+U43+X43+AA43+AD43+AG43+AJ43+AM43+AP43+AS43+AV43+AY43+BB43+BE43+BH43+BK43+BN43+BQ43+BT43+BW43+BZ43+CC43+CF43+CI43+CL43+CO43+CR43+CU43+CX43+DA43 -> 0 | H43: =ROUND(D43/$H$2*G43,0) -> 0 | I43: =F43+H43 -> 0 | J43: =M43+P43+S43+V43+Y43+AB43+AE43+AH43+AK43+AN43+AQ43+AT43+AW43+AZ43+BC43+BF43+BI43+BL43+BO43+BR43+BU43+BX43+CA43+CD43+CG43+CJ43+CM43+CP43+CS43+CV43+CY43 -> 0 | M43: =round(($D$43/$F$2)*K43+($D$43/$H$2)*L43,0) -> 0 | P43: =round(($D$43/$F$2)*N43+($D$43/$H$2)*O43,0) -> 0 | S43: =round(($D$43/$F$2)*Q43+($D$43/$H$2)*R43,0) -> 0 | V43: =round(($D$43/$F$2)*T43+($D$43/$H$2)*U43,0) -> 0 | Y43: =round(($D$43/$F$2)*W43+($D$43/$H$2)*X43,0) -> 0 | AB43: =round(($D$43/$F$2)*Z43+($D$43/$H$2)*AA43,0) -> 0 | AE43: =round(($D$43/$F$2)*AC43+($D$43/$H$2)*AD43,0) -> 0 | AH43: =round(($D$43/$F$2)*AF43+($D$43/$H$2)*AG43,0) -> 0 | AK43: =round(($D$43/$F$2)*AI43+($D$43/$H$2)*AJ43,0) -> 0 | AN43: =round(($D$43/$F$2)*AL43+($D$43/$H$2)*AM43,0) -> 0 | AQ43: =round(($D$43/$F$2)*AO43+($D$43/$H$2)*AP43,0) -> 0 | AT43: =round(($D$43/$F$2)*AR43+($D$43/$H$2)*AS43,0) -> 0 | AW43: =round(($D$43/$F$2)*AU43+($D$43/$H$2)*AV43,0) -> 0 | AZ43: =round(($D$43/$F$2)*AX43+($D$43/$H$2)*AY43,0) -> 0 | BC43: =round(($D$43/$F$2)*BA43+($D$43/$H$2)*BB43,0) -> 0 | BF43: =round(($D$43/$F$2)*BD43+($D$43/$H$2)*BE43,0) -> 0 | BI43: =round(($D$43/$F$2)*BG43+($D$43/$H$2)*BH43,0) -> 0 | BL43: =round(($D$43/$F$2)*BJ43+($D$43/$H$2)*BK43,0) -> 0 | BO43: =round(($D$43/$F$2)*BM43+($D$43/$H$2)*BN43,0) -> 0 | BR43: =round(($D$43/$F$2)*BP43+($D$43/$H$2)*BQ43,0) -> 0 | BU43: =round(($D$43/$F$2)*BS43+($D$43/$H$2)*BT43,0) -> 0 | BX43: =round(($D$43/$F$2)*BV43+($D$43/$H$2)*BW43,0) -> 0 | CA43: =round(($D$43/$F$2)*BY43+($D$43/$H$2)*BZ43,0) -> 0 | CD43: =round(($D$43/$F$2)*CB43+($D$43/$H$2)*CC43,0) -> 0 | CG43: =round(($D$43/$F$2)*CE43+($D$43/$H$2)*CF43,0) -> 0 | CJ43: =round(($D$43/$F$2)*CH43+($D$43/$H$2)*CI43,0) -> 0 | CM43: =round(($D$43/$F$2)*CK43+($D$43/$H$2)*CL43,0) -> 0 | CP43: =round(($D$43/$F$2)*CN43+($D$43/$H$2)*CO43,0) -> 0 | CS43: =round(($D$43/$F$2)*CQ43+($D$43/$H$2)*CR43,0) -> 0 | CV43: =round(($D$43/$F$2)*CT43+($D$43/$H$2)*CU43,0) -> 0 | CY43: =round(($D$43/$F$2)*CW43+($D$43/$H$2)*CX43,0) -> 0 | DB43: =round(($D$43/$F$2)*CZ43+($D$43/$H$2)*DA43,0) -> 0
A44: 12 | E44: =K44+N44+Q44+T44+W44+Z44+AC44+AF44+AI44+AL44+AO44+AR44+AU44+AX44+BA44+BD44+BG44+BJ44+BM44+BP44+BS44+BV44+BY44+CB44+CE44+CH44+CK44+CN44+CQ44+CT44+CW44+CZ44 -> 0 | F44: =ROUND(D44/$F$2*E44,0) -> 0 | G44: =L44+O44+R44+U44+X44+AA44+AD44+AG44+AJ44+AM44+AP44+AS44+AV44+AY44+BB44+BE44+BH44+BK44+BN44+BQ44+BT44+BW44+BZ44+CC44+CF44+CI44+CL44+CO44+CR44+CU44+CX44+DA44 -> 0 | H44: =ROUND(D44/$H$2*G44,0) -> 0 | I44: =F44+H44 -> 0 | J44: =M44+P44+S44+V44+Y44+AB44+AE44+AH44+AK44+AN44+AQ44+AT44+AW44+AZ44+BC44+BF44+BI44+BL44+BO44+BR44+BU44+BX44+CA44+CD44+CG44+CJ44+CM44+CP44+CS44+CV44+CY44 -> 0 | M44: =round(($D$44/$F$2)*K44+($D$44/$H$2)*L44,0) -> 0 | P44: =round(($D$44/$F$2)*N44+($D$44/$H$2)*O44,0) -> 0 | S44: =round(($D$44/$F$2)*Q44+($D$44/$H$2)*R44,0) -> 0 | V44: =round(($D$44/$F$2)*T44+($D$44/$H$2)*U44,0) -> 0 | Y44: =round(($D$44/$F$2)*W44+($D$44/$H$2)*X44,0) -> 0 | AB44: =round(($D$44/$F$2)*Z44+($D$44/$H$2)*AA44,0) -> 0 | AE44: =round(($D$44/$F$2)*AC44+($D$44/$H$2)*AD44,0) -> 0 | AH44: =round(($D$44/$F$2)*AF44+($D$44/$H$2)*AG44,0) -> 0 | AK44: =round(($D$44/$F$2)*AI44+($D$44/$H$2)*AJ44,0) -> 0 | AN44: =round(($D$44/$F$2)*AL44+($D$44/$H$2)*AM44,0) -> 0 | AQ44: =round(($D$44/$F$2)*AO44+($D$44/$H$2)*AP44,0) -> 0 | AT44: =round(($D$44/$F$2)*AR44+($D$44/$H$2)*AS44,0) -> 0 | AW44: =round(($D$44/$F$2)*AU44+($D$44/$H$2)*AV44,0) -> 0 | AZ44: =round(($D$44/$F$2)*AX44+($D$44/$H$2)*AY44,0) -> 0 | BC44: =round(($D$44/$F$2)*BA44+($D$44/$H$2)*BB44,0) -> 0 | BF44: =round(($D$44/$F$2)*BD44+($D$44/$H$2)*BE44,0) -> 0 | BI44: =round(($D$44/$F$2)*BG44+($D$44/$H$2)*BH44,0) -> 0 | BL44: =round(($D$44/$F$2)*BJ44+($D$44/$H$2)*BK44,0) -> 0 | BO44: =round(($D$44/$F$2)*BM44+($D$44/$H$2)*BN44,0) -> 0 | BR44: =round(($D$44/$F$2)*BP44+($D$44/$H$2)*BQ44,0) -> 0 | BU44: =round(($D$44/$F$2)*BS44+($D$44/$H$2)*BT44,0) -> 0 | BX44: =round(($D$44/$F$2)*BV44+($D$44/$H$2)*BW44,0) -> 0 | CA44: =round(($D$44/$F$2)*BY44+($D$44/$H$2)*BZ44,0) -> 0 | CD44: =round(($D$44/$F$2)*CB44+($D$44/$H$2)*CC44,0) -> 0 | CG44: =round(($D$44/$F$2)*CE44+($D$44/$H$2)*CF44,0) -> 0 | CJ44: =round(($D$44/$F$2)*CH44+($D$44/$H$2)*CI44,0) -> 0 | CM44: =round(($D$44/$F$2)*CK44+($D$44/$H$2)*CL44,0) -> 0 | CP44: =round(($D$44/$F$2)*CN44+($D$44/$H$2)*CO44,0) -> 0 | CS44: =round(($D$44/$F$2)*CQ44+($D$44/$H$2)*CR44,0) -> 0 | CV44: =round(($D$44/$F$2)*CT44+($D$44/$H$2)*CU44,0) -> 0 | CY44: =round(($D$44/$F$2)*CW44+($D$44/$H$2)*CX44,0) -> 0 | DB44: =round(($D$44/$F$2)*CZ44+($D$44/$H$2)*DA44,0) -> 0
A45: 13 | E45: =K45+N45+Q45+T45+W45+Z45+AC45+AF45+AI45+AL45+AO45+AR45+AU45+AX45+BA45+BD45+BG45+BJ45+BM45+BP45+BS45+BV45+BY45+CB45+CE45+CH45+CK45+CN45+CQ45+CT45+CW45+CZ45 -> 0 | F45: =ROUND(D45/$F$2*E45,0) -> 0 | G45: =L45+O45+R45+U45+X45+AA45+AD45+AG45+AJ45+AM45+AP45+AS45+AV45+AY45+BB45+BE45+BH45+BK45+BN45+BQ45+BT45+BW45+BZ45+CC45+CF45+CI45+CL45+CO45+CR45+CU45+CX45+DA45 -> 0 | H45: =ROUND(D45/$H$2*G45,0) -> 0 | I45: =F45+H45 -> 0 | J45: =M45+P45+S45+V45+Y45+AB45+AE45+AH45+AK45+AN45+AQ45+AT45+AW45+AZ45+BC45+BF45+BI45+BL45+BO45+BR45+BU45+BX45+CA45+CD45+CG45+CJ45+CM45+CP45+CS45+CV45+CY45 -> 0 | M45: =round(($D$45/$F$2)*K45+($D$45/$H$2)*L45,0) -> 0 | P45: =round(($D$45/$F$2)*N45+($D$45/$H$2)*O45,0) -> 0 | S45: =round(($D$45/$F$2)*Q45+($D$45/$H$2)*R45,0) -> 0 | V45: =round(($D$45/$F$2)*T45+($D$45/$H$2)*U45,0) -> 0 | Y45: =round(($D$45/$F$2)*W45+($D$45/$H$2)*X45,0) -> 0 | AB45: =round(($D$45/$F$2)*Z45+($D$45/$H$2)*AA45,0) -> 0 | AE45: =round(($D$45/$F$2)*AC45+($D$45/$H$2)*AD45,0) -> 0 | AH45: =round(($D$45/$F$2)*AF45+($D$45/$H$2)*AG45,0) -> 0 | AK45: =round(($D$45/$F$2)*AI45+($D$45/$H$2)*AJ45,0) -> 0 | AN45: =round(($D$45/$F$2)*AL45+($D$45/$H$2)*AM45,0) -> 0 | AQ45: =round(($D$45/$F$2)*AO45+($D$45/$H$2)*AP45,0) -> 0 | AT45: =round(($D$45/$F$2)*AR45+($D$45/$H$2)*AS45,0) -> 0 | AW45: =round(($D$45/$F$2)*AU45+($D$45/$H$2)*AV45,0) -> 0 | AZ45: =round(($D$45/$F$2)*AX45+($D$45/$H$2)*AY45,0) -> 0 | BC45: =round(($D$45/$F$2)*BA45+($D$45/$H$2)*BB45,0) -> 0 | BF45: =round(($D$45/$F$2)*BD45+($D$45/$H$2)*BE45,0) -> 0 | BI45: =round(($D$45/$F$2)*BG45+($D$45/$H$2)*BH45,0) -> 0 | BL45: =round(($D$45/$F$2)*BJ45+($D$45/$H$2)*BK45,0) -> 0 | BO45: =round(($D$45/$F$2)*BM45+($D$45/$H$2)*BN45,0) -> 0 | BR45: =round(($D$45/$F$2)*BP45+($D$45/$H$2)*BQ45,0) -> 0 | BU45: =round(($D$45/$F$2)*BS45+($D$45/$H$2)*BT45,0) -> 0 | BX45: =round(($D$45/$F$2)*BV45+($D$45/$H$2)*BW45,0) -> 0 | CA45: =round(($D$45/$F$2)*BY45+($D$45/$H$2)*BZ45,0) -> 0 | CD45: =round(($D$45/$F$2)*CB45+($D$45/$H$2)*CC45,0) -> 0 | CG45: =round(($D$45/$F$2)*CE45+($D$45/$H$2)*CF45,0) -> 0 | CJ45: =round(($D$45/$F$2)*CH45+($D$45/$H$2)*CI45,0) -> 0 | CM45: =round(($D$45/$F$2)*CK45+($D$45/$H$2)*CL45,0) -> 0 | CP45: =round(($D$45/$F$2)*CN45+($D$45/$H$2)*CO45,0) -> 0 | CS45: =round(($D$45/$F$2)*CQ45+($D$45/$H$2)*CR45,0) -> 0 | CV45: =round(($D$45/$F$2)*CT45+($D$45/$H$2)*CU45,0) -> 0 | CY45: =round(($D$45/$F$2)*CW45+($D$45/$H$2)*CX45,0) -> 0 | DB45: =round(($D$45/$F$2)*CZ45+($D$45/$H$2)*DA45,0) -> 0
A46: 14 | E46: =K46+N46+Q46+T46+W46+Z46+AC46+AF46+AI46+AL46+AO46+AR46+AU46+AX46+BA46+BD46+BG46+BJ46+BM46+BP46+BS46+BV46+BY46+CB46+CE46+CH46+CK46+CN46+CQ46+CT46+CW46+CZ46 -> 0 | F46: =ROUND(D46/$F$2*E46,0) -> 0 | G46: =L46+O46+R46+U46+X46+AA46+AD46+AG46+AJ46+AM46+AP46+AS46+AV46+AY46+BB46+BE46+BH46+BK46+BN46+BQ46+BT46+BW46+BZ46+CC46+CF46+CI46+CL46+CO46+CR46+CU46+CX46+DA46 -> 0 | H46: =ROUND(D46/$H$2*G46,0) -> 0 | I46: =F46+H46 -> 0 | J46: =M46+P46+S46+V46+Y46+AB46+AE46+AH46+AK46+AN46+AQ46+AT46+AW46+AZ46+BC46+BF46+BI46+BL46+BO46+BR46+BU46+BX46+CA46+CD46+CG46+CJ46+CM46+CP46+CS46+CV46+CY46 -> 0 | M46: =round(($D$46/$F$2)*K46+($D$46/$H$2)*L46,0) -> 0 | P46: =round(($D$46/$F$2)*N46+($D$46/$H$2)*O46,0) -> 0 | S46: =round(($D$46/$F$2)*Q46+($D$46/$H$2)*R46,0) -> 0 | V46: =round(($D$46/$F$2)*T46+($D$46/$H$2)*U46,0) -> 0 | Y46: =round(($D$46/$F$2)*W46+($D$46/$H$2)*X46,0) -> 0 | AB46: =round(($D$46/$F$2)*Z46+($D$46/$H$2)*AA46,0) -> 0 | AE46: =round(($D$46/$F$2)*AC46+($D$46/$H$2)*AD46,0) -> 0 | AH46: =round(($D$46/$F$2)*AF46+($D$46/$H$2)*AG46,0) -> 0 | AK46: =round(($D$46/$F$2)*AI46+($D$46/$H$2)*AJ46,0) -> 0 | AN46: =round(($D$46/$F$2)*AL46+($D$46/$H$2)*AM46,0) -> 0 | AQ46: =round(($D$46/$F$2)*AO46+($D$46/$H$2)*AP46,0) -> 0 | AT46: =round(($D$46/$F$2)*AR46+($D$46/$H$2)*AS46,0) -> 0 | AW46: =round(($D$46/$F$2)*AU46+($D$46/$H$2)*AV46,0) -> 0 | AZ46: =round(($D$46/$F$2)*AX46+($D$46/$H$2)*AY46,0) -> 0 | BC46: =round(($D$46/$F$2)*BA46+($D$46/$H$2)*BB46,0) -> 0 | BF46: =round(($D$46/$F$2)*BD46+($D$46/$H$2)*BE46,0) -> 0 | BI46: =round(($D$46/$F$2)*BG46+($D$46/$H$2)*BH46,0) -> 0 | BL46: =round(($D$46/$F$2)*BJ46+($D$46/$H$2)*BK46,0) -> 0 | BO46: =round(($D$46/$F$2)*BM46+($D$46/$H$2)*BN46,0) -> 0 | BR46: =round(($D$46/$F$2)*BP46+($D$46/$H$2)*BQ46,0) -> 0 | BU46: =round(($D$46/$F$2)*BS46+($D$46/$H$2)*BT46,0) -> 0 | BX46: =round(($D$46/$F$2)*BV46+($D$46/$H$2)*BW46,0) -> 0 | CA46: =round(($D$46/$F$2)*BY46+($D$46/$H$2)*BZ46,0) -> 0 | CD46: =round(($D$46/$F$2)*CB46+($D$46/$H$2)*CC46,0) -> 0 | CG46: =round(($D$46/$F$2)*CE46+($D$46/$H$2)*CF46,0) -> 0 | CJ46: =round(($D$46/$F$2)*CH46+($D$46/$H$2)*CI46,0) -> 0 | CM46: =round(($D$46/$F$2)*CK46+($D$46/$H$2)*CL46,0) -> 0 | CP46: =round(($D$46/$F$2)*CN46+($D$46/$H$2)*CO46,0) -> 0 | CS46: =round(($D$46/$F$2)*CQ46+($D$46/$H$2)*CR46,0) -> 0 | CV46: =round(($D$46/$F$2)*CT46+($D$46/$H$2)*CU46,0) -> 0 | CY46: =round(($D$46/$F$2)*CW46+($D$46/$H$2)*CX46,0) -> 0 | DB46: =round(($D$46/$F$2)*CZ46+($D$46/$H$2)*DA46,0) -> 0
A47: 15 | E47: =K47+N47+Q47+T47+W47+Z47+AC47+AF47+AI47+AL47+AO47+AR47+AU47+AX47+BA47+BD47+BG47+BJ47+BM47+BP47+BS47+BV47+BY47+CB47+CE47+CH47+CK47+CN47+CQ47+CT47+CW47+CZ47 -> 0 | F47: =ROUND(D47/$F$2*E47,0) -> 0 | G47: =L47+O47+R47+U47+X47+AA47+AD47+AG47+AJ47+AM47+AP47+AS47+AV47+AY47+BB47+BE47+BH47+BK47+BN47+BQ47+BT47+BW47+BZ47+CC47+CF47+CI47+CL47+CO47+CR47+CU47+CX47 -> 0 | H47: =ROUND(D47/$H$2*G47,0) -> 0 | I47: =F47+H47 -> 0 | J47: =M47+P47+S47+V47+Y47+AB47+AE47+AH47+AK47+AN47+AQ47+AT47+AW47+AZ47+BC47+BF47+BI47+BL47+BO47+BR47+BU47+BX47+CA47+CD47+CG47+CJ47+CM47+CP47+CS47+CV47+CY47 -> 0 | M47: =round(($D$47/$F$2)*K47+($D$47/$H$2)*L47,0) -> 0 | P47: =round(($D$47/$F$2)*N47+($D$47/$H$2)*O47,0) -> 0 | S47: =round(($D$47/$F$2)*Q47+($D$47/$H$2)*R47,0) -> 0 | V47: =round(($D$47/$F$2)*T47+($D$47/$H$2)*U47,0) -> 0 | Y47: =round(($D$47/$F$2)*W47+($D$47/$H$2)*X47,0) -> 0 | AB47: =round(($D$47/$F$2)*Z47+($D$47/$H$2)*AA47,0) -> 0 | AE47: =round(($D$47/$F$2)*AC47+($D$47/$H$2)*AD47,0) -> 0 | AH47: =round(($D$47/$F$2)*AF47+($D$47/$H$2)*AG47,0) -> 0 | AK47: =round(($D$47/$F$2)*AI47+($D$47/$H$2)*AJ47,0) -> 0 | AN47: =round(($D$47/$F$2)*AL47+($D$47/$H$2)*AM47,0) -> 0 | AQ47: =round(($D$47/$F$2)*AO47+($D$47/$H$2)*AP47,0) -> 0 | AT47: =round(($D$47/$F$2)*AR47+($D$47/$H$2)*AS47,0) -> 0 | AW47: =round(($D$47/$F$2)*AU47+($D$47/$H$2)*AV47,0) -> 0 | AZ47: =round(($D$47/$F$2)*AX47+($D$47/$H$2)*AY47,0) -> 0 | BC47: =round(($D$47/$F$2)*BA47+($D$47/$H$2)*BB47,0) -> 0 | BF47: =round(($D$47/$F$2)*BD47+($D$47/$H$2)*BE47,0) -> 0 | BI47: =round(($D$47/$F$2)*BG47+($D$47/$H$2)*BH47,0) -> 0 | BL47: =round(($D$47/$F$2)*BJ47+($D$47/$H$2)*BK47,0) -> 0 | BO47: =round(($D$47/$F$2)*BM47+($D$47/$H$2)*BN47,0) -> 0 | BR47: =round(($D$47/$F$2)*BP47+($D$47/$H$2)*BQ47,0) -> 0 | BU47: =round(($D$47/$F$2)*BS47+($D$47/$H$2)*BT47,0) -> 0 | BX47: =round(($D$47/$F$2)*BV47+($D$47/$H$2)*BW47,0) -> 0 | CA47: =round(($D$47/$F$2)*BY47+($D$47/$H$2)*BZ47,0) -> 0 | CD47: =round(($D$47/$F$2)*CB47+($D$47/$H$2)*CC47,0) -> 0 | CG47: =round(($D$47/$F$2)*CE47+($D$47/$H$2)*CF47,0) -> 0 | CJ47: =round(($D$47/$F$2)*CH47+($D$47/$H$2)*CI47,0) -> 0 | CM47: =round(($D$47/$F$2)*CK47+($D$47/$H$2)*CL47,0) -> 0 | CP47: =round(($D$47/$F$2)*CN47+($D$47/$H$2)*CO47,0) -> 0 | CS47: =round(($D$47/$F$2)*CQ47+($D$47/$H$2)*CR47,0) -> 0 | CV47: =round(($D$47/$F$2)*CT47+($D$47/$H$2)*CU47,0) -> 0 | CY47: =round(($D$47/$F$2)*CW47+($D$47/$H$2)*CX47,0) -> 0 | DB47: =round(($D$47/$F$2)*CZ47+($D$47/$H$2)*DA47,0) -> 0
D48: =SUM(D4:D47) -> 756700 | E48: =SUM(E4:E47) -> 252 | F48: =SUM(F4:F47) -> 161428 | G48: =SUM(G4:G47) -> 720 | H48: =SUM(H4:H47) -> 46918 | I48: =SUM(I4:I47) -> 208346 | J48: =SUM(J4:J47) -> 208410 | K48: =SUM(K4:K47) -> 33 | ... DB48: =SUM(DB4:DB47) -> 0
D49: =Cont.!D55 -> 414500 | E49: =Cont.!E55 -> 114 | F49: =Cont.!F55 -> 49251 | G49: =Cont.!G55 -> 455.5 | H49: =Cont.!H55 -> 24606 | I49: =Cont.!I55 -> 73857 | J49: =Cont.!J55 -> 73867 | K49: =Cont.!K55 -> 13 | ... DB49: =Cont.!DB55 -> 0
J51: =SUM(J48:J50) -> 282277 | K51: =SUM(K48:K50) -> 46 | L51: =SUM(L48:L50) -> 141 | M51: =SUM(M48:M50) -> 36028 | N51: =SUM(N48:N50) -> 46 | O51: =SUM(O48:O50) -> 122.5 | P51: =SUM(P48:P50) -> 34637 | Q51: =SUM(Q48:Q50) -> 47 | ... DB51: =SUM(DB48:DB50) -> 0
E52: =SUM(E38:E47) -> 28 | F52: =SUM(F38:F47) -> 12371 | G52: =SUM(G38:G47) -> 113 | H52: =SUM(H38:H47) -> 6379 | I52: =SUM(I38:I47) -> 18750 | J52: =SUM(J38:J47) -> 18749
H53: Gross | I53: =#REF!+I52 -> #REF!
I54: =M51+P51 -> 70665
I55: =I53-I54 -> #REF!
CG56: =#REF!+CG48+CG52 -> #REF! | CJ56: =#REF!+CJ48+CJ52 -> #REF!

Sheet Cont.
A2: CONTRACTOR WAGES SHEET FOR THE MONTH OF JULY - 2026 | F2: 31 | H2: 248 | K2: 1 | N2: 2 | Q2: 3 | T2: 4 | W2: 5 | Z2: 6 | AC2: 7 | AF2: 8 | AI2: 9 | AL2: 10 | AO2: 11 | AR2: 12 | AU2: 13 | AX2: 14 | BA2: 15 | BD2: 16 | BG2: 17 | BJ2: 18 | BM2: 19 | BP2: 20 | BS2: 21 | BV2: 22 | BY2: 23 | CB2: 24 | CE2: 25 | CH2: 26 | CK2: 27 | CN2: 28 | CQ2: 29 | CT2: 30 | CW2: 31 | CZ2: 1
A3: S.No. | B3: Employee Name | C3: Designation | D3: Basic Salary | E3: 31 | F3: Days Amount | G3: 248 | H3: OT Amount | I3: Gross Salary | J3: Gross Income | K3: Day's | L3: OT | M3: Gross Salary | N3: Day's Amount | O3: OT Amount | P3: Salary | Q3: Day's | R3: OT | S3: Gross Salary | T3: Day's | U3: OT | V3: Gross Salary | W3: Day's | X3: OT | Y3: Gross Salary | Z3: Day's | AA3: OT | AB3: Gross Salary | AC3: Day's | AD3: OT | AE3: Gross Salary | AF3: Day's | AG3: OT | AH3: Gross Salary | AI3: Day's | AJ3: OT | AK3: Gross Salary | AL3: Day's | AM3: OT | AN3: Gross Salary | AO3: Day's | AP3: OT | AQ3: Gross Salary | AR3: Day's | AS3: OT | AT3: Gross Salary | AU3: Day's | AV3: OT | AW3: Gross Salary | AX3: Day's | AY3: OT | AZ3: Gross Salary | BA3: Day's | BB3: OT | BC3: Gross Salary | BD3: Day's | BE3: OT | BF3: Gross Salary | BG3: Day's | BH3: OT | BI3: Gross Salary | BJ3: Day's | BK3: OT | BL3: Gross Salary | BM3: Day's | BN3: OT | BO3: Gross Salary | BP3: Day's | BQ3: OT | BR3: Gross Salary | BS3: Day's | BT3: OT | BU3: Gross Salary | BV3: Day's | BW3: OT | BX3: Gross Salary | BY3: Day's | BZ3: OT | CA3: Gross Salary | CB3: Day's | CC3: OT | CD3: Gross Salary | CE3: Day's | CF3: OT | CG3: Gross Salary | CH3: Day's | CI3: OT | CJ3: Gross Salary | CK3: Day's | CL3: OT | CM3: Gross Salary | CN3: Day's | CO3: OT | CP3: Gross Salary | CQ3: Day's | CR3: OT | CS3: Gross Salary | CT3: Day's | CU3: OT | CV3: Gross Salary | CW3: Day's | CX3: OT | CY3: Gross Salary | CZ3: Day's | DA3: OT | DB3: Gross Salary
A4: 1 | B4: Narender | C4: Helper | D4: 13500 | E4: =K4+N4+Q4+T4+W4+Z4+AC4+AF4+AI4+AL4+AO4+AR4+AU4+AX4+BA4+BD4+BG4+BJ4+BM4+BP4+BS4+BV4+BY4+CB4+CE4+CH4+CK4+CN4+CQ4+CT4+CW4+CZ4 -> 1 | F4: =ROUND(D4/$F$2*E4,0) -> 435 | G4: =L4+O4+R4+U4+X4+AA4+AD4+AG4+AJ4+AM4+AP4+AS4+AV4+AY4+BB4+BE4+BH4+BK4+BN4+BQ4+BT4+BW4+BZ4+CC4+CF4+CI4+CL4+CO4+CR4+CU4+CX4+DA4 -> 0.5 | H4: =ROUND(D4/$H$2*G4,0) -> 27 | I4: =F4+H4 -> 462 | J4: =M4+P4+S4+V4+Y4+AB4+AE4+AH4+AK4+AN4+AQ4+AT4+AW4+AZ4+BC4+BF4+BI4+BL4+BO4+BR4+BU4+BX4+CA4+CD4+CG4+CJ4+CM4+CP4+CS4+CV4+CY4 -> 463 | K4: 1 | L4: 0.5 | M4: =ROUND((($D$4/$E$3*K4)+($D$4/$H$2*L4)),0) -> 463 | P4: =ROUND(($D$4/$E$3*N4)+($D$4/$H$2*O4),0) -> 0 | S4: =ROUND(($D$4/$E$3*Q4)+($D$4/$H$2*R4),0) -> 0 | V4: =ROUND(($D$4/$E$3*T4)+($D$4/$H$2*U4),0) -> 0 | Y4: =ROUND(($D$4/$E$3*W4)+($D$4/$H$2*X4),0) -> 0 | AB4: =ROUND(($D$4/$E$3*Z4)+($D$4/$H$2*AA4),0) -> 0 | AE4: =ROUND(($D$4/$E$3*AC4)+($D$4/$H$2*AD4),0) -> 0 | AH4: =ROUND(($D$4/$E$3*AF4)+($D$4/$H$2*AG4),0) -> 0 | AK4: =ROUND(($D$4/$E$3*AI4)+($D$4/$H$2*AJ4),0) -> 0 | AN4: =ROUND(($D$4/$E$3*AL4)+($D$4/$H$2*AM4),0) -> 0 | AQ4: =ROUND(($D$4/$E$3*AO4)+($D$4/$H$2*AP4),0) -> 0 | AT4: =ROUND(($D$4/$E$3*AR4)+($D$4/$H$2*AS4),0) -> 0 | AW4: =ROUND(($D$4/$E$3*AU4)+($D$4/$H$2*AV4),0) -> 0 | AZ4: =ROUND(($D$4/$E$3*AX4)+($D$4/$H$2*AY4),0) -> 0 | BC4: =ROUND(($D$4/$E$3*BA4)+($D$4/$H$2*BB4),0) -> 0 | BF4: =ROUND(($D$4/$E$3*BD4)+($D$4/$H$2*BE4),0) -> 0 | BI4: =ROUND(($D$4/$E$3*BG4)+($D$4/$H$2*BH4),0) -> 0 | BL4: =ROUND(($D$4/$E$3*BJ4)+($D$4/$H$2*BK4),0) -> 0 | BO4: =ROUND(($D$4/$E$3*BM4)+($D$4/$H$2*BN4),0) -> 0 | BR4: =ROUND(($D$4/$E$3*BP4)+($D$4/$H$2*BQ4),0) -> 0 | BU4: =ROUND(($D$4/$E$3*BS4)+($D$4/$H$2*BT4),0) -> 0 | BX4: =ROUND(($D$4/$E$3*BV4)+($D$4/$H$2*BW4),0) -> 0 | CA4: =ROUND(($D$4/$E$3*BY4)+($D$4/$H$2*BZ4),0) -> 0 | CD4: =ROUND(($D$4/$E$3*CB4)+($D$4/$H$2*CC4),0) -> 0 | CG4: =ROUND(($D$4/$E$3*CE4)+($D$4/$H$2*CF4),0) -> 0 | CJ4: =ROUND(($D$4/$E$3*CH4)+($D$4/$H$2*CI4),0) -> 0 | CM4: =ROUND(($D$4/$E$3*CK4)+($D$4/$H$2*CL4),0) -> 0 | CP4: =ROUND(($D$4/$E$3*CN4)+($D$4/$H$2*CO4),0) -> 0 | CS4: =ROUND(($D$4/$E$3*CQ4)+($D$4/$H$2*CR4),0) -> 0 | CV4: =ROUND(($D$4/$E$3*CT4)+($D$4/$H$2*CU4),0) -> 0 | CY4: =ROUND(($D$4/$E$3*CW4)+($D$4/$H$2*CX4),0) -> 0
A5: 2 | B5: Surender | C5: Helper | D5: 13500 | E5: =K5+N5+Q5+T5+W5+Z5+AC5+AF5+AI5+AL5+AO5+AR5+AU5+AX5+BA5+BD5+BG5+BJ5+BM5+BP5+BS5+BV5+BY5+CB5+CE5+CH5+CK5+CN5+CQ5+CT5+CW5+CZ5 -> 1 | F5: =ROUND(D5/$F$2*E5,0) -> 435 | G5: =L5+O5+R5+U5+X5+AA5+AD5+AG5+AJ5+AM5+AP5+AS5+AV5+AY5+BB5+BE5+BH5+BK5+BN5+BQ5+BT5+BW5+BZ5+CC5+CF5+CI5+CL5+CO5+CR5+CU5+CX5+DA4 -> 0.5 | H5: =ROUND(D5/$H$2*G5,0) -> 27 | I5: =F5+H5 -> 462 | J5: =M5+P5+S5+V5+Y5+AB5+AE5+AH5+AK5+AN5+AQ5+AT5+AW5+AZ5+BC5+BF5+BI5+BL5+BO5+BR5+BU5+BX5+CA5+CD5+CG5+CJ5+CM5+CP5+CS5+CV5+CY5 -> 463 | K5: 1 | L5: 0.5 | M5: =ROUND(($D$5/$E$3*K5)+($D$5/$H$2*L5),0) -> 463 | P5: =ROUND(($D$5/$E$3*N5)+($D$5/$H$2*O5),0) -> 0 | S5: =ROUND(($D$5/$E$3*Q5)+($D$5/$H$2*R5),0) -> 0 | V5: =ROUND(($D$5/$E$3*T5)+($D$5/$H$2*U5),0) -> 0 | Y5: =ROUND(($D$5/$E$3*W5)+($D$5/$H$2*X5),0) -> 0 | AB5: =ROUND(($D$5/$E$3*Z5)+($D$5/$H$2*AA5),0) -> 0 | AE5: =ROUND(($D$5/$E$3*AC5)+($D$5/$H$2*AD5),0) -> 0 | AH5: =ROUND(($D$5/$E$3*AF5)+($D$5/$H$2*AG5),0) -> 0 | AK5: =ROUND(($D$5/$E$3*AI5)+($D$5/$H$2*AJ5),0) -> 0 | AN5: =ROUND(($D$5/$E$3*AL5)+($D$5/$H$2*AM5),0) -> 0 | AQ5: =ROUND(($D$5/$E$3*AO5)+($D$5/$H$2*AP5),0) -> 0 | AT5: =ROUND(($D$5/$E$3*AR5)+($D$5/$H$2*AS5),0) -> 0 | AW5: =ROUND(($D$5/$E$3*AU5)+($D$5/$H$2*AV5),0) -> 0 | AZ5: =ROUND(($D$5/$E$3*AX5)+($D$5/$H$2*AY5),0) -> 0 | BC5: =ROUND(($D$5/$E$3*BA5)+($D$5/$H$2*BB5),0) -> 0 | BF5: =ROUND(($D$5/$E$3*BD5)+($D$5/$H$2*BE5),0) -> 0 | BI5: =ROUND(($D$5/$E$3*BG5)+($D$5/$H$2*BH5),0) -> 0 | BL5: =ROUND(($D$5/$E$3*BJ5)+($D$5/$H$2*BK5),0) -> 0 | BO5: =ROUND(($D$5/$E$3*BM5)+($D$5/$H$2*BN5),0) -> 0 | BR5: =ROUND(($D$5/$E$3*BP5)+($D$5/$H$2*BQ5),0) -> 0 | BU5: =ROUND(($D$5/$E$3*BS5)+($D$5/$H$2*BT5),0) -> 0 | BX5: =ROUND(($D$5/$E$3*BV5)+($D$5/$H$2*BW5),0) -> 0 | CA5: =ROUND(($D$5/$E$3*BY5)+($D$5/$H$2*BZ5),0) -> 0 | CD5: =ROUND(($D$5/$E$3*CB5)+($D$5/$H$2*CC5),0) -> 0 | CG5: =ROUND(($D$5/$E$3*CE5)+($D$5/$H$2*CF5),0) -> 0 | CJ5: =ROUND(($D$5/$E$3*CH5)+($D$5/$H$2*CI5),0) -> 0 | CM5: =ROUND(($D$5/$E$3*CK5)+($D$5/$H$2*CL5),0) -> 0 | CP5: =ROUND(($D$5/$E$3*CN5)+($D$5/$H$2*CO5),0) -> 0 | CS5: =ROUND(($D$5/$E$3*CQ5)+($D$5/$H$2*CR5),0) -> 0 | CV5: =ROUND(($D$5/$E$3*CT5)+($D$5/$H$2*CU5),0) -> 0 | CY5: =ROUND(($D$5/$E$3*CW5)+($D$5/$H$2*CX5),0) -> 0
A6: 3 | B6: Yashpal | C6: Helper | D6: 13500 | E6: =K6+N6+Q6+T6+W6+Z6+AC6+AF6+AI6+AL6+AO6+AR6+AU6+AX6+BA6+BD6+BG6+BJ6+BM6+BP6+BS6+BV6+BY6+CB6+CE6+CH6+CK6+CN6+CQ6+CT6+CW6+CZ6 -> 1 | F6: =ROUND(D6/$F$2*E6,0) -> 435 | G6: =L6+O6+R6+U6+X6+AA6+AD6+AG6+AJ6+AM6+AP6+AS6+AV6+AY6+BB6+BE6+BH6+BK6+BN6+BQ6+BT6+BW6+BZ6+CC6+CF6+CI6+CL6+CO6+CR6+CU6+CX6+DA5 -> 0.5 | H6: =ROUND(D6/$H$2*G6,0) -> 27 | I6: =F6+H6 -> 462 | J6: =M6+P6+S6+V6+Y6+AB6+AE6+AH6+AK6+AN6+AQ6+AT6+AW6+AZ6+BC6+BF6+BI6+BL6+BO6+BR6+BU6+BX6+CA6+CD6+CG6+CJ6+CM6+CP6+CS6+CV6+CY6 -> 463 | K6: 1 | L6: 0.5 | M6: =ROUND(($D$6/$E$3*K6)+($D$6/$H$2*L6),0) -> 463 | P6: =ROUND(($D$6/$E$3*N6)+($D$6/$H$2*O6),0) -> 0 | S6: =ROUND(($D$6/$E$3*Q6)+($D$6/$H$2*R6),0) -> 0 | V6: =ROUND(($D$6/$E$3*T6)+($D$6/$H$2*U6),0) -> 0 | Y6: =ROUND(($D$6/$E$3*W6)+($D$6/$H$2*X6),0) -> 0 | AB6: =ROUND(($D$6/$E$3*Z6)+($D$6/$H$2*AA6),0) -> 0 | AE6: =ROUND(($D$6/$E$3*AC6)+($D$6/$H$2*AD6),0) -> 0 | AH6: =ROUND(($D$6/$E$3*AF6)+($D$6/$H$2*AG6),0) -> 0 | AK6: =ROUND(($D$6/$E$3*AI6)+($D$6/$H$2*AJ6),0) -> 0 | AN6: =ROUND(($D$6/$E$3*AL6)+($D$6/$H$2*AM6),0) -> 0 | AQ6: =ROUND(($D$6/$E$3*AO6)+($D$6/$H$2*AP6),0) -> 0 | AT6: =ROUND(($D$6/$E$3*AR6)+($D$6/$H$2*AS6),0) -> 0 | AW6: =ROUND(($D$6/$E$3*AU6)+($D$6/$H$2*AV6),0) -> 0 | AZ6: =ROUND(($D$6/$E$3*AX6)+($D$6/$H$2*AY6),0) -> 0 | BC6: =ROUND(($D$6/$E$3*BA6)+($D$6/$H$2*BB6),0) -> 0 | BF6: =ROUND(($D$6/$E$3*BD6)+($D$6/$H$2*BE6),0) -> 0 | BI6: =ROUND(($D$6/$E$3*BG6)+($D$6/$H$2*BH6),0) -> 0 | BL6: =ROUND(($D$6/$E$3*BJ6)+($D$6/$H$2*BK6),0) -> 0 | BO6: =ROUND(($D$6/$E$3*BM6)+($D$6/$H$2*BN6),0) -> 0 | BR6: =ROUND(($D$6/$E$3*BP6)+($D$6/$H$2*BQ6),0) -> 0 | BU6: =ROUND(($D$6/$E$3*BS6)+($D$6/$H$2*BT6),0) -> 0 | BX6: =ROUND(($D$6/$E$3*BV6)+($D$6/$H$2*BW6),0) -> 0 | CA6: =ROUND(($D$6/$E$3*BY6)+($D$6/$H$2*BZ6),0) -> 0 | CD6: =ROUND(($D$6/$E$3*CB6)+($D$6/$H$2*CC6),0) -> 0 | CG6: =ROUND(($D$6/$E$3*CE6)+($D$6/$H$2*CF6),0) -> 0 | CJ6: =ROUND(($D$6/$E$3*CH6)+($D$6/$H$2*CI6),0) -> 0 | CM6: =ROUND(($D$6/$E$3*CK6)+($D$6/$H$2*CL6),0) -> 0 | CP6: =ROUND(($D$6/$E$3*CN6)+($D$6/$H$2*CO6),0) -> 0 | CS6: =ROUND(($D$6/$E$3*CQ6)+($D$6/$H$2*CR6),0) -> 0 | CV6: =ROUND(($D$6/$E$3*CT6)+($D$6/$H$2*CU6),0) -> 0 | CY6: =ROUND(($D$6/$E$3*CW6)+($D$6/$H$2*CX6),0) -> 0
A7: 4 | B7: ANIL | C7: Helper | D7: 13500 | E7: =K7+N7+Q7+T7+W7+Z7+AC7+AF7+AI7+AL7+AO7+AR7+AU7+AX7+BA7+BD7+BG7+BJ7+BM7+BP7+BS7+BV7+BY7+CB7+CE7+CH7+CK7+CN7+CQ7+CT7+CW7+CZ7 -> 5 | F7: =ROUND(D7/$F$2*E7,0) -> 2177 | G7: =L7+O7+R7+U7+X7+AA7+AD7+AG7+AJ7+AM7+AP7+AS7+AV7+AY7+BB7+BE7+BH7+BK7+BN7+BQ7+BT7+BW7+BZ7+CC7+CF7+CI7+CL7+CO7+CR7+CU7+CX7+DA6 -> 17.5 | H7: =ROUND(D7/$H$2*G7,0) -> 953 | I7: =F7+H7 -> 3130 | J7: =M7+P7+S7+V7+Y7+AB7+AE7+AH7+AK7+AN7+AQ7+AT7+AW7+AZ7+BC7+BF7+BI7+BL7+BO7+BR7+BU7+BX7+CA7+CD7+CG7+CJ7+CM7+CP7+CS7+CV7+CY7 -> 3130 | M7: =ROUND(($D$7/$E$3*K7)+($D$7/$H$2*L7),0) -> 0 | P7: =ROUND(($D$7/$E$3*N7)+($D$7/$H$2*O7),0) -> 0 | Q7: 1 | R7: 3.5 | S7: =ROUND(($D$7/$E$3*Q7)+($D$7/$H$2*R7),0) -> 626 | T7: 1 | U7: 3.5 | V7: =ROUND(($D$7/$E$3*T7)+($D$7/$H$2*U7),0) -> 626 | W7: 1 | X7: 3.5 | Y7: =ROUND(($D$7/$E$3*W7)+($D$7/$H$2*X7),0) -> 626 | Z7: 1 | AA7: 3.5 | AB7: =ROUND(($D$7/$E$3*Z7)+($D$7/$H$2*AA7),0) -> 626 | AC7: 1 | AD7: 3.5 | AE7: =ROUND(($D$7/$E$3*AC7)+($D$7/$H$2*AD7),0) -> 626 | AH7: =ROUND(($D$7/$E$3*AF7)+($D$7/$H$2*AG7),0) -> 0 | AK7: =ROUND(($D$7/$E$3*AI7)+($D$7/$H$2*AJ7),0) -> 0 | AN7: =ROUND(($D$7/$E$3*AL7)+($D$7/$H$2*AM7),0) -> 0 | AQ7: =ROUND(($D$7/$E$3*AO7)+($D$7/$H$2*AP7),0) -> 0 | AT7: =ROUND(($D$7/$E$3*AR7)+($D$7/$H$2*AS7),0) -> 0 | AW7: =ROUND(($D$7/$E$3*AU7)+($D$7/$H$2*AV7),0) -> 0 | AZ7: =ROUND(($D$7/$E$3*AX7)+($D$7/$H$2*AY7),0) -> 0 | BC7: =ROUND(($D$7/$E$3*BA7)+($D$7/$H$2*BB7),0) -> 0 | BF7: =ROUND(($D$7/$E$3*BD7)+($D$7/$H$2*BE7),0) -> 0 | BI7: =ROUND(($D$7/$E$3*BG7)+($D$7/$H$2*BH7),0) -> 0 | BL7: =ROUND(($D$7/$E$3*BJ7)+($D$7/$H$2*BK7),0) -> 0 | BO7: =ROUND(($D$7/$E$3*BM7)+($D$7/$H$2*BN7),0) -> 0 | BR7: =ROUND(($D$7/$E$3*BP7)+($D$7/$H$2*BQ7),0) -> 0 | BU7: =ROUND(($D$7/$E$3*BS7)+($D$7/$H$2*BT7),0) -> 0 | BX7: =ROUND(($D$7/$E$3*BV7)+($D$7/$H$2*BW7),0) -> 0 | CA7: =ROUND(($D$7/$E$3*BY7)+($D$7/$H$2*BZ7),0) -> 0 | CD7: =ROUND(($D$7/$E$3*CB7)+($D$7/$H$2*CC7),0) -> 0 | CG7: =ROUND(($D$7/$E$3*CE7)+($D$7/$H$2*CF7),0) -> 0 | CJ7: =ROUND(($D$7/$E$3*CH7)+($D$7/$H$2*CI7),0) -> 0 | CM7: =ROUND(($D$7/$E$3*CK7)+($D$7/$H$2*CL7),0) -> 0 | CP7: =ROUND(($D$7/$E$3*CN7)+($D$7/$H$2*CO7),0) -> 0 | CS7: =ROUND(($D$7/$E$3*CQ7)+($D$7/$H$2*CR7),0) -> 0 | CV7: =ROUND(($D$7/$E$3*CT7)+($D$7/$H$2*CU7),0) -> 0 | CY7: =ROUND(($D$7/$E$3*CW7)+($D$7/$H$2*CX7),0) -> 0
A8: 5 | B8: DHARMENDRA | C8: Helper | D8: 13500 | E8: =K8+N8+Q8+T8+W8+Z8+AC8+AF8+AI8+AL8+AO8+AR8+AU8+AX8+BA8+BD8+BG8+BJ8+BM8+BP8+BS8+BV8+BY8+CB8+CE8+CH8+CK8+CN8+CQ8+CT8+CW8+CZ8 -> 7 | F8: =ROUND(D8/$F$2*E8,0) -> 3048 | G8: =L8+O8+R8+U8+X8+AA8+AD8+AG8+AJ8+AM8+AP8+AS8+AV8+AY8+BB8+BE8+BH8+BK8+BN8+BQ8+BT8+BW8+BZ8+CC8+CF8+CI8+CL8+CO8+CR8+CU8+CX8+DA7 -> 38 | H8: =ROUND(D8/$H$2*G8,0) -> 2069 | I8: =F8+H8 -> 5117 | J8: =M8+P8+S8+V8+Y8+AB8+AE8+AH8+AK8+AN8+AQ8+AT8+AW8+AZ8+BC8+BF8+BI8+BL8+BO8+BR8+BU8+BX8+CA8+CD8+CG8+CJ8+CM8+CP8+CS8+CV8+CY8 -> 5117 | K8: 1 | L8: 3.5 | M8: =ROUND(($D$8/$E$3*K8)+($D$8/$H$2*L8),0) -> 626 | N8: 1 | O8: 8 | P8: =ROUND(($D$8/$E$3*N8)+($D$8/$H$2*O8),0) -> 871 | Q8: 1 | R8: 3.5 | S8: =ROUND(($D$8/$E$3*Q8)+($D$8/$H$2*R8),0) -> 626 | T8: 1 | U8: 7.5 | V8: =ROUND(($D$8/$E$3*T8)+($D$8/$H$2*U8),0) -> 844 | W8: 1 | X8: 3.5 | Y8: =ROUND(($D$8/$E$3*W8)+($D$8/$H$2*X8),0) -> 626 | Z8: 1 | AA8: 7.5 | AB8: =ROUND(($D$8/$E$3*Z8)+($D$8/$H$2*AA8),0) -> 844 | AC8: 1 | AD8: 4.5 | AE8: =ROUND(($D$8/$E$3*AC8)+($D$8/$H$2*AD8),0) -> 680 | AH8: =ROUND(($D$8/$E$3*AF8)+($D$8/$H$2*AG8),0) -> 0 | AK8: =ROUND(($D$8/$E$3*AI8)+($D$8/$H$2*AJ8),0) -> 0 | AN8: =ROUND(($D$8/$E$3*AL8)+($D$8/$H$2*AM8),0) -> 0 | AQ8: =ROUND(($D$8/$E$3*AO8)+($D$8/$H$2*AP8),0) -> 0 | AT8: =ROUND(($D$8/$E$3*AR8)+($D$8/$H$2*AS8),0) -> 0 | AW8: =ROUND(($D$8/$E$3*AU8)+($D$8/$H$2*AV8),0) -> 0 | AZ8: =ROUND(($D$8/$E$3*AX8)+($D$8/$H$2*AY8),0) -> 0 | BC8: =ROUND(($D$8/$E$3*BA8)+($D$8/$H$2*BB8),0) -> 0 | BF8: =ROUND(($D$8/$E$3*BD8)+($D$8/$H$2*BE8),0) -> 0 | BI8: =ROUND(($D$8/$E$3*BG8)+($D$8/$H$2*BH8),0) -> 0 | BL8: =ROUND(($D$8/$E$3*BJ8)+($D$8/$H$2*BK8),0) -> 0 | BO8: =ROUND(($D$8/$E$3*BM8)+($D$8/$H$2*BN8),0) -> 0 | BR8: =ROUND(($D$8/$E$3*BP8)+($D$8/$H$2*BQ8),0) -> 0 | BU8: =ROUND(($D$8/$E$3*BS8)+($D$8/$H$2*BT8),0) -> 0 | BX8: =ROUND(($D$8/$E$3*BV8)+($D$8/$H$2*BW8),0) -> 0 | CA8: =ROUND(($D$8/$E$3*BY8)+($D$8/$H$2*BZ8),0) -> 0 | CD8: =ROUND(($D$8/$E$3*CB8)+($D$8/$H$2*CC8),0) -> 0 | CG8: =ROUND(($D$8/$E$3*CE8)+($D$8/$H$2*CF8),0) -> 0 | CJ8: =ROUND(($D$8/$E$3*CH8)+($D$8/$H$2*CI8),0) -> 0 | CM8: =ROUND(($D$8/$E$3*CK8)+($D$8/$H$2*CL8),0) -> 0 | CP8: =ROUND(($D$8/$E$3*CN8)+($D$8/$H$2*CO8),0) -> 0 | CS8: =ROUND(($D$8/$E$3*CQ8)+($D$8/$H$2*CR8),0) -> 0 | CV8: =ROUND(($D$8/$E$3*CT8)+($D$8/$H$2*CU8),0) -> 0 | CY8: =ROUND(($D$8/$E$3*CW8)+($D$8/$H$2*CX8),0) -> 0
A9: 6 | B9: RAKESH | C9: Helper | D9: 13500 | E9: =K9+N9+Q9+T9+W9+Z9+AC9+AF9+AI9+AL9+AO9+AR9+AU9+AX9+BA9+BD9+BG9+BJ9+BM9+BP9+BS9+BV9+BY9+CB9+CE9+CH9+CK9+CN9+CQ9+CT9+CW9+CZ9 -> 4 | F9: =ROUND(D9/$F$2*E9,0) -> 1742 | G9: =L9+O9+R9+U9+X9+AA9+AD9+AG9+AJ9+AM9+AP9+AS9+AV9+AY9+BB9+BE9+BH9+BK9+BN9+BQ9+BT9+BW9+BZ9+CC9+CF9+CI9+CL9+CO9+CR9+CU9+CX9+DA8 -> 14 | H9: =ROUND(D9/$H$2*G9,0) -> 762 | I9: =F9+H9 -> 2504 | J9: =M9+P9+S9+V9+Y9+AB9+AE9+AH9+AK9+AN9+AQ9+AT9+AW9+AZ9+BC9+BF9+BI9+BL9+BO9+BR9+BU9+BX9+CA9+CD9+CG9+CJ9+CM9+CP9+CS9+CV9+CY9 -> 2504 | M9: =ROUND(($D$9/$E$3*K9)+($D$9/$H$2*L9),0) -> 0 | P9: =ROUND(($D$9/$E$3*N9)+($D$9/$H$2*O9),0) -> 0 | Q9: 1 | R9: 3.5 | S9: =ROUND(($D$9/$E$3*Q9)+($D$9/$H$2*R9),0) -> 626 | V9: =ROUND(($D$9/$E$3*T9)+($D$9/$H$2*U9),0) -> 0 | W9: 1 | X9: 3.5 | Y9: =ROUND(($D$9/$E$3*W9)+($D$9/$H$2*X9),0) -> 626 | Z9: 1 | AA9: 3.5 | AB9: =ROUND(($D$9/$E$3*Z9)+($D$9/$H$2*AA9),0) -> 626 | AC9: 1 | AD9: 3.5 | AE9: =ROUND(($D$9/$E$3*AC9)+($D$9/$H$2*AD9),0) -> 626 | AH9: =ROUND(($D$9/$E$3*AF9)+($D$9/$H$2*AG9),0) -> 0 | AK9: =ROUND(($D$9/$E$3*AI9)+($D$9/$H$2*AJ9),0) -> 0 | AN9: =ROUND(($D$9/$E$3*AL9)+($D$9/$H$2*AM9),0) -> 0 | AQ9: =ROUND(($D$9/$E$3*AO9)+($D$9/$H$2*AP9),0) -> 0 | AT9: =ROUND(($D$9/$E$3*AR9)+($D$9/$H$2*AS9),0) -> 0 | AW9: =ROUND(($D$9/$E$3*AU9)+($D$9/$H$2*AV9),0) -> 0 | AZ9: =ROUND(($D$9/$E$3*AX9)+($D$9/$H$2*AY9),0) -> 0 | BC9: =ROUND(($D$9/$E$3*BA9)+($D$9/$H$2*BB9),0) -> 0 | BF9: =ROUND(($D$9/$E$3*BD9)+($D$9/$H$2*BE9),0) -> 0 | BI9: =ROUND(($D$9/$E$3*BG9)+($D$9/$H$2*BH9),0) -> 0 | BL9: =ROUND(($D$9/$E$3*BJ9)+($D$9/$H$2*BK9),0) -> 0 | BO9: =ROUND(($D$9/$E$3*BM9)+($D$9/$H$2*BN9),0) -> 0 | BR9: =ROUND(($D$9/$E$3*BP9)+($D$9/$H$2*BQ9),0) -> 0 | BU9: =ROUND(($D$9/$E$3*BS9)+($D$9/$H$2*BT9),0) -> 0 | BX9: =ROUND(($D$9/$E$3*BV9)+($D$9/$H$2*BW9),0) -> 0 | CA9: =ROUND(($D$9/$E$3*BY9)+($D$9/$H$2*BZ9),0) -> 0 | CD9: =ROUND(($D$9/$E$3*CB9)+($D$9/$H$2*CC9),0) -> 0 | CG9: =ROUND(($D$9/$E$3*CE9)+($D$9/$H$2*CF9),0) -> 0 | CJ9: =ROUND(($D$9/$E$3*CH9)+($D$9/$H$2*CI9),0) -> 0 | CM9: =ROUND(($D$9/$E$3*CK9)+($D$9/$H$2*CL9),0) -> 0 | CP9: =ROUND(($D$9/$E$3*CN9)+($D$9/$H$2*CO9),0) -> 0 | CS9: =ROUND(($D$9/$E$3*CQ9)+($D$9/$H$2*CR9),0) -> 0 | CV9: =ROUND(($D$9/$E$3*CT9)+($D$9/$H$2*CU9),0) -> 0 | CY9: =ROUND(($D$9/$E$3*CW9)+($D$9/$H$2*CX9),0) -> 0
A10: 7 | B10: KALLU | C10: Helper | D10: 13500 | E10: =K10+N10+Q10+T10+W10+Z10+AC10+AF10+AI10+AL10+AO10+AR10+AU10+AX10+BA10+BD10+BG10+BJ10+BM10+BP10+BS10+BV10+BY10+CB10+CE10+CH10+CK10+CN10+CQ10+CT10+CW10+CZ10 -> 4 | F10: =ROUND(D10/$F$2*E10,0) -> 1742 | G10: =L10+O10+R10+U10+X10+AA10+AD10+AG10+AJ10+AM10+AP10+AS10+AV10+AY10+BB10+BE10+BH10+BK10+BN10+BQ10+BT10+BW10+BZ10+CC10+CF10+CI10+CL10+CO10+CR10+CU10+CX10+DA9 -> 18 | H10: =ROUND(D10/$H$2*G10,0) -> 980 | I10: =F10+H10 -> 2722 | J10: =M10+P10+S10+V10+Y10+AB10+AE10+AH10+AK10+AN10+AQ10+AT10+AW10+AZ10+BC10+BF10+BI10+BL10+BO10+BR10+BU10+BX10+CA10+CD10+CG10+CJ10+CM10+CP10+CS10+CV10+CY10 -> 2722 | M10: =ROUND(($D$10/$E$3*K10)+($D$10/$H$2*L10),0) -> 0 | P10: =ROUND(($D$10/$E$3*N10)+($D$10/$H$2*O10),0) -> 0 | Q10: 1 | R10: 3.5 | S10: =ROUND(($D$10/$E$3*Q10)+($D$10/$H$2*R10),0) -> 626 | V10: =ROUND(($D$10/$E$3*T10)+($D$10/$H$2*U10),0) -> 0 | W10: 1 | X10: 3.5 | Y10: =ROUND(($D$10/$E$3*W10)+($D$10/$H$2*X10),0) -> 626 | Z10: 1 | AA10: 7.5 | AB10: =ROUND(($D$10/$E$3*Z10)+($D$10/$H$2*AA10),0) -> 844 | AC10: 1 | AD10: 3.5 | AE10: =ROUND(($D$10/$E$3*AC10)+($D$10/$H$2*AD10),0) -> 626 | AH10: =ROUND(($D$10/$E$3*AF10)+($D$10/$H$2*AG10),0) -> 0 | AK10: =ROUND(($D$10/$E$3*AI10)+($D$10/$H$2*AJ10),0) -> 0 | AN10: =ROUND(($D$10/$E$3*AL10)+($D$10/$H$2*AM10),0) -> 0 | AQ10: =ROUND(($D$10/$E$3*AO10)+($D$10/$H$2*AP10),0) -> 0 | AT10: =ROUND(($D$10/$E$3*AR10)+($D$10/$H$2*AS10),0) -> 0 | AW10: =ROUND(($D$10/$E$3*AU10)+($D$10/$H$2*AV10),0) -> 0 | AZ10: =ROUND(($D$10/$E$3*AX10)+($D$10/$H$2*AY10),0) -> 0 | BC10: =ROUND(($D$10/$E$3*BA10)+($D$10/$H$2*BB10),0) -> 0 | BF10: =ROUND(($D$10/$E$3*BD10)+($D$10/$H$2*BE10),0) -> 0 | BI10: =ROUND(($D$10/$E$3*BG10)+($D$10/$H$2*BH10),0) -> 0 | BL10: =ROUND(($D$10/$E$3*BJ10)+($D$10/$H$2*BK10),0) -> 0 | BO10: =ROUND(($D$10/$E$3*BM10)+($D$10/$H$2*BN10),0) -> 0 | BR10: =ROUND(($D$10/$E$3*BP10)+($D$10/$H$2*BQ10),0) -> 0 | BU10: =ROUND(($D$10/$E$3*BS10)+($D$10/$H$2*BT10),0) -> 0 | BX10: =ROUND(($D$10/$E$3*BV10)+($D$10/$H$2*BW10),0) -> 0 | CA10: =ROUND(($D$10/$E$3*BY10)+($D$10/$H$2*BZ10),0) -> 0 | CD10: =ROUND(($D$10/$E$3*CB10)+($D$10/$H$2*CC10),0) -> 0 | CG10: =ROUND(($D$10/$E$3*CE10)+($D$10/$H$2*CF10),0) -> 0 | CJ10: =ROUND(($D$10/$E$3*CH10)+($D$10/$H$2*CI10),0) -> 0 | CM10: =ROUND(($D$10/$E$3*CK10)+($D$10/$H$2*CL10),0) -> 0 | CP10: =ROUND(($D$10/$E$3*CN10)+($D$10/$H$2*CO10),0) -> 0 | CS10: =ROUND(($D$10/$E$3*CQ10)+($D$10/$H$2*CR10),0) -> 0 | CV10: =ROUND(($D$10/$E$3*CT10)+($D$10/$H$2*CU10),0) -> 0 | CY10: =ROUND(($D$10/$E$3*CW10)+($D$10/$H$2*CX10),0) -> 0
A11: 8 | B11: Dhirendra | C11: Helper | D11: 13500 | E11: =K11+N11+Q11+T11+W11+Z11+AC11+AF11+AI11+AL11+AO11+AR11+AU11+AX11+BA11+BD11+BG11+BJ11+BM11+BP11+BS11+BV11+BY11+CB11+CE11+CH11+CK11+CN11+CQ11+CT11+CW11+CZ11 -> 4 | F11: =ROUND(D11/$F$2*E11,0) -> 1742 | G11: =L11+O11+R11+U11+X11+AA11+AD11+AG11+AJ11+AM11+AP11+AS11+AV11+AY11+BB11+BE11+BH11+BK11+BN11+BQ11+BT11+BW11+BZ11+CC11+CF11+CI11+CL11+CO11+CR11+CU11+CX11+DA10 -> 14 | H11: =ROUND(D11/$H$2*G11,0) -> 762 | I11: =F11+H11 -> 2504 | J11: =M11+P11+S11+V11+Y11+AB11+AE11+AH11+AK11+AN11+AQ11+AT11+AW11+AZ11+BC11+BF11+BI11+BL11+BO11+BR11+BU11+BX11+CA11+CD11+CG11+CJ11+CM11+CP11+CS11+CV11+CY11 -> 2504 | M11: =ROUND(($D$11/$E$3*K11)+($D$11/$H$2*L11),0) -> 0 | P11: =ROUND(($D$11/$E$3*N11)+($D$11/$H$2*O11),0) -> 0 | S11: =ROUND(($D$11/$E$3*Q11)+($D$11/$H$2*R11),0) -> 0 | T11: 1 | U11: 3.5 | V11: =ROUND(($D$11/$E$3*T11)+($D$11/$H$2*U11),0) -> 626 | W11: 1 | X11: 3.5 | Y11: =ROUND(($D$11/$E$3*W11)+($D$11/$H$2*X11),0) -> 626 | Z11: 1 | AA11: 3.5 | AB11: =ROUND(($D$11/$E$3*Z11)+($D$11/$H$2*AA11),0) -> 626 | AC11: 1 | AD11: 3.5 | AE11: =ROUND(($D$11/$E$3*AC11)+($D$11/$H$2*AD11),0) -> 626 | AH11: =ROUND(($D$11/$E$3*AF11)+($D$11/$H$2*AG11),0) -> 0 | AK11: =ROUND(($D$11/$E$3*AI11)+($D$11/$H$2*AJ11),0) -> 0 | AN11: =ROUND(($D$11/$E$3*AL11)+($D$11/$H$2*AM11),0) -> 0 | AQ11: =ROUND(($D$11/$E$3*AO11)+($D$11/$H$2*AP11),0) -> 0 | AT11: =ROUND(($D$11/$E$3*AR11)+($D$11/$H$2*AS11),0) -> 0 | AW11: =ROUND(($D$11/$E$3*AU11)+($D$11/$H$2*AV11),0) -> 0 | AZ11: =ROUND(($D$11/$E$3*AX11)+($D$11/$H$2*AY11),0) -> 0 | BC11: =ROUND(($D$11/$E$3*BA11)+($D$11/$H$2*BB11),0) -> 0 | BF11: =ROUND(($D$11/$E$3*BD11)+($D$11/$H$2*BE11),0) -> 0 | BI11: =ROUND(($D$11/$E$3*BG11)+($D$11/$H$2*BH11),0) -> 0 | BL11: =ROUND(($D$11/$E$3*BJ11)+($D$11/$H$2*BK11),0) -> 0 | BO11: =ROUND(($D$11/$E$3*BM11)+($D$11/$H$2*BN11),0) -> 0 | BR11: =ROUND(($D$11/$E$3*BP11)+($D$11/$H$2*BQ11),0) -> 0 | BU11: =ROUND(($D$11/$E$3*BS11)+($D$11/$H$2*BT11),0) -> 0 | BX11: =ROUND(($D$11/$E$3*BV11)+($D$11/$H$2*BW11),0) -> 0 | CA11: =ROUND(($D$11/$E$3*BY11)+($D$11/$H$2*BZ11),0) -> 0 | CD11: =ROUND(($D$11/$E$3*CB11)+($D$11/$H$2*CC11),0) -> 0 | CG11: =ROUND(($D$11/$E$3*CE11)+($D$11/$H$2*CF11),0) -> 0 | CJ11: =ROUND(($D$11/$E$3*CH11)+($D$11/$H$2*CI11),0) -> 0 | CM11: =ROUND(($D$11/$E$3*CK11)+($D$11/$H$2*CL11),0) -> 0 | CP11: =ROUND(($D$11/$E$3*CN11)+($D$11/$H$2*CO11),0) -> 0 | CS11: =ROUND(($D$11/$E$3*CQ11)+($D$11/$H$2*CR11),0) -> 0 | CV11: =ROUND(($D$11/$E$3*CT11)+($D$11/$H$2*CU11),0) -> 0 | CY11: =ROUND(($D$11/$E$3*CW11)+($D$11/$H$2*CX11),0) -> 0
A12: 9 | B12: Aakash | C12: Helper | D12: 13500 | E12: =K12+N12+Q12+T12+W12+Z12+AC12+AF12+AI12+AL12+AO12+AR12+AU12+AX12+BA12+BD12+BG12+BJ12+BM12+BP12+BS12+BV12+BY12+CB12+CE12+CH12+CK12+CN12+CQ12+CT12+CW12+CZ12 -> 4 | F12: =ROUND(D12/$F$2*E12,0) -> 1742 | G12: =L12+O12+R12+U12+X12+AA12+AD12+AG12+AJ12+AM12+AP12+AS12+AV12+AY12+BB12+BE12+BH12+BK12+BN12+BQ12+BT12+BW12+BZ12+CC12+CF12+CI12+CL12+CO12+CR12+CU12+CX12+DA11 -> 14 | H12: =ROUND(D12/$H$2*G12,0) -> 762 | I12: =F12+H12 -> 2504 | J12: =M12+P12+S12+V12+Y12+AB12+AE12+AH12+AK12+AN12+AQ12+AT12+AW12+AZ12+BC12+BF12+BI12+BL12+BO12+BR12+BU12+BX12+CA12+CD12+CG12+CJ12+CM12+CP12+CS12+CV12+CY12 -> 2504 | M12: =ROUND(($D$12/$E$3*K12)+($D$12/$H$2*L12),0) -> 0 | P12: =ROUND(($D$12/$E$3*N12)+($D$12/$H$2*O12),0) -> 0 | S12: =ROUND(($D$12/$E$3*Q12)+($D$12/$H$2*R12),0) -> 0 | T12: 1 | U12: 3.5 | V12: =ROUND(($D$12/$E$3*T12)+($D$12/$H$2*U12),0) -> 626 | W12: 1 | X12: 3.5 | Y12: =ROUND(($D$12/$E$3*W12)+($D$12/$H$2*X12),0) -> 626 | Z12: 1 | AA12: 3.5 | AB12: =ROUND(($D$12/$E$3*Z12)+($D$12/$H$2*AA12),0) -> 626 | AC12: 1 | AD12: 3.5 | AE12: =ROUND(($D$12/$E$3*AC12)+($D$12/$H$2*AD12),0) -> 626 | AH12: =ROUND(($D$12/$E$3*AF12)+($D$12/$H$2*AG12),0) -> 0 | AK12: =ROUND(($D$12/$E$3*AI12)+($D$12/$H$2*AJ12),0) -> 0 | AN12: =ROUND(($D$12/$E$3*AL12)+($D$12/$H$2*AM12),0) -> 0 | AQ12: =ROUND(($D$12/$E$3*AO12)+($D$12/$H$2*AP12),0) -> 0 | AT12: =ROUND(($D$12/$E$3*AR12)+($D$12/$H$2*AS12),0) -> 0 | AW12: =ROUND(($D$12/$E$3*AU12)+($D$12/$H$2*AV12),0) -> 0 | AZ12: =ROUND(($D$12/$E$3*AX12)+($D$12/$H$2*AY12),0) -> 0 | BC12: =ROUND(($D$12/$E$3*BA12)+($D$12/$H$2*BB12),0) -> 0 | BF12: =ROUND(($D$12/$E$3*BD12)+($D$12/$H$2*BE12),0) -> 0 | BI12: =ROUND(($D$12/$E$3*BG12)+($D$12/$H$2*BH12),0) -> 0 | BL12: =ROUND(($D$12/$E$3*BJ12)+($D$12/$H$2*BK12),0) -> 0 | BO12: =ROUND(($D$12/$E$3*BM12)+($D$12/$H$2*BN12),0) -> 0 | BR12: =ROUND(($D$12/$E$3*BP12)+($D$12/$H$2*BQ12),0) -> 0 | BU12: =ROUND(($D$12/$E$3*BS12)+($D$12/$H$2*BT12),0) -> 0 | BX12: =ROUND(($D$12/$E$3*BV12)+($D$12/$H$2*BW12),0) -> 0 | CA12: =ROUND(($D$12/$E$3*BY12)+($D$12/$H$2*BZ12),0) -> 0 | CD12: =ROUND(($D$12/$E$3*CB12)+($D$12/$H$2*CC12),0) -> 0 | CG12: =ROUND(($D$12/$E$3*CE12)+($D$12/$H$2*CF12),0) -> 0 | CJ12: =ROUND(($D$12/$E$3*CH12)+($D$12/$H$2*CI12),0) -> 0 | CM12: =ROUND(($D$12/$E$3*CK12)+($D$12/$H$2*CL12),0) -> 0 | CP12: =ROUND(($D$12/$E$3*CN12)+($D$12/$H$2*CO12),0) -> 0 | CS12: =ROUND(($D$12/$E$3*CQ12)+($D$12/$H$2*CR12),0) -> 0 | CV12: =ROUND(($D$12/$E$3*CT12)+($D$12/$H$2*CU12),0) -> 0 | CY12: =ROUND(($D$12/$E$3*CW12)+($D$12/$H$2*CX12),0) -> 0
A13: 10 | B13: PREM PRAKASH | C13: Helper | D13: 13500 | E13: =K13+N13+Q13+T13+W13+Z13+AC13+AF13+AI13+AL13+AO13+AR13+AU13+AX13+BA13+BD13+BG13+BJ13+BM13+BP13+BS13+BV13+BY13+CB13+CE13+CH13+CK13+CN13+CQ13+CT13+CW13+CZ13 -> 7 | F13: =ROUND(D13/$F$2*E13,0) -> 3048 | G13: =L13+O13+R13+U13+X13+AA13+AD13+AG13+AJ13+AM13+AP13+AS13+AV13+AY13+BB13+BE13+BH13+BK13+BN13+BQ13+BT13+BW13+BZ13+CC13+CF13+CI13+CL13+CO13+CR13+CU13+CX13+DA12 -> 41 | H13: =ROUND(D13/$H$2*G13,0) -> 2232 | I13: =F13+H13 -> 5280 | J13: =M13+P13+S13+V13+Y13+AB13+AE13+AH13+AK13+AN13+AQ13+AT13+AW13+AZ13+BC13+BF13+BI13+BL13+BO13+BR13+BU13+BX13+CA13+CD13+CG13+CJ13+CM13+CP13+CS13+CV13+CY13 -> 5281 | K13: 1 | L13: 3.5 | M13: =ROUND(($D$13/$E$3*K13)+($D$13/$H$2*L13),0) -> 626 | N13: 1 | O13: 8 | P13: =ROUND(($D$13/$E$3*N13)+($D$13/$H$2*O13),0) -> 871 | Q13: 1 | R13: 7.5 | S13: =ROUND(($D$13/$E$3*Q13)+($D$13/$H$2*R13),0) -> 844 | T13: 1 | U13: 7.5 | V13: =ROUND(($D$13/$E$3*T13)+($D$13/$H$2*U13),0) -> 844 | W13: 1 | X13: 3.5 | Y13: =ROUND(($D$13/$E$3*W13)+($D$13/$H$2*X13),0) -> 626 | Z13: 1 | AA13: 7.5 | AB13: =ROUND(($D$13/$E$3*Z13)+($D$13/$H$2*AA13),0) -> 844 | AC13: 1 | AD13: 3.5 | AE13: =ROUND(($D$13/$E$3*AC13)+($D$13/$H$2*AD13),0) -> 626 | AH13: =ROUND(($D$13/$E$3*AF13)+($D$13/$H$2*AG13),0) -> 0 | AK13: =ROUND(($D$13/$E$3*AI13)+($D$13/$H$2*AJ13),0) -> 0 | AN13: =ROUND(($D$13/$E$3*AL13)+($D$13/$H$2*AM13),0) -> 0 | AQ13: =ROUND(($D$13/$E$3*AO13)+($D$13/$H$2*AP13),0) -> 0 | AT13: =ROUND(($D$13/$E$3*AR13)+($D$13/$H$2*AS13),0) -> 0 | AW13: =ROUND(($D$13/$E$3*AU13)+($D$13/$H$2*AV13),0) -> 0 | AZ13: =ROUND(($D$13/$E$3*AX13)+($D$13/$H$2*AY13),0) -> 0 | BC13: =ROUND(($D$13/$E$3*BA13)+($D$13/$H$2*BB13),0) -> 0 | BF13: =ROUND(($D$13/$E$3*BD13)+($D$13/$H$2*BE13),0) -> 0 | BI13: =ROUND(($D$13/$E$3*BG13)+($D$13/$H$2*BH13),0) -> 0 | BL13: =ROUND(($D$13/$E$3*BJ13)+($D$13/$H$2*BK13),0) -> 0 | BO13: =ROUND(($D$13/$E$3*BM13)+($D$13/$H$2*BN13),0) -> 0 | BR13: =ROUND(($D$13/$E$3*BP13)+($D$13/$H$2*BQ13),0) -> 0 | BU13: =ROUND(($D$13/$E$3*BS13)+($D$13/$H$2*BT13),0) -> 0 | BX13: =ROUND(($D$13/$E$3*BV13)+($D$13/$H$2*BW13),0) -> 0 | CA13: =ROUND(($D$13/$E$3*BY13)+($D$13/$H$2*BZ13),0) -> 0 | CD13: =ROUND(($D$13/$E$3*CB13)+($D$13/$H$2*CC13),0) -> 0 | CG13: =ROUND(($D$13/$E$3*CE13)+($D$13/$H$2*CF13),0) -> 0 | CJ13: =ROUND(($D$13/$E$3*CH13)+($D$13/$H$2*CI13),0) -> 0 | CM13: =ROUND(($D$13/$E$3*CK13)+($D$13/$H$2*CL13),0) -> 0 | CP13: =ROUND(($D$13/$E$3*CN13)+($D$13/$H$2*CO13),0) -> 0 | CS13: =ROUND(($D$13/$E$3*CQ13)+($D$13/$H$2*CR13),0) -> 0 | CV13: =ROUND(($D$13/$E$3*CT13)+($D$13/$H$2*CU13),0) -> 0 | CY13: =ROUND(($D$13/$E$3*CW13)+($D$13/$H$2*CX13),0) -> 0
A14: 11 | B14: Ankur | C14: Helper | D14: 13500 | E14: =K14+N14+Q14+T14+W14+Z14+AC14+AF14+AI14+AL14+AO14+AR14+AU14+AX14+BA14+BD14+BG14+BJ14+BM14+BP14+BS14+BV14+BY14+CB14+CE14+CH14+CK14+CN14+CQ14+CT14+CW14+CZ14 -> 4 | F14: =ROUND(D14/$F$2*E14,0) -> 1742 | G14: =L14+O14+R14+U14+X14+AA14+AD14+AG14+AJ14+AM14+AP14+AS14+AV14+AY14+BB14+BE14+BH14+BK14+BN14+BQ14+BT14+BW14+BZ14+CC14+CF14+CI14+CL14+CO14+CR14+CU14+CX14+DA13 -> 14 | H14: =ROUND(D14/$H$2*G14,0) -> 762 | I14: =F14+H14 -> 2504 | J14: =M14+P14+S14+V14+Y14+AB14+AE14+AH14+AK14+AN14+AQ14+AT14+AW14+AZ14+BC14+BF14+BI14+BL14+BO14+BR14+BU14+BX14+CA14+CD14+CG14+CJ14+CM14+CP14+CS14+CV14+CY14 -> 2504 | M14: =ROUND(($D$14/$E$3*K14)+($D$14/$H$2*L14),0) -> 0 | P14: =ROUND(($D$14/$E$3*N14)+($D$14/$H$2*O14),0) -> 0 | S14: =ROUND(($D$14/$E$3*Q14)+($D$14/$H$2*R14),0) -> 0 | T14: 1 | U14: 3.5 | V14: =ROUND(($D$14/$E$3*T14)+($D$14/$H$2*U14),0) -> 626 | W14: 1 | X14: 3.5 | Y14: =ROUND(($D$14/$E$3*W14)+($D$14/$H$2*X14),0) -> 626 | Z14: 1 | AA14: 3.5 | AB14: =ROUND(($D$14/$E$3*Z14)+($D$14/$H$2*AA14),0) -> 626 | AC14: 1 | AD14: 3.5 | AE14: =ROUND(($D$14/$E$3*AC14)+($D$14/$H$2*AD14),0) -> 626 | AH14: =ROUND(($D$14/$E$3*AF14)+($D$14/$H$2*AG14),0) -> 0 | AK14: =ROUND(($D$14/$E$3*AI14)+($D$14/$H$2*AJ14),0) -> 0 | AN14: =ROUND(($D$14/$E$3*AL14)+($D$14/$H$2*AM14),0) -> 0 | AQ14: =ROUND(($D$14/$E$3*AO14)+($D$14/$H$2*AP14),0) -> 0 | AT14: =ROUND(($D$14/$E$3*AR14)+($D$14/$H$2*AS14),0) -> 0 | AW14: =ROUND(($D$14/$E$3*AU14)+($D$14/$H$2*AV14),0) -> 0 | AZ14: =ROUND(($D$14/$E$3*AX14)+($D$14/$H$2*AY14),0) -> 0 | BC14: =ROUND(($D$14/$E$3*BA14)+($D$14/$H$2*BB14),0) -> 0 | BF14: =ROUND(($D$14/$E$3*BD14)+($D$14/$H$2*BE14),0) -> 0 | BI14: =ROUND(($D$14/$E$3*BG14)+($D$14/$H$2*BH14),0) -> 0 | BL14: =ROUND(($D$14/$E$3*BJ14)+($D$14/$H$2*BK14),0) -> 0 | BO14: =ROUND(($D$14/$E$3*BM14)+($D$14/$H$2*BN14),0) -> 0 | BR14: =ROUND(($D$14/$E$3*BP14)+($D$14/$H$2*BQ14),0) -> 0 | BU14: =ROUND(($D$14/$E$3*BS14)+($D$14/$H$2*BT14),0) -> 0 | BX14: =ROUND(($D$14/$E$3*BV14)+($D$14/$H$2*BW14),0) -> 0 | CA14: =ROUND(($D$14/$E$3*BY14)+($D$14/$H$2*BZ14),0) -> 0 | CD14: =ROUND(($D$14/$E$3*CB14)+($D$14/$H$2*CC14),0) -> 0 | CG14: =ROUND(($D$14/$E$3*CE14)+($D$14/$H$2*CF14),0) -> 0 | CJ14: =ROUND(($D$14/$E$3*CH14)+($D$14/$H$2*CI14),0) -> 0 | CM14: =ROUND(($D$14/$E$3*CK14)+($D$14/$H$2*CL14),0) -> 0 | CP14: =ROUND(($D$14/$E$3*CN14)+($D$14/$H$2*CO14),0) -> 0 | CS14: =ROUND(($D$14/$E$3*CQ14)+($D$14/$H$2*CR14),0) -> 0 | CV14: =ROUND(($D$14/$E$3*CT14)+($D$14/$H$2*CU14),0) -> 0 | CY14: =ROUND(($D$14/$E$3*CW14)+($D$14/$H$2*CX14),0) -> 0
A15: 12 | B15: Ram Jeewan | C15: Helper | D15: 13500 | E15: =K15+N15+Q15+T15+W15+Z15+AC15+AF15+AI15+AL15+AO15+AR15+AU15+AX15+BA15+BD15+BG15+BJ15+BM15+BP15+BS15+BV15+BY15+CB15+CE15+CH15+CK15+CN15+CQ15+CT15+CW15+CZ15 -> 2 | F15: =ROUND(D15/$F$2*E15,0) -> 871 | G15: =L15+O15+R15+U15+X15+AA15+AD15+AG15+AJ15+AM15+AP15+AS15+AV15+AY15+BB15+BE15+BH15+BK15+BN15+BQ15+BT15+BW15+BZ15+CC15+CF15+CI15+CL15+CO15+CR15+CU15+CX15+DA14 -> 7 | H15: =ROUND(D15/$H$2*G15,0) -> 381 | I15: =F15+H15 -> 1252 | J15: =M15+P15+S15+V15+Y15+AB15+AE15+AH15+AK15+AN15+AQ15+AT15+AW15+AZ15+BC15+BF15+BI15+BL15+BO15+BR15+BU15+BX15+CA15+CD15+CG15+CJ15+CM15+CP15+CS15+CV15+CY15 -> 1252 | M15: =ROUND(($D$15/$E$3*K15)+($D$15/$H$2*L15),0) -> 0 | P15: =ROUND(($D$15/$E$3*N15)+($D$15/$H$2*O15),0) -> 0 | S15: =ROUND(($D$15/$E$3*Q15)+($D$15/$H$2*R15),0) -> 0 | T15: 1 | U15: 3.5 | V15: =ROUND(($D$15/$E$3*T15)+($D$15/$H$2*U15),0) -> 626 | W15: 1 | X15: 3.5 | Y15: =ROUND(($D$15/$E$3*W15)+($D$15/$H$2*X15),0) -> 626 | AB15: =ROUND(($D$15/$E$3*Z15)+($D$15/$H$2*AA15),0) -> 0 | AE15: =ROUND(($D$15/$E$3*AC15)+($D$15/$H$2*AD15),0) -> 0 | AH15: =ROUND(($D$15/$E$3*AF15)+($D$15/$H$2*AG15),0) -> 0 | AK15: =ROUND(($D$15/$E$3*AI15)+($D$15/$H$2*AJ15),0) -> 0 | AN15: =ROUND(($D$15/$E$3*AL15)+($D$15/$H$2*AM15),0) -> 0 | AQ15: =ROUND(($D$15/$E$3*AO15)+($D$15/$H$2*AP15),0) -> 0 | AT15: =ROUND(($D$15/$E$3*AR15)+($D$15/$H$2*AS15),0) -> 0 | AW15: =ROUND(($D$15/$E$3*AU15)+($D$15/$H$2*AV15),0) -> 0 | AZ15: =ROUND(($D$15/$E$3*AX15)+($D$15/$H$2*AY15),0) -> 0 | BC15: =ROUND(($D$15/$E$3*BA15)+($D$15/$H$2*BB15),0) -> 0 | BF15: =ROUND(($D$15/$E$3*BD15)+($D$15/$H$2*BE15),0) -> 0 | BI15: =ROUND(($D$15/$E$3*BG15)+($D$15/$H$2*BH15),0) -> 0 | BL15: =ROUND(($D$15/$E$3*BJ15)+($D$15/$H$2*BK15),0) -> 0 | BO15: =ROUND(($D$15/$E$3*BM15)+($D$15/$H$2*BN15),0) -> 0 | BR15: =ROUND(($D$15/$E$3*BP15)+($D$15/$H$2*BQ15),0) -> 0 | BU15: =ROUND(($D$15/$E$3*BS15)+($D$15/$H$2*BT15),0) -> 0 | BX15: =ROUND(($D$15/$E$3*BV15)+($D$15/$H$2*BW15),0) -> 0 | CA15: =ROUND(($D$15/$E$3*BY15)+($D$15/$H$2*BZ15),0) -> 0 | CD15: =ROUND(($D$15/$E$3*CB15)+($D$15/$H$2*CC15),0) -> 0 | CG15: =ROUND(($D$15/$E$3*CE15)+($D$15/$H$2*CF15),0) -> 0 | CJ15: =ROUND(($D$15/$E$3*CH15)+($D$15/$H$2*CI15),0) -> 0 | CM15: =ROUND(($D$15/$E$3*CK15)+($D$15/$H$2*CL15),0) -> 0 | CP15: =ROUND(($D$15/$E$3*CN15)+($D$15/$H$2*CO15),0) -> 0 | CS15: =ROUND(($D$15/$E$3*CQ15)+($D$15/$H$2*CR15),0) -> 0 | CV15: =ROUND(($D$15/$E$3*CT15)+($D$15/$H$2*CU15),0) -> 0 | CY15: =ROUND(($D$15/$E$3*CW15)+($D$15/$H$2*CX15),0) -> 0
A16: 13 | B16: Arvind | C16: Helper | D16: 13500 | E16: =K16+N16+Q16+T16+W16+Z16+AC16+AF16+AI16+AL16+AO16+AR16+AU16+AX16+BA16+BD16+BG16+BJ16+BM16+BP16+BS16+BV16+BY16+CB16+CE16+CH16+CK16+CN16+CQ16+CT16+CW16+CZ16 -> 2 | F16: =ROUND(D16/$F$2*E16,0) -> 871 | G16: =L16+O16+R16+U16+X16+AA16+AD16+AG16+AJ16+AM16+AP16+AS16+AV16+AY16+BB16+BE16+BH16+BK16+BN16+BQ16+BT16+BW16+BZ16+CC16+CF16+CI16+CL16+CO16+CR16+CU16+CX16+DA15 -> 7 | H16: =ROUND(D16/$H$2*G16,0) -> 381 | I16: =F16+H16 -> 1252 | J16: =M16+P16+S16+V16+Y16+AB16+AE16+AH16+AK16+AN16+AQ16+AT16+AW16+AZ16+BC16+BF16+BI16+BL16+BO16+BR16+BU16+BX16+CA16+CD16+CG16+CJ16+CM16+CP16+CS16+CV16+CY16 -> 1252 | M16: =ROUND(($D$16/$E$3*K16)+($D$16/$H$2*L16),0) -> 0 | P16: =ROUND(($D$16/$E$3*N16)+($D$16/$H$2*O16),0) -> 0 | S16: =ROUND(($D$16/$E$3*Q16)+($D$16/$H$2*R16),0) -> 0 | T16: 1 | U16: 3.5 | V16: =ROUND(($D$16/$E$3*T16)+($D$16/$H$2*U16),0) -> 626 | W16: 1 | X16: 3.5 | Y16: =ROUND(($D$16/$E$3*W16)+($D$16/$H$2*X16),0) -> 626 | AB16: =ROUND(($D$16/$E$3*Z16)+($D$16/$H$2*AA16),0) -> 0 | AE16: =ROUND(($D$16/$E$3*AC16)+($D$16/$H$2*AD16),0) -> 0 | AH16: =ROUND(($D$16/$E$3*AF16)+($D$16/$H$2*AG16),0) -> 0 | AK16: =ROUND(($D$16/$E$3*AI16)+($D$16/$H$2*AJ16),0) -> 0 | AN16: =ROUND(($D$16/$E$3*AL16)+($D$16/$H$2*AM16),0) -> 0 | AQ16: =ROUND(($D$16/$E$3*AO16)+($D$16/$H$2*AP16),0) -> 0 | AT16: =ROUND(($D$16/$E$3*AR16)+($D$16/$H$2*AS16),0) -> 0 | AW16: =ROUND(($D$16/$E$3*AU16)+($D$16/$H$2*AV16),0) -> 0 | AZ16: =ROUND(($D$16/$E$3*AX16)+($D$16/$H$2*AY16),0) -> 0 | BC16: =ROUND(($D$16/$E$3*BA16)+($D$16/$H$2*BB16),0) -> 0 | BF16: =ROUND(($D$16/$E$3*BD16)+($D$16/$H$2*BE16),0) -> 0 | BI16: =ROUND(($D$16/$E$3*BG16)+($D$16/$H$2*BH16),0) -> 0 | BL16: =ROUND(($D$16/$E$3*BJ16)+($D$16/$H$2*BK16),0) -> 0 | BO16: =ROUND(($D$16/$E$3*BM16)+($D$16/$H$2*BN16),0) -> 0 | BR16: =ROUND(($D$16/$E$3*BP16)+($D$16/$H$2*BQ16),0) -> 0 | BU16: =ROUND(($D$16/$E$3*BS16)+($D$16/$H$2*BT16),0) -> 0 | BX16: =ROUND(($D$16/$E$3*BV16)+($D$16/$H$2*BW16),0) -> 0 | CA16: =ROUND(($D$16/$E$3*BY16)+($D$16/$H$2*BZ16),0) -> 0 | CD16: =ROUND(($D$16/$E$3*CB16)+($D$16/$H$2*CC16),0) -> 0 | CG16: =ROUND(($D$16/$E$3*CE16)+($D$16/$H$2*CF16),0) -> 0 | CJ16: =ROUND(($D$16/$E$3*CH16)+($D$16/$H$2*CI16),0) -> 0 | CM16: =ROUND(($D$16/$E$3*CK16)+($D$16/$H$2*CL16),0) -> 0 | CP16: =ROUND(($D$16/$E$3*CN16)+($D$16/$H$2*CO16),0) -> 0 | CS16: =ROUND(($D$16/$E$3*CQ16)+($D$16/$H$2*CR16),0) -> 0 | CV16: =ROUND(($D$16/$E$3*CT16)+($D$16/$H$2*CU16),0) -> 0 | CY16: =ROUND(($D$16/$E$3*CW16)+($D$16/$H$2*CX16),0) -> 0
A17: 14 | B17: Ankit | C17: Helper | D17: 13500 | E17: =K17+N17+Q17+T17+W17+Z17+AC17+AF17+AI17+AL17+AO17+AR17+AU17+AX17+BA17+BD17+BG17+BJ17+BM17+BP17+BS17+BV17+BY17+CB17+CE17+CH17+CK17+CN17+CQ17+CT17+CW17+CZ17 -> 4 | F17: =ROUND(D17/$F$2*E17,0) -> 1742 | G17: =L17+O17+R17+U17+X17+AA17+AD17+AG17+AJ17+AM17+AP17+AS17+AV17+AY17+BB17+BE17+BH17+BK17+BN17+BQ17+BT17+BW17+BZ17+CC17+CF17+CI17+CL17+CO17+CR17+CU17+CX17+DA16 -> 12.5 | H17: =ROUND(D17/$H$2*G17,0) -> 680 | I17: =F17+H17 -> 2422 | J17: =M17+P17+S17+V17+Y17+AB17+AE17+AH17+AK17+AN17+AQ17+AT17+AW17+AZ17+BC17+BF17+BI17+BL17+BO17+BR17+BU17+BX17+CA17+CD17+CG17+CJ17+CM17+CP17+CS17+CV17+CY17 -> 2422 | M17: =ROUND(($D$17/$E$3*K17)+($D$17/$H$2*L17),0) -> 0 | P17: =ROUND(($D$17/$E$3*N17)+($D$17/$H$2*O17),0) -> 0 | S17: =ROUND(($D$17/$E$3*Q17)+($D$17/$H$2*R17),0) -> 0 | T17: 1 | U17: 3.5 | V17: =ROUND(($D$17/$E$3*T17)+($D$17/$H$2*U17),0) -> 626 | W17: 1 | X17: 3.5 | Y17: =ROUND(($D$17/$E$3*W17)+($D$17/$H$2*X17),0) -> 626 | Z17: 1 | AA17: 2 | AB17: =ROUND(($D$17/$E$3*Z17)+($D$17/$H$2*AA17),0) -> 544 | AC17: 1 | AD17: 3.5 | AE17: =ROUND(($D$17/$E$3*AC17)+($D$17/$H$2*AD17),0) -> 626 | AH17: =ROUND(($D$17/$E$3*AF17)+($D$17/$H$2*AG17),0) -> 0 | AK17: =ROUND(($D$17/$E$3*AI17)+($D$17/$H$2*AJ17),0) -> 0 | AN17: =ROUND(($D$17/$E$3*AL17)+($D$17/$H$2*AM17),0) -> 0 | AQ17: =ROUND(($D$17/$E$3*AO17)+($D$17/$H$2*AP17),0) -> 0 | AT17: =ROUND(($D$17/$E$3*AR17)+($D$17/$H$2*AS17),0) -> 0 | AW17: =ROUND(($D$17/$E$3*AU17)+($D$17/$H$2*AV17),0) -> 0 | AZ17: =ROUND(($D$17/$E$3*AX17)+($D$17/$H$2*AY17),0) -> 0 | BC17: =ROUND(($D$17/$E$3*BA17)+($D$17/$H$2*BB17),0) -> 0 | BF17: =ROUND(($D$17/$E$3*BD17)+($D$17/$H$2*BE17),0) -> 0 | BI17: =ROUND(($D$17/$E$3*BG17)+($D$17/$H$2*BH17),0) -> 0 | BL17: =ROUND(($D$17/$E$3*BJ17)+($D$17/$H$2*BK17),0) -> 0 | BO17: =ROUND(($D$17/$E$3*BM17)+($D$17/$H$2*BN17),0) -> 0 | BR17: =ROUND(($D$17/$E$3*BP17)+($D$17/$H$2*BQ17),0) -> 0 | BU17: =ROUND(($D$17/$E$3*BS17)+($D$17/$H$2*BT17),0) -> 0 | BX17: =ROUND(($D$17/$E$3*BV17)+($D$17/$H$2*BW17),0) -> 0 | CA17: =ROUND(($D$17/$E$3*BY17)+($D$17/$H$2*BZ17),0) -> 0 | CD17: =ROUND(($D$17/$E$3*CB17)+($D$17/$H$2*CC17),0) -> 0 | CG17: =ROUND(($D$17/$E$3*CE17)+($D$17/$H$2*CF17),0) -> 0 | CJ17: =ROUND(($D$17/$E$3*CH17)+($D$17/$H$2*CI17),0) -> 0 | CM17: =ROUND(($D$17/$E$3*CK17)+($D$17/$H$2*CL17),0) -> 0 | CP17: =ROUND(($D$17/$E$3*CN17)+($D$17/$H$2*CO17),0) -> 0 | CS17: =ROUND(($D$17/$E$3*CQ17)+($D$17/$H$2*CR17),0) -> 0 | CV17: =ROUND(($D$17/$E$3*CT17)+($D$17/$H$2*CU17),0) -> 0 | CY17: =ROUND(($D$17/$E$3*CW17)+($D$17/$H$2*CX17),0) -> 0
A18: 15 | B18: NIRMAL | C18: Helper | D18: 13500 | E18: =K18+N18+Q18+T18+W18+Z18+AC18+AF18+AI18+AL18+AO18+AR18+AU18+AX18+BA18+BD18+BG18+BJ18+BM18+BP18+BS18+BV18+BY18+CB18+CE18+CH18+CK18+CN18+CQ18+CT18+CW18+CZ18 -> 3 | F18: =ROUND(D18/$F$2*E18,0) -> 1306 | G18: =L18+O18+R18+U18+X18+AA18+AD18+AG18+AJ18+AM18+AP18+AS18+AV18+AY18+BB18+BE18+BH18+BK18+BN18+BQ18+BT18+BW18+BZ18+CC18+CF18+CI18+CL18+CO18+CR18+CU18+CX18+DA17 -> 10.5 | H18: =ROUND(D18/$H$2*G18,0) -> 572 | I18: =F18+H18 -> 1878 | J18: =M18+P18+S18+V18+Y18+AB18+AE18+AH18+AK18+AN18+AQ18+AT18+AW18+AZ18+BC18+BF18+BI18+BL18+BO18+BR18+BU18+BX18+CA18+CD18+CG18+CJ18+CM18+CP18+CS18+CV18+CY18 -> 1878 | M18: =ROUND(($D$18/$E$3*K18)+($D$18/$H$2*L18),0) -> 0 | P18: =ROUND(($D$18/$E$3*N18)+($D$18/$H$2*O18),0) -> 0 | S18: =ROUND(($D$18/$E$3*Q18)+($D$18/$H$2*R18),0) -> 0 | V18: =ROUND(($D$18/$E$3*T18)+($D$18/$H$2*U18),0) -> 0 | W18: 1 | X18: 3.5 | Y18: =ROUND(($D$18/$E$3*W18)+($D$18/$H$2*X18),0) -> 626 | Z18: 1 | AA18: 3.5 | AB18: =ROUND(($D$18/$E$3*Z18)+($D$18/$H$2*AA18),0) -> 626 | AC18: 1 | AD18: 3.5 | AE18: =ROUND(($D$18/$E$3*AC18)+($D$18/$H$2*AD18),0) -> 626 | AH18: =ROUND(($D$18/$E$3*AF18)+($D$18/$H$2*AG18),0) -> 0 | AK18: =ROUND(($D$18/$E$3*AI18)+($D$18/$H$2*AJ18),0) -> 0 | AN18: =ROUND(($D$18/$E$3*AL18)+($D$18/$H$2*AM18),0) -> 0 | AQ18: =ROUND(($D$18/$E$3*AO18)+($D$18/$H$2*AP18),0) -> 0 | AT18: =ROUND(($D$18/$E$3*AR18)+($D$18/$H$2*AS18),0) -> 0 | AW18: =ROUND(($D$18/$E$3*AU18)+($D$18/$H$2*AV18),0) -> 0 | AZ18: =ROUND(($D$18/$E$3*AX18)+($D$18/$H$2*AY18),0) -> 0 | BC18: =ROUND(($D$18/$E$3*BA18)+($D$18/$H$2*BB18),0) -> 0 | BF18: =ROUND(($D$18/$E$3*BD18)+($D$18/$H$2*BE18),0) -> 0 | BI18: =ROUND(($D$18/$E$3*BG18)+($D$18/$H$2*BH18),0) -> 0 | BL18: =ROUND(($D$18/$E$3*BJ18)+($D$18/$H$2*BK18),0) -> 0 | BO18: =ROUND(($D$18/$E$3*BM18)+($D$18/$H$2*BN18),0) -> 0 | BR18: =ROUND(($D$18/$E$3*BP18)+($D$18/$H$2*BQ18),0) -> 0 | BU18: =ROUND(($D$18/$E$3*BS18)+($D$18/$H$2*BT18),0) -> 0 | BX18: =ROUND(($D$18/$E$3*BV18)+($D$18/$H$2*BW18),0) -> 0 | CA18: =ROUND(($D$18/$E$3*BY18)+($D$18/$H$2*BZ18),0) -> 0 | CD18: =ROUND(($D$18/$E$3*CB18)+($D$18/$H$2*CC18),0) -> 0 | CG18: =ROUND(($D$18/$E$3*CE18)+($D$18/$H$2*CF18),0) -> 0 | CJ18: =ROUND(($D$18/$E$3*CH18)+($D$18/$H$2*CI18),0) -> 0 | CM18: =ROUND(($D$18/$E$3*CK18)+($D$18/$H$2*CL18),0) -> 0 | CP18: =ROUND(($D$18/$E$3*CN18)+($D$18/$H$2*CO18),0) -> 0 | CS18: =ROUND(($D$18/$E$3*CQ18)+($D$18/$H$2*CR18),0) -> 0 | CV18: =ROUND(($D$18/$E$3*CT18)+($D$18/$H$2*CU18),0) -> 0 | CY18: =ROUND(($D$18/$E$3*CW18)+($D$18/$H$2*CX18),0) -> 0
A19: 16 | B19: SANDEEP | C19: Helper | D19: 13500 | E19: =K19+N19+Q19+T19+W19+Z19+AC19+AF19+AI19+AL19+AO19+AR19+AU19+AX19+BA19+BD19+BG19+BJ19+BM19+BP19+BS19+BV19+BY19+CB19+CE19+CH19+CK19+CN19+CQ19+CT19+CW19+CZ19 -> 2 | F19: =ROUND(D19/$F$2*E19,0) -> 871 | G19: =L19+O19+R19+U19+X19+AA19+AD19+AG19+AJ19+AM19+AP19+AS19+AV19+AY19+BB19+BE19+BH19+BK19+BN19+BQ19+BT19+BW19+BZ19+CC19+CF19+CI19+CL19+CO19+CR19+CU19+CX19+DA18 -> 7 | H19: =ROUND(D19/$H$2*G19,0) -> 381 | I19: =F19+H19 -> 1252 | J19: =M19+P19+S19+V19+Y19+AB19+AE19+AH19+AK19+AN19+AQ19+AT19+AW19+AZ19+BC19+BF19+BI19+BL19+BO19+BR19+BU19+BX19+CA19+CD19+CG19+CJ19+CM19+CP19+CS19+CV19+CY19 -> 1252 | M19: =ROUND(($D$19/$E$3*K19)+($D$19/$H$2*L19),0) -> 0 | P19: =ROUND(($D$19/$E$3*N19)+($D$19/$H$2*O19),0) -> 0 | S19: =ROUND(($D$19/$E$3*Q19)+($D$19/$H$2*R19),0) -> 0 | V19: =ROUND(($D$19/$E$3*T19)+($D$19/$H$2*U19),0) -> 0 | Y19: =ROUND(($D$19/$E$3*W19)+($D$19/$H$2*X19),0) -> 0 | Z19: 1 | AA19: 3.5 | AB19: =ROUND(($D$19/$E$3*Z19)+($D$19/$H$2*AA19),0) -> 626 | AC19: 1 | AD19: 3.5 | AE19: =ROUND(($D$19/$E$3*AC19)+($D$19/$H$2*AD19),0) -> 626 | AH19: =ROUND(($D$19/$E$3*AF19)+($D$19/$H$2*AG19),0) -> 0 | AK19: =ROUND(($D$19/$E$3*AI19)+($D$19/$H$2*AJ19),0) -> 0 | AN19: =ROUND(($D$19/$E$3*AL19)+($D$19/$H$2*AM19),0) -> 0 | AQ19: =ROUND(($D$19/$E$3*AO19)+($D$19/$H$2*AP19),0) -> 0 | AT19: =ROUND(($D$19/$E$3*AR19)+($D$19/$H$2*AS19),0) -> 0 | AW19: =ROUND(($D$19/$E$3*AU19)+($D$19/$H$2*AV19),0) -> 0 | AZ19: =ROUND(($D$19/$E$3*AX19)+($D$19/$H$2*AY19),0) -> 0 | BC19: =ROUND(($D$19/$E$3*BA19)+($D$19/$H$2*BB19),0) -> 0 | BF19: =ROUND(($D$19/$E$3*BD19)+($D$19/$H$2*BE19),0) -> 0 | BI19: =ROUND(($D$19/$E$3*BG19)+($D$19/$H$2*BH19),0) -> 0 | BL19: =ROUND(($D$19/$E$3*BJ19)+($D$19/$H$2*BK19),0) -> 0 | BO19: =ROUND(($D$19/$E$3*BM19)+($D$19/$H$2*BN19),0) -> 0 | BR19: =ROUND(($D$19/$E$3*BP19)+($D$19/$H$2*BQ19),0) -> 0 | BU19: =ROUND(($D$19/$E$3*BS19)+($D$19/$H$2*BT19),0) -> 0 | BX19: =ROUND(($D$19/$E$3*BV19)+($D$19/$H$2*BW19),0) -> 0 | CA19: =ROUND(($D$19/$E$3*BY19)+($D$19/$H$2*BZ19),0) -> 0 | CD19: =ROUND(($D$19/$E$3*CB19)+($D$19/$H$2*CC19),0) -> 0 | CG19: =ROUND(($D$19/$E$3*CE19)+($D$19/$H$2*CF19),0) -> 0 | CJ19: =ROUND(($D$19/$E$3*CH19)+($D$19/$H$2*CI19),0) -> 0 | CM19: =ROUND(($D$19/$E$3*CK19)+($D$19/$H$2*CL19),0) -> 0 | CP19: =ROUND(($D$19/$E$3*CN19)+($D$19/$H$2*CO19),0) -> 0 | CS19: =ROUND(($D$19/$E$3*CQ19)+($D$19/$H$2*CR19),0) -> 0 | CV19: =ROUND(($D$19/$E$3*CT19)+($D$19/$H$2*CU19),0) -> 0 | CY19: =ROUND(($D$19/$E$3*CW19)+($D$19/$H$2*CX19),0) -> 0
A20: 17 | E20: =K20+N20+Q20+T20+W20+Z20+AC20+AF20+AI20+AL20+AO20+AR20+AU20+AX20+BA20+BD20+BG20+BJ20+BM20+BP20+BS20+BV20+BY20+CB20+CE20+CH20+CK20+CN20+CQ20+CT20+CW20+CZ20 -> 0 | F20: =ROUND(D20/$F$2*E20,0) -> 0 | G20: =L20+O20+R20+U20+X20+AA20+AD20+AG20+AJ20+AM20+AP20+AS20+AV20+AY20+BB20+BE20+BH20+BK20+BN20+BQ20+BT20+BW20+BZ20+CC20+CF20+CI20+CL20+CO20+CR20+CU20+CX20+DA19 -> 0 | H20: =ROUND(D20/$H$2*G20,0) -> 0 | I20: =F20+H20 -> 0 | J20: =M20+P20+S20+V20+Y20+AB20+AE20+AH20+AK20+AN20+AQ20+AT20+AW20+AZ20+BC20+BF20+BI20+BL20+BO20+BR20+BU20+BX20+CA20+CD20+CG20+CJ20+CM20+CP20+CS20+CV20+CY20 -> 0 | M20: =ROUND(($D$20/$E$3*K20)+($D$20/$H$2*L20),0) -> 0 | P20: =ROUND(($D$20/$E$3*N20)+($D$20/$H$2*O20),0) -> 0 | S20: =ROUND(($D$20/$E$3*Q20)+($D$20/$H$2*R20),0) -> 0 | V20: =ROUND(($D$20/$E$3*T20)+($D$20/$H$2*U20),0) -> 0 | Y20: =ROUND(($D$20/$E$3*W20)+($D$20/$H$2*X20),0) -> 0 | AB20: =ROUND(($D$20/$E$3*Z20)+($D$20/$H$2*AA20),0) -> 0 | AE20: =ROUND(($D$20/$E$3*AC20)+($D$20/$H$2*AD20),0) -> 0 | AH20: =ROUND(($D$20/$E$3*AF20)+($D$20/$H$2*AG20),0) -> 0 | AK20: =ROUND(($D$20/$E$3*AI20)+($D$20/$H$2*AJ20),0) -> 0 | AN20: =ROUND(($D$20/$E$3*AL20)+($D$20/$H$2*AM20),0) -> 0 | AQ20: =ROUND(($D$20/$E$3*AO20)+($D$20/$H$2*AP20),0) -> 0 | AT20: =ROUND(($D$20/$E$3*AR20)+($D$20/$H$2*AS20),0) -> 0 | AW20: =ROUND(($D$20/$E$3*AU20)+($D$20/$H$2*AV20),0) -> 0 | AZ20: =ROUND(($D$20/$E$3*AX20)+($D$20/$H$2*AY20),0) -> 0 | BC20: =ROUND(($D$20/$E$3*BA20)+($D$20/$H$2*BB20),0) -> 0 | BF20: =ROUND(($D$20/$E$3*BD20)+($D$20/$H$2*BE20),0) -> 0 | BI20: =ROUND(($D$20/$E$3*BG20)+($D$20/$H$2*BH20),0) -> 0 | BL20: =ROUND(($D$20/$E$3*BJ20)+($D$20/$H$2*BK20),0) -> 0 | BO20: =ROUND(($D$20/$E$3*BM20)+($D$20/$H$2*BN20),0) -> 0 | BR20: =ROUND(($D$20/$E$3*BP20)+($D$20/$H$2*BQ20),0) -> 0 | BU20: =ROUND(($D$20/$E$3*BS20)+($D$20/$H$2*BT20),0) -> 0 | BX20: =ROUND(($D$20/$E$3*BV20)+($D$20/$H$2*BW20),0) -> 0 | CA20: =ROUND(($D$20/$E$3*BY20)+($D$20/$H$2*BZ20),0) -> 0 | CD20: =ROUND(($D$20/$E$3*CB20)+($D$20/$H$2*CC20),0) -> 0 | CG20: =ROUND(($D$20/$E$3*CE20)+($D$20/$H$2*CF20),0) -> 0 | CJ20: =ROUND(($D$20/$E$3*CH20)+($D$20/$H$2*CI20),0) -> 0 | CM20: =ROUND(($D$20/$E$3*CK20)+($D$20/$H$2*CL20),0) -> 0 | CP20: =ROUND(($D$20/$E$3*CN20)+($D$20/$H$2*CO20),0) -> 0 | CS20: =ROUND(($D$20/$E$3*CQ20)+($D$20/$H$2*CR20),0) -> 0 | CV20: =ROUND(($D$20/$E$3*CT20)+($D$20/$H$2*CU20),0) -> 0 | CY20: =ROUND(($D$20/$E$3*CW20)+($D$20/$H$2*CX20),0) -> 0
A21: 18 | E21: =K21+N21+Q21+T21+W21+Z21+AC21+AF21+AI21+AL21+AO21+AR21+AU21+AX21+BA21+BD21+BG21+BJ21+BM21+BP21+BS21+BV21+BY21+CB21+CE21+CH21+CK21+CN21+CQ21+CT21+CW21+CZ21 -> 0 | F21: =ROUND(D21/$F$2*E21,0) -> 0 | G21: =L21+O21+R21+U21+X21+AA21+AD21+AG21+AJ21+AM21+AP21+AS21+AV21+AY21+BB21+BE21+BH21+BK21+BN21+BQ21+BT21+BW21+BZ21+CC21+CF21+CI21+CL21+CO21+CR21+CU21+CX21+DA20 -> 0 | H21: =ROUND(D21/$H$2*G21,0) -> 0 | I21: =F21+H21 -> 0 | J21: =M21+P21+S21+V21+Y21+AB21+AE21+AH21+AK21+AN21+AQ21+AT21+AW21+AZ21+BC21+BF21+BI21+BL21+BO21+BR21+BU21+BX21+CA21+CD21+CG21+CJ21+CM21+CP21+CS21+CV21+CY21 -> 0 | M21: =ROUND(($D$21/$E$3*K21)+($D$21/$H$2*L21),0) -> 0 | P21: =ROUND(($D$21/$E$3*N21)+($D$21/$H$2*O21),0) -> 0 | S21: =ROUND(($D$21/$E$3*Q21)+($D$21/$H$2*R21),0) -> 0 | V21: =ROUND(($D$21/$E$3*T21)+($D$21/$H$2*U21),0) -> 0 | Y21: =ROUND(($D$21/$E$3*W21)+($D$21/$H$2*X21),0) -> 0 | AB21: =ROUND(($D$21/$E$3*Z21)+($D$21/$H$2*AA21),0) -> 0 | AE21: =ROUND(($D$21/$E$3*AC21)+($D$21/$H$2*AD21),0) -> 0 | AH21: =ROUND(($D$21/$E$3*AF21)+($D$21/$H$2*AG21),0) -> 0 | AK21: =ROUND(($D$21/$E$3*AI21)+($D$21/$H$2*AJ21),0) -> 0 | AN21: =ROUND(($D$21/$E$3*AL21)+($D$21/$H$2*AM21),0) -> 0 | AQ21: =ROUND(($D$21/$E$3*AO21)+($D$21/$H$2*AP21),0) -> 0 | AT21: =ROUND(($D$21/$E$3*AR21)+($D$21/$H$2*AS21),0) -> 0 | AW21: =ROUND(($D$21/$E$3*AU21)+($D$21/$H$2*AV21),0) -> 0 | AZ21: =ROUND(($D$21/$E$3*AX21)+($D$21/$H$2*AY21),0) -> 0 | BC21: =ROUND(($D$21/$E$3*BA21)+($D$21/$H$2*BB21),0) -> 0 | BF21: =ROUND(($D$21/$E$3*BD21)+($D$21/$H$2*BE21),0) -> 0 | BI21: =ROUND(($D$21/$E$3*BG21)+($D$21/$H$2*BH21),0) -> 0 | BL21: =ROUND(($D$21/$E$3*BJ21)+($D$21/$H$2*BK21),0) -> 0 | BO21: =ROUND(($D$21/$E$3*BM21)+($D$21/$H$2*BN21),0) -> 0 | BR21: =ROUND(($D$21/$E$3*BP21)+($D$21/$H$2*BQ21),0) -> 0 | BU21: =ROUND(($D$21/$E$3*BS21)+($D$21/$H$2*BT21),0) -> 0 | BX21: =ROUND(($D$21/$E$3*BV21)+($D$21/$H$2*BW21),0) -> 0 | CA21: =ROUND(($D$21/$E$3*BY21)+($D$21/$H$2*BZ21),0) -> 0 | CD21: =ROUND(($D$21/$E$3*CB21)+($D$21/$H$2*CC21),0) -> 0 | CG21: =ROUND(($D$21/$E$3*CE21)+($D$21/$H$2*CF21),0) -> 0 | CJ21: =ROUND(($D$21/$E$3*CH21)+($D$21/$H$2*CI21),0) -> 0 | CM21: =ROUND(($D$21/$E$3*CK21)+($D$21/$H$2*CL21),0) -> 0 | CP21: =ROUND(($D$21/$E$3*CN21)+($D$21/$H$2*CO21),0) -> 0 | CS21: =ROUND(($D$21/$E$3*CQ21)+($D$21/$H$2*CR21),0) -> 0 | CV21: =ROUND(($D$21/$E$3*CT21)+($D$21/$H$2*CU21),0) -> 0 | CY21: =ROUND(($D$21/$E$3*CW21)+($D$21/$H$2*CX21),0) -> 0
A22: 19 | E22: =K22+N22+Q22+T22+W22+Z22+AC22+AF22+AI22+AL22+AO22+AR22+AU22+AX22+BA22+BD22+BG22+BJ22+BM22+BP22+BS22+BV22+BY22+CB22+CE22+CH22+CK22+CN22+CQ22+CT22+CW22+CZ22 -> 0 | F22: =ROUND(D22/$F$2*E22,0) -> 0 | G22: =L22+O22+R22+U22+X22+AA22+AD22+AG22+AJ22+AM22+AP22+AS22+AV22+AY22+BB22+BE22+BH22+BK22+BN22+BQ22+BT22+BW22+BZ22+CC22+CF22+CI22+CL22+CO22+CR22+CU22+CX22+DA21 -> 0 | H22: =ROUND(D22/$H$2*G22,0) -> 0 | I22: =F22+H22 -> 0 | J22: =M22+P22+S22+V22+Y22+AB22+AE22+AH22+AK22+AN22+AQ22+AT22+AW22+AZ22+BC22+BF22+BI22+BL22+BO22+BR22+BU22+BX22+CA22+CD22+CG22+CJ22+CM22+CP22+CS22+CV22+CY22 -> 0 | M22: =ROUND(($D$22/$E$3*K22)+($D$22/$H$2*L22),0) -> 0 | P22: =ROUND(($D$22/$E$3*N22)+($D$22/$H$2*O22),0) -> 0 | S22: =ROUND(($D$22/$E$3*Q22)+($D$22/$H$2*R22),0) -> 0 | V22: =ROUND(($D$22/$E$3*T22)+($D$22/$H$2*U22),0) -> 0 | Y22: =ROUND(($D$22/$E$3*W22)+($D$22/$H$2*X22),0) -> 0 | AB22: =ROUND(($D$22/$E$3*Z22)+($D$22/$H$2*AA22),0) -> 0 | AE22: =ROUND(($D$22/$E$3*AC22)+($D$22/$H$2*AD22),0) -> 0 | AH22: =ROUND(($D$22/$E$3*AF22)+($D$22/$H$2*AG22),0) -> 0 | AK22: =ROUND(($D$22/$E$3*AI22)+($D$22/$H$2*AJ22),0) -> 0 | AN22: =ROUND(($D$22/$E$3*AL22)+($D$22/$H$2*AM22),0) -> 0 | AQ22: =ROUND(($D$22/$E$3*AO22)+($D$22/$H$2*AP22),0) -> 0 | AT22: =ROUND(($D$22/$E$3*AR22)+($D$22/$H$2*AS22),0) -> 0 | AW22: =ROUND(($D$22/$E$3*AU22)+($D$22/$H$2*AV22),0) -> 0 | AZ22: =ROUND(($D$22/$E$3*AX22)+($D$22/$H$2*AY22),0) -> 0 | BC22: =ROUND(($D$22/$E$3*BA22)+($D$22/$H$2*BB22),0) -> 0 | BF22: =ROUND(($D$22/$E$3*BD22)+($D$22/$H$2*BE22),0) -> 0 | BI22: =ROUND(($D$22/$E$3*BG22)+($D$22/$H$2*BH22),0) -> 0 | BL22: =ROUND(($D$22/$E$3*BJ22)+($D$22/$H$2*BK22),0) -> 0 | BO22: =ROUND(($D$22/$E$3*BM22)+($D$22/$H$2*BN22),0) -> 0 | BR22: =ROUND(($D$22/$E$3*BP22)+($D$22/$H$2*BQ22),0) -> 0 | BU22: =ROUND(($D$22/$E$3*BS22)+($D$22/$H$2*BT22),0) -> 0 | BX22: =ROUND(($D$22/$E$3*BV22)+($D$22/$H$2*BW22),0) -> 0 | CA22: =ROUND(($D$22/$E$3*BY22)+($D$22/$H$2*BZ22),0) -> 0 | CD22: =ROUND(($D$22/$E$3*CB22)+($D$22/$H$2*CC22),0) -> 0 | CG22: =ROUND(($D$22/$E$3*CE22)+($D$22/$H$2*CF22),0) -> 0 | CJ22: =ROUND(($D$22/$E$3*CH22)+($D$22/$H$2*CI22),0) -> 0 | CM22: =ROUND(($D$22/$E$3*CK22)+($D$22/$H$2*CL22),0) -> 0 | CP22: =ROUND(($D$22/$E$3*CN22)+($D$22/$H$2*CO22),0) -> 0 | CS22: =ROUND(($D$22/$E$3*CQ22)+($D$22/$H$2*CR22),0) -> 0 | CV22: =ROUND(($D$22/$E$3*CT22)+($D$22/$H$2*CU22),0) -> 0 | CY22: =ROUND(($D$22/$E$3*CW22)+($D$22/$H$2*CX22),0) -> 0
A23: 20 | E23: =K23+N23+Q23+T23+W23+Z23+AC23+AF23+AI23+AL23+AO23+AR23+AU23+AX23+BA23+BD23+BG23+BJ23+BM23+BP23+BS23+BV23+BY23+CB23+CE23+CH23+CK23+CN23+CQ23+CT23+CW23+CZ23 -> 0 | F23: =ROUND(D23/$F$2*E23,0) -> 0 | G23: =L23+O23+R23+U23+X23+AA23+AD23+AG23+AJ23+AM23+AP23+AS23+AV23+AY23+BB23+BE23+BH23+BK23+BN23+BQ23+BT23+BW23+BZ23+CC23+CF23+CI23+CL23+CO23+CR23+CU23+CX23+DA22 -> 0 | H23: =ROUND(D23/$H$2*G23,0) -> 0 | I23: =F23+H23 -> 0 | J23: =M23+P23+S23+V23+Y23+AB23+AE23+AH23+AK23+AN23+AQ23+AT23+AW23+AZ23+BC23+BF23+BI23+BL23+BO23+BR23+BU23+BX23+CA23+CD23+CG23+CJ23+CM23+CP23+CS23+CV23+CY23 -> 0 | M23: =ROUND(($D$23/$E$3*K23)+($D$23/$H$2*L23),0) -> 0 | P23: =ROUND(($D$23/$E$3*N23)+($D$23/$H$2*O23),0) -> 0 | S23: =ROUND(($D$23/$E$3*Q23)+($D$23/$H$2*R23),0) -> 0 | V23: =ROUND(($D$23/$E$3*T23)+($D$23/$H$2*U23),0) -> 0 | Y23: =ROUND(($D$23/$E$3*W23)+($D$23/$H$2*X23),0) -> 0 | AB23: =ROUND(($D$23/$E$3*Z23)+($D$23/$H$2*AA23),0) -> 0 | AE23: =ROUND(($D$23/$E$3*AC23)+($D$23/$H$2*AD23),0) -> 0 | AH23: =ROUND(($D$23/$E$3*AF23)+($D$23/$H$2*AG23),0) -> 0 | AK23: =ROUND(($D$23/$E$3*AI23)+($D$23/$H$2*AJ23),0) -> 0 | AN23: =ROUND(($D$23/$E$3*AL23)+($D$23/$H$2*AM23),0) -> 0 | AQ23: =ROUND(($D$23/$E$3*AO23)+($D$23/$H$2*AP23),0) -> 0 | AT23: =ROUND(($D$23/$E$3*AR23)+($D$23/$H$2*AS23),0) -> 0 | AW23: =ROUND(($D$23/$E$3*AU23)+($D$23/$H$2*AV23),0) -> 0 | AZ23: =ROUND(($D$23/$E$3*AX23)+($D$23/$H$2*AY23),0) -> 0 | BC23: =ROUND(($D$23/$E$3*BA23)+($D$23/$H$2*BB23),0) -> 0 | BF23: =ROUND(($D$23/$E$3*BD23)+($D$23/$H$2*BE23),0) -> 0 | BI23: =ROUND(($D$23/$E$3*BG23)+($D$23/$H$2*BH23),0) -> 0 | BL23: =ROUND(($D$23/$E$3*BJ23)+($D$23/$H$2*BK23),0) -> 0 | BO23: =ROUND(($D$23/$E$3*BM23)+($D$23/$H$2*BN23),0) -> 0 | BR23: =ROUND(($D$23/$E$3*BP23)+($D$23/$H$2*BQ23),0) -> 0 | BU23: =ROUND(($D$23/$E$3*BS23)+($D$23/$H$2*BT23),0) -> 0 | BX23: =ROUND(($D$23/$E$3*BV23)+($D$23/$H$2*BW23),0) -> 0 | CA23: =ROUND(($D$23/$E$3*BY23)+($D$23/$H$2*BZ23),0) -> 0 | CD23: =ROUND(($D$23/$E$3*CB23)+($D$23/$H$2*CC23),0) -> 0 | CG23: =ROUND(($D$23/$E$3*CE23)+($D$23/$H$2*CF23),0) -> 0 | CJ23: =ROUND(($D$23/$E$3*CH23)+($D$23/$H$2*CI23),0) -> 0 | CM23: =ROUND(($D$23/$E$3*CK23)+($D$23/$H$2*CL23),0) -> 0 | CP23: =ROUND(($D$23/$E$3*CN23)+($D$23/$H$2*CO23),0) -> 0 | CS23: =ROUND(($D$23/$E$3*CQ23)+($D$23/$H$2*CR23),0) -> 0 | CV23: =ROUND(($D$23/$E$3*CT23)+($D$23/$H$2*CU23),0) -> 0 | CY23: =ROUND(($D$23/$E$3*CW23)+($D$23/$H$2*CX23),0) -> 0
A24: 21 | E24: =K24+N24+Q24+T24+W24+Z24+AC24+AF24+AI24+AL24+AO24+AR24+AU24+AX24+BA24+BD24+BG24+BJ24+BM24+BP24+BS24+BV24+BY24+CB24+CE24+CH24+CK24+CN24+CQ24+CT24+CW24+CZ24 -> 0 | F24: =ROUND(D24/$F$2*E24,0) -> 0 | G24: =L24+O24+R24+U24+X24+AA24+AD24+AG24+AJ24+AM24+AP24+AS24+AV24+AY24+BB24+BE24+BH24+BK24+BN24+BQ24+BT24+BW24+BZ24+CC24+CF24+CI24+CL24+CO24+CR24+CU24+CX24+DA23 -> 0 | H24: =ROUND(D24/$H$2*G24,0) -> 0 | I24: =F24+H24 -> 0 | J24: =M24+P24+S24+V24+Y24+AB24+AE24+AH24+AK24+AN24+AQ24+AT24+AW24+AZ24+BC24+BF24+BI24+BL24+BO24+BR24+BU24+BX24+CA24+CD24+CG24+CJ24+CM24+CP24+CS24+CV24+CY24 -> 0 | M24: =ROUND(($D$24/$E$3*K24)+($D$24/$H$2*L24),0) -> 0 | P24: =ROUND(($D$24/$E$3*N24)+($D$24/$H$2*O24),0) -> 0 | S24: =ROUND(($D$24/$E$3*Q24)+($D$24/$H$2*R24),0) -> 0 | V24: =ROUND(($D$24/$E$3*T24)+($D$24/$H$2*U24),0) -> 0 | Y24: =ROUND(($D$24/$E$3*W24)+($D$24/$H$2*X24),0) -> 0 | AB24: =ROUND(($D$24/$E$3*Z24)+($D$24/$H$2*AA24),0) -> 0 | AE24: =ROUND(($D$24/$E$3*AC24)+($D$24/$H$2*AD24),0) -> 0 | AH24: =ROUND(($D$24/$E$3*AF24)+($D$24/$H$2*AG24),0) -> 0 | AK24: =ROUND(($D$24/$E$3*AI24)+($D$24/$H$2*AJ24),0) -> 0 | AN24: =ROUND(($D$24/$E$3*AL24)+($D$24/$H$2*AM24),0) -> 0 | AQ24: =ROUND(($D$24/$E$3*AO24)+($D$24/$H$2*AP24),0) -> 0 | AT24: =ROUND(($D$24/$E$3*AR24)+($D$24/$H$2*AS24),0) -> 0 | AW24: =ROUND(($D$24/$E$3*AU24)+($D$24/$H$2*AV24),0) -> 0 | AZ24: =ROUND(($D$24/$E$3*AX24)+($D$24/$H$2*AY24),0) -> 0 | BC24: =ROUND(($D$24/$E$3*BA24)+($D$24/$H$2*BB24),0) -> 0 | BF24: =ROUND(($D$24/$E$3*BD24)+($D$24/$H$2*BE24),0) -> 0 | BI24: =ROUND(($D$24/$E$3*BG24)+($D$24/$H$2*BH24),0) -> 0 | BL24: =ROUND(($D$24/$E$3*BJ24)+($D$24/$H$2*BK24),0) -> 0 | BO24: =ROUND(($D$24/$E$3*BM24)+($D$24/$H$2*BN24),0) -> 0 | BR24: =ROUND(($D$24/$E$3*BP24)+($D$24/$H$2*BQ24),0) -> 0 | BU24: =ROUND(($D$24/$E$3*BS24)+($D$24/$H$2*BT24),0) -> 0 | BX24: =ROUND(($D$24/$E$3*BV24)+($D$24/$H$2*BW24),0) -> 0 | CA24: =ROUND(($D$24/$E$3*BY24)+($D$24/$H$2*BZ24),0) -> 0 | CD24: =ROUND(($D$24/$E$3*CB24)+($D$24/$H$2*CC24),0) -> 0 | CG24: =ROUND(($D$24/$E$3*CE24)+($D$24/$H$2*CF24),0) -> 0 | CJ24: =ROUND(($D$24/$E$3*CH24)+($D$24/$H$2*CI24),0) -> 0 | CM24: =ROUND(($D$24/$E$3*CK24)+($D$24/$H$2*CL24),0) -> 0 | CP24: =ROUND(($D$24/$E$3*CN24)+($D$24/$H$2*CO24),0) -> 0 | CS24: =ROUND(($D$24/$E$3*CQ24)+($D$24/$H$2*CR24),0) -> 0 | CV24: =ROUND(($D$24/$E$3*CT24)+($D$24/$H$2*CU24),0) -> 0 | CY24: =ROUND(($D$24/$E$3*CW24)+($D$24/$H$2*CX24),0) -> 0
A25: 22 | E25: =K25+N25+Q25+T25+W25+Z25+AC25+AF25+AI25+AL25+AO25+AR25+AU25+AX25+BA25+BD25+BG25+BJ25+BM25+BP25+BS25+BV25+BY25+CB25+CE25+CH25+CK25+CN25+CQ25+CT25+CW25+CZ25 -> 0 | F25: =ROUND(D25/$F$2*E25,0) -> 0 | G25: =L25+O25+R25+U25+X25+AA25+AD25+AG25+AJ25+AM25+AP25+AS25+AV25+AY25+BB25+BE25+BH25+BK25+BN25+BQ25+BT25+BW25+BZ25+CC25+CF25+CI25+CL25+CO25+CR25+CU25+CX25+DA24 -> 0 | H25: =ROUND(D25/$H$2*G25,0) -> 0 | I25: =F25+H25 -> 0 | J25: =M25+P25+S25+V25+Y25+AB25+AE25+AH25+AK25+AN25+AQ25+AT25+AW25+AZ25+BC25+BF25+BI25+BL25+BO25+BR25+BU25+BX25+CA25+CD25+CG25+CJ25+CM25+CP25+CS25+CV25+CY25 -> 0 | M25: =ROUND(($D$25/$E$3*K25)+($D$25/$H$2*L25),0) -> 0 | P25: =ROUND(($D$25/$E$3*N25)+($D$25/$H$2*O25),0) -> 0 | S25: =ROUND(($D$25/$E$3*Q25)+($D$25/$H$2*R25),0) -> 0 | V25: =ROUND(($D$25/$E$3*T25)+($D$25/$H$2*U25),0) -> 0 | Y25: =ROUND(($D$25/$E$3*W25)+($D$25/$H$2*X25),0) -> 0 | AB25: =ROUND(($D$25/$E$3*Z25)+($D$25/$H$2*AA25),0) -> 0 | AE25: =ROUND(($D$25/$E$3*AC25)+($D$25/$H$2*AD25),0) -> 0 | AH25: =ROUND(($D$25/$E$3*AF25)+($D$25/$H$2*AG25),0) -> 0 | AK25: =ROUND(($D$25/$E$3*AI25)+($D$25/$H$2*AJ25),0) -> 0 | AN25: =ROUND(($D$25/$E$3*AL25)+($D$25/$H$2*AM25),0) -> 0 | AQ25: =ROUND(($D$25/$E$3*AO25)+($D$25/$H$2*AP25),0) -> 0 | AT25: =ROUND(($D$25/$E$3*AR25)+($D$25/$H$2*AS25),0) -> 0 | AW25: =ROUND(($D$25/$E$3*AU25)+($D$25/$H$2*AV25),0) -> 0 | AZ25: =ROUND(($D$25/$E$3*AX25)+($D$25/$H$2*AY25),0) -> 0 | BC25: =ROUND(($D$25/$E$3*BA25)+($D$25/$H$2*BB25),0) -> 0 | BF25: =ROUND(($D$25/$E$3*BD25)+($D$25/$H$2*BE25),0) -> 0 | BI25: =ROUND(($D$25/$E$3*BG25)+($D$25/$H$2*BH25),0) -> 0 | BL25: =ROUND(($D$25/$E$3*BJ25)+($D$25/$H$2*BK25),0) -> 0 | BO25: =ROUND(($D$25/$E$3*BM25)+($D$25/$H$2*BN25),0) -> 0 | BR25: =ROUND(($D$25/$E$3*BP25)+($D$25/$H$2*BQ25),0) -> 0 | BU25: =ROUND(($D$25/$E$3*BS25)+($D$25/$H$2*BT25),0) -> 0 | BX25: =ROUND(($D$25/$E$3*BV25)+($D$25/$H$2*BW25),0) -> 0 | CA25: =ROUND(($D$25/$E$3*BY25)+($D$25/$H$2*BZ25),0) -> 0 | CD25: =ROUND(($D$25/$E$3*CB25)+($D$25/$H$2*CC25),0) -> 0 | CG25: =ROUND(($D$25/$E$3*CE25)+($D$25/$H$2*CF25),0) -> 0 | CJ25: =ROUND(($D$25/$E$3*CH25)+($D$25/$H$2*CI25),0) -> 0 | CM25: =ROUND(($D$25/$E$3*CK25)+($D$25/$H$2*CL25),0) -> 0 | CP25: =ROUND(($D$25/$E$3*CN25)+($D$25/$H$2*CO25),0) -> 0 | CS25: =ROUND(($D$25/$E$3*CQ25)+($D$25/$H$2*CR25),0) -> 0 | CV25: =ROUND(($D$25/$E$3*CT25)+($D$25/$H$2*CU25),0) -> 0 | CY25: =ROUND(($D$25/$E$3*CW25)+($D$25/$H$2*CX25),0) -> 0
A26: 23 | E26: =K26+N26+Q26+T26+W26+Z26+AC26+AF26+AI26+AL26+AO26+AR26+AU26+AX26+BA26+BD26+BG26+BJ26+BM26+BP26+BS26+BV26+BY26+CB26+CE26+CH26+CK26+CN26+CQ26+CT26+CW26+CZ26 -> 0 | F26: =ROUND(D26/$F$2*E26,0) -> 0 | G26: =L26+O26+R26+U26+X26+AA26+AD26+AG26+AJ26+AM26+AP26+AS26+AV26+AY26+BB26+BE26+BH26+BK26+BN26+BQ26+BT26+BW26+BZ26+CC26+CF26+CI26+CL26+CO26+CR26+CU26+CX26+DA25 -> 0 | H26: =ROUND(D26/$H$2*G26,0) -> 0 | I26: =F26+H26 -> 0 | J26: =M26+P26+S26+V26+Y26+AB26+AE26+AH26+AK26+AN26+AQ26+AT26+AW26+AZ26+BC26+BF26+BI26+BL26+BO26+BR26+BU26+BX26+CA26+CD26+CG26+CJ26+CM26+CP26+CS26+CV26+CY26 -> 0 | M26: =ROUND(($D$26/$E$3*K26)+($D$26/$H$2*L26),0) -> 0 | P26: =ROUND(($D$26/$E$3*N26)+($D$26/$H$2*O26),0) -> 0 | S26: =ROUND(($D$26/$E$3*Q26)+($D$26/$H$2*R26),0) -> 0 | V26: =ROUND(($D$26/$E$3*T26)+($D$26/$H$2*U26),0) -> 0 | Y26: =ROUND(($D$26/$E$3*W26)+($D$26/$H$2*X26),0) -> 0 | AB26: =ROUND(($D$25/$E$3*Z26)+($D$25/$H$2*AA26),0) -> 0 | AE26: =ROUND(($D$26/$E$3*AC26)+($D$26/$H$2*AD26),0) -> 0 | AH26: =ROUND(($D$26/$E$3*AF26)+($D$26/$H$2*AG26),0) -> 0 | AK26: =ROUND(($D$26/$E$3*AI26)+($D$26/$H$2*AJ26),0) -> 0 | AN26: =ROUND(($D$26/$E$3*AL26)+($D$26/$H$2*AM26),0) -> 0 | AQ26: =ROUND(($D$26/$E$3*AO26)+($D$26/$H$2*AP26),0) -> 0 | AT26: =ROUND(($D$26/$E$3*AR26)+($D$26/$H$2*AS26),0) -> 0 | AW26: =ROUND(($D$26/$E$3*AU26)+($D$26/$H$2*AV26),0) -> 0 | AZ26: =ROUND(($D$26/$E$3*AX26)+($D$26/$H$2*AY26),0) -> 0 | BC26: =ROUND(($D$26/$E$3*BA26)+($D$26/$H$2*BB26),0) -> 0 | BF26: =ROUND(($D$26/$E$3*BD26)+($D$26/$H$2*BE26),0) -> 0 | BI26: =ROUND(($D$26/$E$3*BG26)+($D$26/$H$2*BH26),0) -> 0 | BL26: =ROUND(($D$26/$E$3*BJ26)+($D$26/$H$2*BK26),0) -> 0 | BO26: =ROUND(($D$26/$E$3*BM26)+($D$26/$H$2*BN26),0) -> 0 | BR26: =ROUND(($D$26/$E$3*BP26)+($D$26/$H$2*BQ26),0) -> 0 | BU26: =ROUND(($D$26/$E$3*BS26)+($D$26/$H$2*BT26),0) -> 0 | BX26: =ROUND(($D$26/$E$3*BV26)+($D$26/$H$2*BW26),0) -> 0 | CA26: =ROUND(($D$26/$E$3*BY26)+($D$26/$H$2*BZ26),0) -> 0 | CD26: =ROUND(($D$26/$E$3*CB26)+($D$26/$H$2*CC26),0) -> 0 | CG26: =ROUND(($D$26/$E$3*CE26)+($D$26/$H$2*CF26),0) -> 0 | CJ26: =ROUND(($D$26/$E$3*CH26)+($D$26/$H$2*CI26),0) -> 0 | CM26: =ROUND(($D$26/$E$3*CK26)+($D$26/$H$2*CL26),0) -> 0 | CP26: =ROUND(($D$26/$E$3*CN26)+($D$26/$H$2*CO26),0) -> 0 | CS26: =ROUND(($D$26/$E$3*CQ26)+($D$26/$H$2*CR26),0) -> 0 | CV26: =ROUND(($D$26/$E$3*CT26)+($D$26/$H$2*CU26),0) -> 0 | CY26: =ROUND(($D$26/$E$3*CW26)+($D$26/$H$2*CX26),0) -> 0
A27: 24 | E27: =K27+N27+Q27+T27+W27+Z27+AC27+AF27+AI27+AL27+AO27+AR27+AU27+AX27+BA27+BD27+BG27+BJ27+BM27+BP27+BS27+BV27+BY27+CB27+CE27+CH27+CK27+CN27+CQ27+CT27+CW27+CZ27 -> 0 | F27: =ROUND(D27/$F$2*E27,0) -> 0 | G27: =L27+O27+R27+U27+X27+AA27+AD27+AG27+AJ27+AM27+AP27+AS27+AV27+AY27+BB27+BE27+BH27+BK27+BN27+BQ27+BT27+BW27+BZ27+CC27+CF27+CI27+CL27+CO27+CR27+CU27+CX27+DA26 -> 0 | H27: =ROUND(D27/$H$2*G27,0) -> 0 | I27: =F27+H27 -> 0 | J27: =M27+P27+S27+V27+Y27+AB27+AE27+AH27+AK27+AN27+AQ27+AT27+AW27+AZ27+BC27+BF27+BI27+BL27+BO27+BR27+BU27+BX27+CA27+CD27+CG27+CJ27+CM27+CP27+CS27+CV27+CY27 -> 0 | M27: =ROUND(($D$27/$E$3*K27)+($D$27/$H$2*L27),0) -> 0 | P27: =ROUND(($D$27/$E$3*N27)+($D$27/$H$2*O27),0) -> 0 | S27: =ROUND(($D$27/$E$3*Q27)+($D$27/$H$2*R27),0) -> 0 | V27: =ROUND(($D$27/$E$3*T27)+($D$27/$H$2*U27),0) -> 0 | Y27: =ROUND(($D$27/$E$3*W27)+($D$27/$H$2*X27),0) -> 0 | AB27: =ROUND(($D$27/$E$3*Z27)+($D$27/$H$2*AA27),0) -> 0 | AE27: =ROUND(($D$27/$E$3*AC27)+($D$27/$H$2*AD27),0) -> 0 | AH27: =ROUND(($D$27/$E$3*AF27)+($D$27/$H$2*AG27),0) -> 0 | AK27: =ROUND(($D$27/$E$3*AI27)+($D$27/$H$2*AJ27),0) -> 0 | AN27: =ROUND(($D$27/$E$3*AL27)+($D$27/$H$2*AM27),0) -> 0 | AQ27: =ROUND(($D$27/$E$3*AO27)+($D$27/$H$2*AP27),0) -> 0 | AT27: =ROUND(($D$27/$E$3*AR27)+($D$27/$H$2*AS27),0) -> 0 | AW27: =ROUND(($D$27/$E$3*AU27)+($D$27/$H$2*AV27),0) -> 0 | AZ27: =ROUND(($D$27/$E$3*AX27)+($D$27/$H$2*AY27),0) -> 0 | BC27: =ROUND(($D$27/$E$3*BA27)+($D$27/$H$2*BB27),0) -> 0 | BF27: =ROUND(($D$27/$E$3*BD27)+($D$27/$H$2*BE27),0) -> 0 | BI27: =ROUND(($D$27/$E$3*BG27)+($D$27/$H$2*BH27),0) -> 0 | BL27: =ROUND(($D$27/$E$3*BJ27)+($D$27/$H$2*BK27),0) -> 0 | BO27: =ROUND(($D$27/$E$3*BM27)+($D$27/$H$2*BN27),0) -> 0 | BR27: =ROUND(($D$27/$E$3*BP27)+($D$27/$H$2*BQ27),0) -> 0 | BU27: =ROUND(($D$27/$E$3*BS27)+($D$27/$H$2*BT27),0) -> 0 | BX27: =ROUND(($D$27/$E$3*BV27)+($D$27/$H$2*BW27),0) -> 0 | CA27: =ROUND(($D$27/$E$3*BY27)+($D$27/$H$2*BZ27),0) -> 0 | CD27: =ROUND(($D$27/$E$3*CB27)+($D$27/$H$2*CC27),0) -> 0 | CG27: =ROUND(($D$27/$E$3*CE27)+($D$27/$H$2*CF27),0) -> 0 | CJ27: =ROUND(($D$27/$E$3*CH27)+($D$27/$H$2*CI27),0) -> 0 | CM27: =ROUND(($D$27/$E$3*CK27)+($D$27/$H$2*CL27),0) -> 0 | CP27: =ROUND(($D$27/$E$3*CN27)+($D$27/$H$2*CO27),0) -> 0 | CS27: =ROUND(($D$27/$E$3*CQ27)+($D$27/$H$2*CR27),0) -> 0 | CV27: =ROUND(($D$27/$E$3*CT27)+($D$27/$H$2*CU27),0) -> 0 | CY27: =ROUND(($D$27/$E$3*CW27)+($D$27/$H$2*CX27),0) -> 0
A28: 25 | E28: =K28+N28+Q28+T28+W28+Z28+AC28+AF28+AI28+AL28+AO28+AR28+AU28+AX28+BA28+BD28+BG28+BJ28+BM28+BP28+BS28+BV28+BY28+CB28+CE28+CH28+CK28+CN28+CQ28+CT28+CW28+CZ28 -> 0 | F28: =ROUND(D28/$F$2*E28,0) -> 0 | G28: =L28+O28+R28+U28+X28+AA28+AD28+AG28+AJ28+AM28+AP28+AS28+AV28+AY28+BB28+BE28+BH28+BK28+BN28+BQ28+BT28+BW28+BZ28+CC28+CF28+CI28+CL28+CO28+CR28+CU28+CX28+DA27 -> 0 | H28: =ROUND(D28/$H$2*G28,0) -> 0 | I28: =F28+H28 -> 0 | J28: =M28+P28+S28+V28+Y28+AB28+AE28+AH28+AK28+AN28+AQ28+AT28+AW28+AZ28+BC28+BF28+BI28+BL28+BO28+BR28+BU28+BX28+CA28+CD28+CG28+CJ28+CM28+CP28+CS28+CV28+CY28 -> 0 | M28: =ROUND(($D$28/$E$3*K28)+($D$28/$H$2*L28),0) -> 0 | P28: =ROUND(($D$28/$E$3*N28)+($D$28/$H$2*O28),0) -> 0 | S28: =ROUND(($D$28/$E$3*Q28)+($D$28/$H$2*R28),0) -> 0 | V28: =ROUND(($D$28/$E$3*T28)+($D$28/$H$2*U28),0) -> 0 | Y28: =ROUND(($D$28/$E$3*W28)+($D$28/$H$2*X28),0) -> 0 | AB28: =ROUND(($D$28/$E$3*Z28)+($D$28/$H$2*AA28),0) -> 0 | AE28: =ROUND(($D$28/$E$3*AC28)+($D$28/$H$2*AD28),0) -> 0 | AH28: =ROUND(($D$28/$E$3*AF28)+($D$28/$H$2*AG28),0) -> 0 | AK28: =ROUND(($D$28/$E$3*AI28)+($D$28/$H$2*AJ28),0) -> 0 | AN28: =ROUND(($D$28/$E$3*AL28)+($D$28/$H$2*AM28),0) -> 0 | AQ28: =ROUND(($D$28/$E$3*AO28)+($D$28/$H$2*AP28),0) -> 0 | AT28: =ROUND(($D$28/$E$3*AR28)+($D$28/$H$2*AS28),0) -> 0 | AW28: =ROUND(($D$28/$E$3*AU28)+($D$28/$H$2*AV28),0) -> 0 | AZ28: =ROUND(($D$28/$E$3*AX28)+($D$28/$H$2*AY28),0) -> 0 | BC28: =ROUND(($D$28/$E$3*BA28)+($D$28/$H$2*BB28),0) -> 0 | BF28: =ROUND(($D$28/$E$3*BD28)+($D$28/$H$2*BE28),0) -> 0 | BI28: =ROUND(($D$28/$E$3*BG28)+($D$28/$H$2*BH28),0) -> 0 | BL28: =ROUND(($D$28/$E$3*BJ28)+($D$28/$H$2*BK28),0) -> 0 | BO28: =ROUND(($D$28/$E$3*BM28)+($D$28/$H$2*BN28),0) -> 0 | BR28: =ROUND(($D$28/$E$3*BP28)+($D$28/$H$2*BQ28),0) -> 0 | BU28: =ROUND(($D$28/$E$3*BS28)+($D$28/$H$2*BT28),0) -> 0 | BX28: =ROUND(($D$28/$E$3*BV28)+($D$28/$H$2*BW28),0) -> 0 | CA28: =ROUND(($D$28/$E$3*BY28)+($D$28/$H$2*BZ28),0) -> 0 | CD28: =ROUND(($D$28/$E$3*CB28)+($D$28/$H$2*CC28),0) -> 0 | CG28: =ROUND(($D$28/$E$3*CE28)+($D$28/$H$2*CF28),0) -> 0 | CJ28: =ROUND(($D$28/$E$3*CH28)+($D$28/$H$2*CI28),0) -> 0 | CM28: =ROUND(($D$28/$E$3*CK28)+($D$28/$H$2*CL28),0) -> 0 | CP28: =ROUND(($D$28/$E$3*CN28)+($D$28/$H$2*CO28),0) -> 0 | CS28: =ROUND(($D$28/$E$3*CQ28)+($D$28/$H$2*CR28),0) -> 0 | CV28: =ROUND(($D$28/$E$3*CT28)+($D$28/$H$2*CU28),0) -> 0 | CY28: =ROUND(($D$28/$E$3*CW28)+($D$28/$H$2*CX28),0) -> 0
A29: 26 | E29: =K29+N29+Q29+T29+W29+Z29+AC29+AF29+AI29+AL29+AO29+AR29+AU29+AX29+BA29+BD29+BG29+BJ29+BM29+BP29+BS29+BV29+BY29+CB29+CE29+CH29+CK29+CN29+CQ29+CT29+CW29+CZ29 -> 0 | F29: =ROUND(D29/$F$2*E29,0) -> 0 | G29: =L29+O29+R29+U29+X29+AA29+AD29+AG29+AJ29+AM29+AP29+AS29+AV29+AY29+BB29+BE29+BH29+BK29+BN29+BQ29+BT29+BW29+BZ29+CC29+CF29+CI29+CL29+CO29+CR29+CU29+CX29+DA28 -> 0 | H29: =ROUND(D29/$H$2*G29,0) -> 0 | I29: =F29+H29 -> 0 | J29: =M29+P29+S29+V29+Y29+AB29+AE29+AH29+AK29+AN29+AQ29+AT29+AW29+AZ29+BC29+BF29+BI29+BL29+BO29+BR29+BU29+BX29+CA29+CD29+CG29+CJ29+CM29+CP29+CS29+CV29+CY29 -> 0 | M29: =ROUND(($D$29/$E$3*K29)+($D$29/$H$2*L29),0) -> 0 | P29: =ROUND(($D$29/$E$3*N29)+($D$29/$H$2*O29),0) -> 0 | S29: =ROUND(($D$29/$E$3*Q29)+($D$29/$H$2*R29),0) -> 0 | V29: =ROUND(($D$29/$E$3*T29)+($D$29/$H$2*U29),0) -> 0 | Y29: =ROUND(($D$29/$E$3*W29)+($D$29/$H$2*X29),0) -> 0 | AB29: =ROUND(($D$29/$E$3*Z29)+($D$29/$H$2*AA29),0) -> 0 | AE29: =ROUND(($D$29/$E$3*AC29)+($D$29/$H$2*AD29),0) -> 0 | AH29: =ROUND(($D$29/$E$3*AF29)+($D$29/$H$2*AG29),0) -> 0 | AK29: =ROUND(($D$29/$E$3*AI29)+($D$29/$H$2*AJ29),0) -> 0 | AN29: =ROUND(($D$29/$E$3*AL29)+($D$29/$H$2*AM29),0) -> 0 | AQ29: =ROUND(($D$29/$E$3*AO29)+($D$29/$H$2*AP29),0) -> 0 | AT29: =ROUND(($D$29/$E$3*AR29)+($D$29/$H$2*AS29),0) -> 0 | AW29: =ROUND(($D$29/$E$3*AU29)+($D$29/$H$2*AV29),0) -> 0 | AZ29: =ROUND(($D$29/$E$3*AX29)+($D$29/$H$2*AY29),0) -> 0 | BC29: =ROUND(($D$29/$E$3*BA29)+($D$29/$H$2*BB29),0) -> 0 | BF29: =ROUND(($D$29/$E$3*BD29)+($D$29/$H$2*BE29),0) -> 0 | BI29: =ROUND(($D$29/$E$3*BG29)+($D$29/$H$2*BH29),0) -> 0 | BL29: =ROUND(($D$29/$E$3*BJ29)+($D$29/$H$2*BK29),0) -> 0 | BO29: =ROUND(($D$29/$E$3*BM29)+($D$29/$H$2*BN29),0) -> 0 | BR29: =ROUND(($D$29/$E$3*BP29)+($D$29/$H$2*BQ29),0) -> 0 | BU29: =ROUND(($D$29/$E$3*BS29)+($D$29/$H$2*BT29),0) -> 0 | BX29: =ROUND(($D$29/$E$3*BV29)+($D$29/$H$2*BW29),0) -> 0 | CA29: =ROUND(($D$29/$E$3*BY29)+($D$29/$H$2*BZ29),0) -> 0 | CD29: =ROUND(($D$29/$E$3*CB29)+($D$29/$H$2*CC29),0) -> 0 | CG29: =ROUND(($D$29/$E$3*CE29)+($D$29/$H$2*CF29),0) -> 0 | CJ29: =ROUND(($D$29/$E$3*CH29)+($D$29/$H$2*CI29),0) -> 0 | CM29: =ROUND(($D$29/$E$3*CK29)+($D$29/$H$2*CL29),0) -> 0 | CP29: =ROUND(($D$29/$E$3*CN29)+($D$29/$H$2*CO29),0) -> 0 | CS29: =ROUND(($D$29/$E$3*CQ29)+($D$29/$H$2*CR29),0) -> 0 | CV29: =ROUND(($D$29/$E$3*CT29)+($D$29/$H$2*CU29),0) -> 0 | CY29: =ROUND(($D$29/$E$3*CW29)+($D$29/$H$2*CX29),0) -> 0
A30: 27 | E30: =K30+N30+Q30+T30+W30+Z30+AC30+AF30+AI30+AL30+AO30+AR30+AU30+AX30+BA30+BD30+BG30+BJ30+BM30+BP30+BS30+BV30+BY30+CB30+CE30+CH30+CK30+CN30+CQ30+CT30+CW30+CZ30 -> 0 | F30: =ROUND(D30/$F$2*E30,0) -> 0 | G30: =L30+O30+R30+U30+X30+AA30+AD30+AG30+AJ30+AM30+AP30+AS30+AV30+AY30+BB30+BE30+BH30+BK30+BN30+BQ30+BT30+BW30+BZ30+CC30+CF30+CI30+CL30+CO30+CR30+CU30+CX30+DA29 -> 0 | H30: =ROUND(D30/$H$2*G30,0) -> 0 | I30: =F30+H30 -> 0 | J30: =M30+P30+S30+V30+Y30+AB30+AE30+AH30+AK30+AN30+AQ30+AT30+AW30+AZ30+BC30+BF30+BI30+BL30+BO30+BR30+BU30+BX30+CA30+CD30+CG30+CJ30+CM30+CP30+CS30+CV30+CY30 -> 0 | M30: =ROUND(($D$30/$E$3*K30)+($D$30/$H$2*L30),0) -> 0 | P30: =ROUND(($D$30/$E$3*N30)+($D$30/$H$2*O30),0) -> 0 | S30: =ROUND(($D$30/$E$3*Q30)+($D$30/$H$2*R30),0) -> 0 | V30: =ROUND(($D$30/$E$3*T30)+($D$30/$H$2*U30),0) -> 0 | Y30: =ROUND(($D$30/$E$3*W30)+($D$30/$H$2*X30),0) -> 0 | AB30: =ROUND(($D$30/$E$3*Z30)+($D$30/$H$2*AA30),0) -> 0 | AE30: =ROUND(($D$30/$E$3*AC30)+($D$30/$H$2*AD30),0) -> 0 | AH30: =ROUND(($D$30/$E$3*AF30)+($D$30/$H$2*AG30),0) -> 0 | AK30: =ROUND(($D$30/$E$3*AI30)+($D$30/$H$2*AJ30),0) -> 0 | AN30: =ROUND(($D$30/$E$3*AL30)+($D$30/$H$2*AM30),0) -> 0 | AQ30: =ROUND(($D$30/$E$3*AO30)+($D$30/$H$2*AP30),0) -> 0 | AT30: =ROUND(($D$30/$E$3*AR30)+($D$30/$H$2*AS30),0) -> 0 | AW30: =ROUND(($D$30/$E$3*AU30)+($D$30/$H$2*AV30),0) -> 0 | AZ30: =ROUND(($D$30/$E$3*AX30)+($D$30/$H$2*AY30),0) -> 0 | BC30: =ROUND(($D$30/$E$3*BA30)+($D$30/$H$2*BB30),0) -> 0 | BF30: =ROUND(($D$30/$E$3*BD30)+($D$30/$H$2*BE30),0) -> 0 | BI30: =ROUND(($D$30/$E$3*BG30)+($D$30/$H$2*BH30),0) -> 0 | BL30: =ROUND(($D$30/$E$3*BJ30)+($D$30/$H$2*BK30),0) -> 0 | BO30: =ROUND(($D$30/$E$3*BM30)+($D$30/$H$2*BN30),0) -> 0 | BR30: =ROUND(($D$30/$E$3*BP30)+($D$30/$H$2*BQ30),0) -> 0 | BU30: =ROUND(($D$30/$E$3*BS30)+($D$30/$H$2*BT30),0) -> 0 | BX30: =ROUND(($D$30/$E$3*BV30)+($D$30/$H$2*BW30),0) -> 0 | CA30: =ROUND(($D$30/$E$3*BY30)+($D$30/$H$2*BZ30),0) -> 0 | CD30: =ROUND(($D$30/$E$3*CB30)+($D$30/$H$2*CC30),0) -> 0 | CG30: =ROUND(($D$30/$E$3*CE30)+($D$30/$H$2*CF30),0) -> 0 | CJ30: =ROUND(($D$30/$E$3*CH30)+($D$30/$H$2*CI30),0) -> 0 | CM30: =ROUND(($D$30/$E$3*CK30)+($D$30/$H$2*CL30),0) -> 0 | CP30: =ROUND(($D$30/$E$3*CN30)+($D$30/$H$2*CO30),0) -> 0 | CS30: =ROUND(($D$30/$E$3*CQ30)+($D$30/$H$2*CR30),0) -> 0 | CV30: =ROUND(($D$30/$E$3*CT30)+($D$30/$H$2*CU30),0) -> 0 | CY30: =ROUND(($D$30/$E$3*CW30)+($D$30/$H$2*CX30),0) -> 0
A31: 28 | E31: =K31+N31+Q31+T31+W31+Z31+AC31+AF31+AI31+AL31+AO31+AR31+AU31+AX31+BA31+BD31+BG31+BJ31+BM31+BP31+BS31+BV31+BY31+CB31+CE31+CH31+CK31+CN31+CQ31+CT31+CW31+CZ31 -> 0 | F31: =ROUND(D31/$F$2*E31,0) -> 0 | G31: =L31+O31+R31+U31+X31+AA31+AD31+AG31+AJ31+AM31+AP31+AS31+AV31+AY31+BB31+BE31+BH31+BK31+BN31+BQ31+BT31+BW31+BZ31+CC31+CF31+CI31+CL31+CO31+CR31+CU31+CX31+DA30 -> 0 | H31: =ROUND(D31/$H$2*G31,0) -> 0 | I31: =F31+H31 -> 0 | J31: =M31+P31+S31+V31+Y31+AB31+AE31+AH31+AK31+AN31+AQ31+AT31+AW31+AZ31+BC31+BF31+BI31+BL31+BO31+BR31+BU31+BX31+CA31+CD31+CG31+CJ31+CM31+CP31+CS31+CV31+CY31 -> 0 | M31: =ROUND(($D$31/$E$3*K31)+($D$31/$H$2*L31),0) -> 0 | P31: =ROUND(($D$31/$E$3*N31)+($D$31/$H$2*O31),0) -> 0 | S31: =ROUND(($D$31/$E$3*Q31)+($D$31/$H$2*R31),0) -> 0 | V31: =ROUND(($D$31/$E$3*T31)+($D$31/$H$2*U31),0) -> 0 | Y31: =ROUND(($D$31/$E$3*W31)+($D$31/$H$2*X31),0) -> 0 | AB31: =ROUND(($D$31/$E$3*Z31)+($D$31/$H$2*AA31),0) -> 0 | AE31: =ROUND(($D$31/$E$3*AC31)+($D$31/$H$2*AD31),0) -> 0 | AH31: =ROUND(($D$31/$E$3*AF31)+($D$31/$H$2*AG31),0) -> 0 | AK31: =ROUND(($D$31/$E$3*AI31)+($D$31/$H$2*AJ31),0) -> 0 | AN31: =ROUND(($D$31/$E$3*AL31)+($D$31/$H$2*AM31),0) -> 0 | AQ31: =ROUND(($D$31/$E$3*AO31)+($D$31/$H$2*AP31),0) -> 0 | AT31: =ROUND(($D$31/$E$3*AR31)+($D$31/$H$2*AS31),0) -> 0 | AW31: =ROUND(($D$31/$E$3*AU31)+($D$31/$H$2*AV31),0) -> 0 | AZ31: =ROUND(($D$31/$E$3*AX31)+($D$31/$H$2*AY31),0) -> 0 | BC31: =ROUND(($D$31/$E$3*BA31)+($D$31/$H$2*BB31),0) -> 0 | BF31: =ROUND(($D$31/$E$3*BD31)+($D$31/$H$2*BE31),0) -> 0 | BI31: =ROUND(($D$31/$E$3*BG31)+($D$31/$H$2*BH31),0) -> 0 | BL31: =ROUND(($D$31/$E$3*BJ31)+($D$31/$H$2*BK31),0) -> 0 | BO31: =ROUND(($D$31/$E$3*BM31)+($D$31/$H$2*BN31),0) -> 0 | BR31: =ROUND(($D$31/$E$3*BP31)+($D$31/$H$2*BQ31),0) -> 0 | BU31: =ROUND(($D$31/$E$3*BS31)+($D$31/$H$2*BT31),0) -> 0 | BX31: =ROUND(($D$31/$E$3*BV31)+($D$31/$H$2*BW31),0) -> 0 | CA31: =ROUND(($D$31/$E$3*BY31)+($D$31/$H$2*BZ31),0) -> 0 | CD31: =ROUND(($D$31/$E$3*CB31)+($D$31/$H$2*CC31),0) -> 0 | CG31: =ROUND(($D$31/$E$3*CE31)+($D$31/$H$2*CF31),0) -> 0 | CJ31: =ROUND(($D$31/$E$3*CH31)+($D$31/$H$2*CI31),0) -> 0 | CM31: =ROUND(($D$31/$E$3*CK31)+($D$31/$H$2*CL31),0) -> 0 | CP31: =ROUND(($D$31/$E$3*CN31)+($D$31/$H$2*CO31),0) -> 0 | CS31: =ROUND(($D$31/$E$3*CQ31)+($D$31/$H$2*CR31),0) -> 0 | CV31: =ROUND(($D$31/$E$3*CT31)+($D$31/$H$2*CU31),0) -> 0 | CY31: =ROUND(($D$31/$E$3*CW31)+($D$31/$H$2*CX31),0) -> 0
A32: 29 | E32: =K32+N32+Q32+T32+W32+Z32+AC32+AF32+AI32+AL32+AO32+AR32+AU32+AX32+BA32+BD32+BG32+BJ32+BM32+BP32+BS32+BV32+BY32+CB32+CE32+CH32+CK32+CN32+CQ32+CT32+CW32+CZ32 -> 0 | F32: =ROUND(D32/$F$2*E32,0) -> 0 | G32: =L32+O32+R32+U32+X32+AA32+AD32+AG32+AJ32+AM32+AP32+AS32+AV32+AY32+BB32+BE32+BH32+BK32+BN32+BQ32+BT32+BW32+BZ32+CC32+CF32+CI32+CL32+CO32+CR32+CU32+CX32+DA31 -> 0 | H32: =ROUND(D32/$H$2*G32,0) -> 0 | I32: =F32+H32 -> 0 | J32: =M32+P32+S32+V32+Y32+AB32+AE32+AH32+AK32+AN32+AQ32+AT32+AW32+AZ32+BC32+BF32+BI32+BL32+BO32+BR32+BU32+BX32+CA32+CD32+CG32+CJ32+CM32+CP32+CS32+CV32+CY32 -> 0 | M32: =ROUND(($D$32/$E$3*K32)+($D$32/$H$2*L32),0) -> 0 | P32: =ROUND(($D$32/$E$3*N32)+($D$32/$H$2*O32),0) -> 0 | S32: =ROUND(($D$32/$E$3*Q32)+($D$32/$H$2*R32),0) -> 0 | V32: =ROUND(($D$32/$E$3*T32)+($D$32/$H$2*U32),0) -> 0 | Y32: =ROUND(($D$32/$E$3*W32)+($D$32/$H$2*X32),0) -> 0 | AB32: =ROUND(($D$32/$E$3*Z32)+($D$32/$H$2*AA32),0) -> 0 | AE32: =ROUND(($D$32/$E$3*AC32)+($D$32/$H$2*AD32),0) -> 0 | AH32: =ROUND(($D$32/$E$3*AF32)+($D$32/$H$2*AG32),0) -> 0 | AK32: =ROUND(($D$32/$E$3*AI32)+($D$32/$H$2*AJ32),0) -> 0 | AN32: =ROUND(($D$32/$E$3*AL32)+($D$32/$H$2*AM32),0) -> 0 | AQ32: =ROUND(($D$32/$E$3*AO32)+($D$32/$H$2*AP32),0) -> 0 | AT32: =ROUND(($D$32/$E$3*AR32)+($D$32/$H$2*AS32),0) -> 0 | AW32: =ROUND(($D$32/$E$3*AU32)+($D$32/$H$2*AV32),0) -> 0 | AZ32: =ROUND(($D$32/$E$3*AX32)+($D$32/$H$2*AY32),0) -> 0 | BC32: =ROUND(($D$32/$E$3*BA32)+($D$32/$H$2*BB32),0) -> 0 | BF32: =ROUND(($D$32/$E$3*BD32)+($D$32/$H$2*BE32),0) -> 0 | BI32: =ROUND(($D$32/$E$3*BG32)+($D$32/$H$2*BH32),0) -> 0 | BL32: =ROUND(($D$32/$E$3*BJ32)+($D$32/$H$2*BK32),0) -> 0 | BO32: =ROUND(($D$32/$E$3*BM32)+($D$32/$H$2*BN32),0) -> 0 | BR32: =ROUND(($D$32/$E$3*BP32)+($D$32/$H$2*BQ32),0) -> 0 | BU32: =ROUND(($D$32/$E$3*BS32)+($D$32/$H$2*BT32),0) -> 0 | BX32: =ROUND(($D$32/$E$3*BV32)+($D$32/$H$2*BW32),0) -> 0 | CA32: =ROUND(($D$32/$E$3*BY32)+($D$32/$H$2*BZ32),0) -> 0 | CD32: =ROUND(($D$32/$E$3*CB32)+($D$32/$H$2*CC32),0) -> 0 | CG32: =ROUND(($D$32/$E$3*CE32)+($D$32/$H$2*CF32),0) -> 0 | CJ32: =ROUND(($D$32/$E$3*CH32)+($D$32/$H$2*CI32),0) -> 0 | CM32: =ROUND(($D$32/$E$3*CK32)+($D$32/$H$2*CL32),0) -> 0 | CP32: =ROUND(($D$32/$E$3*CN32)+($D$32/$H$2*CO32),0) -> 0 | CS32: =ROUND(($D$32/$E$3*CQ32)+($D$32/$H$2*CR32),0) -> 0 | CV32: =ROUND(($D$32/$E$3*CT32)+($D$32/$H$2*CU32),0) -> 0 | CY32: =ROUND(($D$32/$E$3*CW32)+($D$32/$H$2*CX32),0) -> 0
